Workbook
Name TariefLocaties: Locaties!$G$2:$G$15
Name NaamTarieven: Tarieven!$A$2:$A$15
Name DocentenTarieven: Docenten!$G$2:$G$15
Name Locatienaam: Locaties!$A$2:$A$15
Name Naamdocent: Docenten!$A$2:$A$15

Sheet Doel vs Werkelijkheid
A1: § | B1: Gewenst salaris | C1: Ledenaantal (werkelijk) | D1: leden aantal (verwacht) | E1: Actieve leden (verwacht) | F1: Actieve leden | G1: Omzet (werkelijk) | H1: Uitgaven (werkelijk) | I1: Percentage kosten | J1: Status | K1: Brutowinst (werkelijk) | L1: Reserveren inkomstenbelasting | M1: Nettowinst | N1: Salaris | O1: Banksaldo na salaris | P1: Belasting achterstand
A2: augustus | B2: 3000 | C2: 197 | D2: 200 | E2: 340 | F2: =Augustus!AF9 -> 390 | G2: =Augustus!$AF$3+'Extra activiteiten'!K2+Jaarbetalingen!AI3 -> 59241.19 | H2: =Augustus!$AF$5+Augustus!$AF$6 -> 4644.58 | I2: =SUM(H2/G2)*1 -> 0.078401193 | K2: =G2-H2 -> 54596.61 | L2: =IF((K2 / 1) *Inkomstenbelasting!$H$19 < 0, 0, (K2 / 1) * Inkomstenbelasting!$H$19) -> 17696.972 | M2: =K2-L2 -> 36899.638 | N2: =B2 -> 3000 | O2: =M2-N2-P2 -> 23899.638 | P2: 10000
A3: september | B3: 3250 | D3: 220 | E3: 360 | F3: =September!AF9 -> 387 | G3: =September!$AF$3+'Extra activiteiten'!K3 -> 18365.928 | H3: =September!$AF$5+September!$AF$6 -> 14419.3 | I3: =SUM(H3/G3)*1 -> 0.78511143 | K3: =G3-H3 -> 3946.628 | L3: =IF((K3 / 1) *Inkomstenbelasting!$H$19 < 0, 0, (K3 / 1) * Inkomstenbelasting!$H$19) -> 1279.2619 | M3: =K3-L3 -> 2667.3661 | N3: =B3 -> 3250 | O3: =(O2+M3)-N3-P3 -> 23317.004
A4: oktober | B4: 3250 | D4: 230 | E4: 370 | F4: =Oktober!AF9 -> 395 | G4: =Oktober!$AF$3+'Extra activiteiten'!K4 -> 7428.878 | H4: =Oktober!$AF$5+Oktober!$AF$6 -> 8730.34 | I4: =SUM(H4/G4)*1 -> 1.1751896 | K4: =G4-H4 -> -1301.462 | L4: =IF((K4 / 1) *Inkomstenbelasting!$H$19 < 0, 0, (K4 / 1) * Inkomstenbelasting!$H$19) -> 0 | M4: =K4-L4 -> -1301.462 | N4: =B4 -> 3250 | O4: =(O3+M4)-N4-P4 -> 9638.5421 | P4: 9127
A5: november | B5: 3250 | D5: 240 | E5: 380 | F5: =November!AF9 -> 423 | G5: =November!$AF$3+'Extra activiteiten'!K5 -> 7399.3537 | H5: =November!$AF$5+November!$AF$6 -> 7159.92 | I5: =SUM(H5/G5)*1 -> 0.96764127 | K5: =G5-H5 -> 239.43367 | L5: =IF((K5 / 1) *Inkomstenbelasting!$H$19 < 0, 0, (K5 / 1) * Inkomstenbelasting!$H$19) -> 77.610146 | M5: =K5-L5 -> 161.82352 | N5: =B5 -> 3250 | O5: =(O4+M5)-N5-P5 -> 6550.3656
A6: december | B6: 3250 | D6: 245 | E6: 385 | F6: =December!AF9 -> 411 | G6: =December!$AF$3+'Extra activiteiten'!K6 -> 16530.104 | H6: =December!$AF$5+December!$AF$6 -> 7754.54 | I6: =SUM(H6/G6)*1 -> 0.46911624 | K6: =G6-H6 -> 8775.5637 | L6: =IF((K6 / 1) *Inkomstenbelasting!$H$19 < 0, 0, (K6 / 1) * Inkomstenbelasting!$H$19) -> 2844.5155 | M6: =K6-L6 -> 5931.0482 | N6: =B6 -> 3250 | O6: =(O5+M6)-N6-P6 -> 9231.4138
A7: januari | B7: 3250 | D7: 250 | E7: 390 | F7: =Januari!AF9 -> 459 | G7: =Januari!$AF$3+'Extra activiteiten'!K7 -> 10154.22 | H7: =Januari!$AF$5+Januari!$AF$6 -> 10118.52 | I7: =SUM(H7/G7)*1 -> 0.99648419 | K7: =G7-H7 -> 35.700333 | L7: =IF((K7 / 1) *Inkomstenbelasting!$H$19 < 0, 0, (K7 / 1) * Inkomstenbelasting!$H$19) -> 11.571924 | M7: =K7-L7 -> 24.12841 | N7: =B7 -> 3250 | O7: =(O6+M7)-N7-P7 -> 6005.5422
A8: februari | B8: 3250 | D8: 260 | E8: 400 | F8: =Februari!AF9 -> 465 | G8: =Februari!$AF$3+'Extra activiteiten'!K8 -> 8500.4203 | H8: =Februari!$AF$5+Februari!$AF$6 -> 7697.52 | I8: =SUM(H8/G8)*1 -> 0.90554581 | K8: =G8-H8 -> 802.90033 | L8: =IF((K8 / 1) *Inkomstenbelasting!$H$19 < 0, 0, (K8 / 1) * Inkomstenbelasting!$H$19) -> 260.25251 | M8: =K8-L8 -> 542.64783 | N8: =B8 -> 3250 | O8: =(O7+M8)-N8-P8 -> 3298.19
A9: maart | B9: 3250 | D9: 280 | E9: 420 | F9: =Maart!AF9 -> 468 | G9: =Maart!$AF$3+'Extra activiteiten'!K9 -> 10556.35 | H9: =Maart!$AF$5+Maart!$AF$6 -> 11061.67 | I9: =SUM(H9/G9)*1 -> 1.0478688 | K9: =G9-H9 -> -505.31967 | L9: =IF((K9 / 1) *Inkomstenbelasting!$H$19 < 0, 0, (K9 / 1) * Inkomstenbelasting!$H$19) -> 0 | M9: =K9-L9 -> -505.31967 | N9: =B9 -> 3250 | O9: =(O8+M9)-N9-P9 -> -457.12964
A10: april | B10: 3250 | D10: 287 | E10: 427 | F10: =April!AF9 -> 468 | G10: =April!$AF$3+'Extra activiteiten'!K10 -> 8648.3503 | H10: =April!$AF$5+April!$AF$6 -> 6342.34 | I10: =SUM(H10/G10)*1 -> 0.73335836 | K10: =G10-H10 -> 2306.0103 | L10: =IF((K10 / 1) *Inkomstenbelasting!$H$19 < 0, 0, (K10 / 1) * Inkomstenbelasting!$H$19) -> 747.47132 | M10: =K10-L10 -> 1558.539 | N10: =B10 -> 3250 | O10: =(O9+M10)-N10-P10 -> -2148.5906
A11: mei | B11: 3250 | D11: 287 | E11: 427 | F11: =Mei!AF9 -> 461 | G11: =Mei!$AF$3+'Extra activiteiten'!K11 -> 49171.35 | H11: =Mei!$AF$5+Mei!$AF$6 -> 31658.94 | I11: =SUM(H11/G11)*1 -> 0.64384931 | K11: =G11-H11 -> 17512.41 | L11: =IF((K11 / 1) *Inkomstenbelasting!$H$19 < 0, 0, (K11 / 1) * Inkomstenbelasting!$H$19) -> 5676.4813 | M11: =K11-L11 -> 11835.929 | N11: =B11 -> 3250 | O11: =(O10+M11)-N11-P11 -> 6437.3384
A12: juni | B12: 3250 | D12: 295 | E12: 435 | F12: =Juni!AF9 -> 461 | G12: =Juni!$AF$3+'Extra activiteiten'!K12 -> 8713.8503 | H12: =Juni!$AF$5+Juni!$AF$6 -> 6642.78 | I12: =SUM(H12/G12)*1 -> 0.76232432 | K12: =G12-H12 -> 2071.0703 | L12: =IF((K12 / 1) *Inkomstenbelasting!$H$19 < 0, 0, (K12 / 1) * Inkomstenbelasting!$H$19) -> 671.31775 | M12: =K12-L12 -> 1399.7526 | N12: =B12 -> 3250 | O12: =(O11+M12)-N12-P12 -> 4587.091
A13: juli | B13: 3250 | F13: =Juli!AF9 -> 461 | G13: =Juli!$AF$3+'Extra activiteiten'!K13 -> 400 | H13: =Juli!$AF$5+Juli!$AF$6 -> 2424.99 | I13: =SUM(H13/G13)*1 -> 6.062475 | K13: =G13-H13 -> -2024.99 | L13: =IF((K13 / 1) *Inkomstenbelasting!$H$19 < 0, 0, (K13 / 1) * Inkomstenbelasting!$H$19) -> 0 | M13: =K13-L13 -> -2024.99 | N13: =B13 -> 3250 | O13: =(O12+M13)-N13-P13 -> -687.89899
A14: Totaal: | B14: =SUM(B2:B13) -> 38750 | F14: =September!AF20 | G14: =SUM(G2:G13) -> 205110 | H14: =SUM(H2:H13) -> 118655.44 | I14: =SUM(H14/G14)*1 -> 0.57849662 | K14: =SUM(K2:K13) -> 86454.555 | L14: =SUM(L2:L13) -> 29265.454 | M14: =SUM(M2:M13) -> 57189.101 | N14: =SUM(N2:N13) -> 38750 | O14: =C14 | P14: =SUM(P2:P13) -> 19127
E16: Worst | F16: 0.18 | G16: 403.56
B17: bijgewerkt: 17 feb | E17: Beter | F17: 0.234 | G17: 422.028
B18: Zoey wassenaar | E18: Best | F18: 0.3 | G18: 444.6
B19: Drukzo 99,60

Sheet Docenten
A1: Naam docent | B1: Aantal uren per week | C1: Uurloon | D1: Reiskosten per week | E1: Niveau docent | F1: Datum indiensttreding | G1: Daadwerkelijk uurtarief
A2: Eigenaar | B2: 13 | C2: 0 | D2: 0 | E2: Ervaren | F2: 44197 | G2: =(C2*B2+D2)/B2 -> 0
A3: Nova | B3: 8 | C3: 22.5 | D3: 0 | E3: Ervaren | F3: 45170 | G3: =(C3*B3+D3)/B3 -> 22.5
A4: Frederique | B4: 5 | C4: 12.5 | D4: 0 | E4: Starter | F4: 45536 | G4: =(C4*B4+D4)/B4 -> 12.5
A5: Julia | B5: 5 | C5: 15 | D5: 0 | E5: Starter | F5: 45536 | G5: =(C5*B5+D5)/B5 -> 15
A6: Lotte | B6: 2 | C6: 22.5 | D6: 0 | E6: Ervaren | F6: 45901 | G6: =(C6*B6+D6)/B6 -> 22.5
A7: Bianca | B7: 3 | C7: 20 | D7: 0 | E7: Gemiddeld | F7: 45901 | G7: =(C7*B7+D7)/B7 -> 20
A8: Tess | B8: 2 | C8: 17.5 | D8: 0 | E8: Starter | F8: 45901 | G8: =(C8*B8+D8)/B8 -> 17.5
A9: Opvang T | B9: 1 | C9: 45 | D9: 0 | E9: Inval docent | F9: 45901 | G9: =(C9*B9+D9)/B9 -> 45
A10: Fre + 2 | B10: 1 | C10: 18 | D10: 0 | E10: Starter | G10: =(C10*B10+D10)/B10 -> 18
A11: Fre +1 | B11: 1 | C11: 5.5 | D11: 0 | E11: Starter | G11: =(C11*B11+D11)/B11 -> 5.5
A12: Tess +1 | B12: 1 | C12: 21.5 | D12: 0 | E12: Gemiddeld | G12: =(C12*B12+D12)/B12 -> 21.5
A13: Ilja + 1 | B13: 1 | C13: 3.50 | D13: 0 | E13: Ervaren | G13: =(C13*B13+D13)/B13 -> #VALUE!
A14: Dion + 3 | B14: 2 | C14: 34 | D14: 0 | E14: Ervaren | G14: =(C14*B14+D14)/B14 -> 34
G15: =(C15*B15+D15)/B15 -> #DIV/0!
G16: =(C16*B16+D16)/B16 -> #DIV/0!
G17: =(C17*B17+D17)/B17 -> #DIV/0!
G18: =(C18*B18+D18)/B18 -> #DIV/0!
G19: =(C19*B19+D19)/B19 -> #DIV/0!
G20: =(C20*B20+D20)/B20 -> #DIV/0!
G21: =(C21*B21+D21)/B21 -> #DIV/0!
G22: =(C22*B22+D22)/B22 -> #DIV/0!
G23: =(C23*B23+D23)/B23 -> #DIV/0!
G24: =(C24*B24+D24)/B24 -> #DIV/0!
G25: =(C25*B25+D25)/B25 -> #DIV/0!
G26: =(C26*B26+D26)/B26 -> #DIV/0!
... G30: =(C30*B30+D30)/B30 -> #DIV/0!

Sheet Locaties
A1: Naam locatie | B1: Uurtarief | C1: Aantal uren per week | D1: Lesweken per jaar | E1: Bijkomende jaarlijkse kosten | F1: Opmerkingen | G1: Daadwerkelijk Uurtarief
A2: Santpoort Noord | B2: 14.2 | C2: 15 | D2: 36 | E2: 0 | G2: =(E2/D2/C2)+B2 -> 14.2
A3: Santpoort Zuid | B3: 18.9 | C3: 18 | D3: 36 | E3: 0 | G3: =(E3/D3/C3)+B3 -> 18.9
G4: =(E4/D4/C4)+B4 -> #DIV/0!
G5: =(E5/D5/C5)+B5 -> #DIV/0!
G6: =(E6/D6/C6)+B6 -> #DIV/0!
G7: =(E7/D7/C7)+B7 -> #DIV/0!
G8: =(E8/D8/C8)+B8 -> #DIV/0!
G9: =(E9/D9/C9)+B9 -> #DIV/0!
G10: =(E10/D10/C10)+B10 -> #DIV/0!
G11: =(E11/D11/C11)+B11 -> #DIV/0!
G12: =(E12/D12/C12)+B12 -> #DIV/0!
G13: =(E13/D13/C13)+B13 -> #DIV/0!
G14: =(E14/D14/C14)+B14 -> #DIV/0!
G15: =(E15/D15/C15)+B15 -> #DIV/0!

Sheet Tarieven
A1: Naam lidmaatschap | B1: Tarief per jaar | C1: Aantal keer per week | D1: Betaal termijnen | E1: Leeftijd | F1: BTW tarief % | G1: BTW Bedrag | H1: Netto tarief | I1: Per termijn (excl btw) | J1: Tarief per les/per termijn (excl btw)
A2: Geen betaling | B2: 0 | C2: 1 | D2: 1 | F2: 0 | G2: =B2 / 1 * M2 -> 0 | H2: =B2-G2 -> 0 | I2: =H2/D2 -> 0 | J2: =I2/C2 -> 0 | M2: =F2 -> 0
A3: Aangepast tarief | C3: 1 | D3: 1 | F3: 0 | G3: =B3 / 1 * M3 -> 0 | H3: =B3-G3 -> 0 | I3: =H3/D3 -> 0 | J3: =I3/C3 -> 0 | M3: =F3 -> 0
A4: 1x per week | B4: 279 | C4: 1 | D4: 1 | E4: tot 18 jaar | F4: 0 | G4: =B4 / 1 * M4 -> 0 | H4: =B4-G4 -> 279 | I4: =H4/D4 -> 279 | J4: =I4/C4 -> 279 | M4: =F4 -> 0
A5: 1x per week abbo | B5: 310 | C5: 1 | D5: 10 | E5: tot 18 jaar | F5: 0 | G5: =B5 / 1 * M5 -> 0 | H5: =B5-G5 -> 310 | I5: =H5/D5 -> 31 | J5: =I5/C5 -> 31 | M5: =F5 -> 0
A6: 2x per week | B6: 558 | C6: 2 | D6: 1 | E6: tot 18 jaar | F6: 0 | G6: =B6 / 1 * M6 -> 0 | H6: =B6-G6 -> 558 | I6: =H6/D6 -> 558 | J6: =I6/C6 -> 279 | M6: =F6 -> 0
A7: 2x per week abbo | B7: 571 | C7: 2 | D7: 10 | E7: tot 18 jaar | F7: 0 | G7: =B7 / 1 * M7 -> 0 | H7: =B7-G7 -> 571 | I7: =H7/D7 -> 57.1 | J7: =I7/C7 -> 28.55 | M7: =F7 -> 0
A8: 3x per week | B8: 837 | C8: 3 | D8: 1 | E8: tot 18 jaar | F8: 0 | G8: =B8 / 1 * M8 -> 0 | H8: =B8-G8 -> 837 | I8: =H8/D8 -> 837 | J8: =I8/C8 -> 279 | M8: =F8 -> 0
A9: 3x per week abbo | B9: 868 | C9: 3 | D9: 10 | E9: tot 18 jaar | F9: 0 | G9: =B9 / 1 * M9 -> 0 | H9: =B9-G9 -> 868 | I9: =H9/D9 -> 86.8 | J9: =I9/C9 -> 28.933333 | M9: =F9 -> 0
A10: Onbeperkt | B10: 1054.5 | C10: 4 | D10: 1 | E10: tot 18 jaar | F10: 0 | G10: =B10 / 1 * M10 -> 0 | H10: =B10-G10 -> 1054.5 | I10: =H10/D10 -> 1054.5 | J10: =I10/C10 -> 263.625 | M10: =F10 -> 0
A11: Onbeperkt abbo | B11: 1080 | C11: 4 | D11: 10 | E11: tot 18 jaar | F11: 0 | G11: =B11 / 1 * M11 -> 0 | H11: =B11-G11 -> 1080 | I11: =H11/D11 -> 108 | J11: =I11/C11 -> 27 | M11: =F11 -> 0
A12: Cheer regulier | B12: 300 | C12: 1 | D12: 1 | E12: tot 18 jaar | F12: 0 | G12: =B12 / 1 * M12 -> 0 | H12: =B12-G12 -> 300 | I12: =H12/D12 -> 300 | J12: =I12/C12 -> 300 | M12: =F12 -> 0
A13: Cheer regulier abbo | B13: 335 | C13: 1 | D13: 10 | E13: tot 18 jaar | F13: 0 | G13: =B13 / 1 * M13 -> 0 | H13: =B13-G13 -> 335 | I13: =H13/D13 -> 33.5 | J13: =I13/C13 -> 33.5 | M13: =F13 -> 0
A14: Cheer regulier +1 | B14: 579 | C14: 2 | D14: 1 | E14: tot 18 | F14: 0 | G14: =B14 / 1 * M14 -> 0 | H14: =B14-G14 -> 579 | I14: =H14/D14 -> 579 | J14: =I14/C14 -> 289.5 | M14: =F14 -> 0
A15: Cheer regulier +1 abbo | B15: 645 | C15: 2 | D15: 10 | E15: tot 18 | F15: 0 | G15: =B15 / 1 * M15 -> 0 | H15: =B15-G15 -> 645 | I15: =H15/D15 -> 64.5 | J15: =I15/C15 -> 32.25 | M15: =F15 -> 0
... A30: Jeugdfonds | B30: 261 | C30: 1 | D30: 1 | E30: tot 18 | F30: 0 | G30: =B30 / 1 * M30 -> 0 | H30: =B30-G30 -> 261 | I30: =H30/D30 -> 261 | J30: =I30/C30 -> 261 | M30: =F30 -> 0
A31: Cheer regulier + onbeperkt | B31: 1147 | C31: 4 | D31: 1 | F31: 0 | G31: =B31 / 1 * M31 -> 0 | H31: =B31-G31 -> 1147 | I31: =H31/D31 -> 1147 | J31: =I31/C31 -> 286.75 | M31: =F31 -> 0
A32: Cheer regulier + onbeperkt abbo | B32: 1778 | C32: 4 | D32: 10 | F32: 0 | G32: =B32 / 1 * M32 -> 0 | H32: =B32-G32 -> 1778 | I32: =H32/D32 -> 177.8 | J32: =I32/C32 -> 44.45 | M32: =F32 -> 0
G33: =B33 / 1 * M33 -> 0 | H33: =B33-G33 -> 0 | I33: =H33/D33 -> #DIV/0! | J33: =I33/C33 -> #DIV/0! | M33: =F33
G34: =B34 / 1 * M34 -> 0 | H34: =B34-G34 -> 0 | I34: =H34/D34 -> #DIV/0! | J34: =I34/C34 -> #DIV/0! | M34: =F34
G35: =B35 / 1 * M35 -> 0 | H35: =B35-G35 -> 0 | I35: =H35/D35 -> #DIV/0! | J35: =I35/C35 -> #DIV/0! | M35: =F35
G36: =B36 / 1 * M36 -> 0 | H36: =B36-G36 -> 0 | I36: =H36/D36 -> #DIV/0! | J36: =I36/C36 -> #DIV/0! | M36: =F36
G37: =B37 / 1 * M37 -> 0 | H37: =B37-G37 -> 0 | I37: =H37/D37 -> #DIV/0! | J37: =I37/C37 -> #DIV/0! | M37: =F37
G38: =B38 / 1 * M38 -> 0 | H38: =B38-G38 -> 0 | I38: =H38/D38 -> #DIV/0! | J38: =I38/C38 -> #DIV/0! | M38: =F38
G39: =B39 / 1 * M39 -> 0 | H39: =B39-G39 -> 0 | I39: =H39/D39 -> #DIV/0! | J39: =I39/C39 -> #DIV/0! | M39: =F39
G40: =B40 / 1 * M40 -> 0 | H40: =B40-G40 -> 0 | I40: =H40/D40 -> #DIV/0! | J40: =I40/C40 -> #DIV/0! | M40: =F40
G41: =B41 / 1 * M41 -> 0 | H41: =B41-G41 -> 0 | I41: =H41/D41 -> #DIV/0! | J41: =I41/C41 -> #DIV/0! | M41: =F41
G42: =B42 / 1 * M42 -> 0 | H42: =B42-G42 -> 0 | I42: =H42/D42 -> #DIV/0! | J42: =I42/C42 -> #DIV/0! | M42: =F42
G43: =B43 / 1 * M43 -> 0 | H43: =B43-G43 -> 0 | I43: =H43/D43 -> #DIV/0! | J43: =I43/C43 -> #DIV/0! | M43: =F43
G44: =B44 / 1 * M44 -> 0 | H44: =B44-G44 -> 0 | I44: =H44/D44 -> #DIV/0! | J44: =I44/C44 -> #DIV/0! | M44: =F44
... G150: =B150 / 1 * M150 -> 0 | H150: =B150-G150 -> 0 | I150: =H150/D150 -> #DIV/0! | J150: =I150/C150 -> #DIV/0! | M150: =F150

Sheet Rooster
A2: Lesdag | B2: Lestijd | C2: Aantal minuten les | D2: Naam les | E2: Docent | F2: Tarief docent | G2: Tarief docent voor deze les | H2: Locatie | I2: Zaalhuur per uur | J2: Zaalhuur per les
F3: =IFERROR(VLOOKUP(E3, Docenten!$A$2:$G$30, 7, FALSE), "0") -> 0 | G3: =SUM(F3/60)*C3 -> 0 | I3: =IFERROR(VLOOKUP(H3, Locaties!$A$2:$G$15, 7, FALSE), "0") -> 0 | J3: =SUM(I3/60)*C3 -> 0
F4: =IFERROR(VLOOKUP(E4, Docenten!$A$2:$G$30, 7, FALSE), "0") -> 0 | G4: =SUM(F4/60)*C4 -> 0 | I4: =IFERROR(VLOOKUP(H4, Locaties!$A$2:$G$15, 7, FALSE), "0") -> 0 | J4: =SUM(I4/60)*C4 -> 0
A5: Maandag | B5: 0.625 | C5: 60 | D5: Kleuterdans | E5: Lotte | F5: =IFERROR(VLOOKUP(E5, Docenten!$A$2:$G$30, 7, FALSE), "0") -> 22.5 | G5: =SUM(F5/60)*C5 -> 22.5 | H5: Santpoort Zuid | I5: =IFERROR(VLOOKUP(H5, Locaties!$A$2:$G$15, 7, FALSE), "0") -> 18.9 | J5: =SUM(I5/60)*C5 -> 18.9
A6: Maandag | B6: 0.625 | C6: 60 | D6: Streetdance 6+ | E6: Lotte | F6: =IFERROR(VLOOKUP(E6, Docenten!$A$2:$G$30, 7, FALSE), "0") -> 22.5 | G6: =SUM(F6/60)*C6 -> 22.5 | H6: Santpoort Zuid | I6: =IFERROR(VLOOKUP(H6, Locaties!$A$2:$G$15, 7, FALSE), "0") -> 18.9 | J6: =SUM(I6/60)*C6 -> 18.9
A7: Maandag | B7: 0.66666667 | C7: 60 | D7: Urban-Pop-Show 10+ | E7: Lotte | F7: =IFERROR(VLOOKUP(E7, Docenten!$A$2:$G$30, 7, FALSE), "0") -> 22.5 | G7: =SUM(F7/60)*C7 -> 22.5 | H7: Santpoort Zuid | I7: =IFERROR(VLOOKUP(H7, Locaties!$A$2:$G$15, 7, FALSE), "0") -> 18.9 | J7: =SUM(I7/60)*C7 -> 18.9
A8: Maandag | B8: 0.70833333 | C8: 60 | D8: Urban-Pop-Show 12+ | E8: Nova | F8: =IFERROR(VLOOKUP(E8, Docenten!$A$2:$G$30, 7, FALSE), "0") -> 22.5 | G8: =SUM(F8/60)*C8 -> 22.5 | H8: Santpoort Zuid | I8: =IFERROR(VLOOKUP(H8, Locaties!$A$2:$G$15, 7, FALSE), "0") -> 18.9 | J8: =SUM(I8/60)*C8 -> 18.9
A9: Maandag | B9: 0.75 | C9: 60 | D9: Selectie Show | E9: Nova | F9: =IFERROR(VLOOKUP(E9, Docenten!$A$2:$G$30, 7, FALSE), "0") -> 22.5 | G9: =SUM(F9/60)*C9 -> 22.5 | H9: Santpoort Zuid | I9: =IFERROR(VLOOKUP(H9, Locaties!$A$2:$G$15, 7, FALSE), "0") -> 18.9 | J9: =SUM(I9/60)*C9 -> 18.9
A10: Maandag | B10: 0.79166667 | C10: 60 | D10: Commercial 16+ | E10: Nova | F10: =IFERROR(VLOOKUP(E10, Docenten!$A$2:$G$30, 7, FALSE), "0") -> 22.5 | G10: =SUM(F10/60)*C10 -> 22.5 | H10: Santpoort Zuid | I10: =IFERROR(VLOOKUP(H10, Locaties!$A$2:$G$15, 7, FALSE), "0") -> 18.9 | J10: =SUM(I10/60)*C10 -> 18.9
A11: Maandag | B11: 0.83333333 | C11: 60 | D11: Commercial 20+ | E11: Nova | F11: =IFERROR(VLOOKUP(E11, Docenten!$A$2:$G$30, 7, FALSE), "0") -> 22.5 | G11: =SUM(F11/60)*C11 -> 22.5 | H11: Santpoort Zuid | I11: =IFERROR(VLOOKUP(H11, Locaties!$A$2:$G$15, 7, FALSE), "0") -> 18.9 | J11: =SUM(I11/60)*C11 -> 18.9
A12: Maandag | B12: 0.875 | C12: 60 | D12: Jazz 20+ | E12: Nova | F12: =IFERROR(VLOOKUP(E12, Docenten!$A$2:$G$30, 7, FALSE), "0") -> 22.5 | G12: =SUM(F12/60)*C12 -> 22.5 | H12: Santpoort Zuid | I12: =IFERROR(VLOOKUP(H12, Locaties!$A$2:$G$15, 7, FALSE), "0") -> 18.9 | J12: =SUM(I12/60)*C12 -> 18.9
A13: Maandag | B13: 0.66666667 | C13: 60 | D13: Streetdance 6+ | E13: Julia | F13: =IFERROR(VLOOKUP(E13, Docenten!$A$2:$G$30, 7, FALSE), "0") -> 15 | G13: =SUM(F13/60)*C13 -> 15 | H13: Santpoort Noord | I13: =IFERROR(VLOOKUP(H13, Locaties!$A$2:$G$15, 7, FALSE), "0") -> 14.2 | J13: =SUM(I13/60)*C13 -> 14.2
A14: Maandag | B14: 0.70833333 | C14: 60 | D14: Streetdance 8+ | E14: Julia | F14: =IFERROR(VLOOKUP(E14, Docenten!$A$2:$G$30, 7, FALSE), "0") -> 15 | G14: =SUM(F14/60)*C14 -> 15 | H14: Santpoort Noord | I14: =IFERROR(VLOOKUP(H14, Locaties!$A$2:$G$15, 7, FALSE), "0") -> 14.2 | J14: =SUM(I14/60)*C14 -> 14.2
A15: Dinsdag | B15: 0.66666667 | C15: 60 | D15: Modern 8+ | E15: Eigenaar | F15: =IFERROR(VLOOKUP(E15, Docenten!$A$2:$G$30, 7, FALSE), "0") -> 0 | G15: =SUM(F15/60)*C15 -> 0 | H15: Santpoort Zuid | I15: =IFERROR(VLOOKUP(H15, Locaties!$A$2:$G$15, 7, FALSE), "0") -> 18.9 | J15: =SUM(I15/60)*C15 -> 18.9
A16: Dinsdag | B16: 0.70833333 | C16: 60 | D16: Selectie show 8+ | E16: Eigenaar | F16: =IFERROR(VLOOKUP(E16, Docenten!$A$2:$G$30, 7, FALSE), "0") -> 0 | G16: =SUM(F16/60)*C16 -> 0 | H16: Santpoort Zuid | I16: =IFERROR(VLOOKUP(H16, Locaties!$A$2:$G$15, 7, FALSE), "0") -> 18.9 | J16: =SUM(I16/60)*C16 -> 18.9
... A23: Woensdag | B23: 0.77083333 | C23: 60 | D23: Show 12+ | E23: Eigenaar | F23: =IFERROR(VLOOKUP(E23, Docenten!$A$2:$G$30, 7, FALSE), "0") -> 0 | G23: =SUM(F23/60)*C23 -> 0 | H23: Santpoort Noord | I23: =IFERROR(VLOOKUP(H23, Locaties!$A$2:$G$15, 7, FALSE), "0") -> 14.2 | J23: =SUM(I23/60)*C23 -> 14.2
I24: =IFERROR(VLOOKUP(H24, Locaties!$A$2:$G$15, 7, FALSE), "0") -> 0 | J24: =SUM(I24/60)*C24 -> 0
A25: Donderdag | B25: 0.64583333 | C25: 60 | D25: Showdance 6+ | E25: Eigenaar | F25: =IFERROR(VLOOKUP(E25, Docenten!$A$2:$G$30, 7, FALSE), "0") -> 0 | G25: =SUM(F25/60)*C25 -> 0 | H25: Santpoort Zuid | I25: =IFERROR(VLOOKUP(H25, Locaties!$A$2:$G$15, 7, FALSE), "0") -> 18.9 | J25: =SUM(I25/60)*C25 -> 18.9
A26: Donderdag | B26: 0.6875 | C26: 60 | D26: Showdance 8+ | E26: Eigenaar | F26: =IFERROR(VLOOKUP(E26, Docenten!$A$2:$G$30, 7, FALSE), "0") -> 0 | G26: =SUM(F26/60)*C26 -> 0 | H26: Santpoort Zuid | I26: =IFERROR(VLOOKUP(H26, Locaties!$A$2:$G$15, 7, FALSE), "0") -> 18.9 | J26: =SUM(I26/60)*C26 -> 18.9
A27: Donderdag | B27: 0.72916667 | C27: 60 | D27: Modern 14+ | E27: Eigenaar | F27: =IFERROR(VLOOKUP(E27, Docenten!$A$2:$G$30, 7, FALSE), "0") -> 0 | G27: =SUM(F27/60)*C27 -> 0 | H27: Santpoort Zuid | I27: =IFERROR(VLOOKUP(H27, Locaties!$A$2:$G$15, 7, FALSE), "0") -> 18.9 | J27: =SUM(I27/60)*C27 -> 18.9
A28: Donderdag | B28: 0.77083333 | C28: 60 | D28: Commercial 14+ | E28: Nova | F28: =IFERROR(VLOOKUP(E28, Docenten!$A$2:$G$30, 7, FALSE), "0") -> 22.5 | G28: =SUM(F28/60)*C28 -> 22.5 | H28: Santpoort Zuid | I28: =IFERROR(VLOOKUP(H28, Locaties!$A$2:$G$15, 7, FALSE), "0") -> 18.9 | J28: =SUM(I28/60)*C28 -> 18.9
A29: Donderdag | B29: 0.8125 | C29: 60 | D29: Selectie Hiphop 16+ | E29: Nova | F29: =IFERROR(VLOOKUP(E29, Docenten!$A$2:$G$30, 7, FALSE), "0") -> 22.5 | G29: =SUM(F29/60)*C29 -> 22.5 | H29: Santpoort Zuid | I29: =IFERROR(VLOOKUP(H29, Locaties!$A$2:$G$15, 7, FALSE), "0") -> 18.9 | J29: =SUM(I29/60)*C29 -> 18.9
A30: Donderdag | B30: 0.85416667 | C30: 60 | D30: Modern 16+ | E30: Nova | F30: =IFERROR(VLOOKUP(E30, Docenten!$A$2:$G$30, 7, FALSE), "0") -> 22.5 | G30: =SUM(F30/60)*C30 -> 22.5 | H30: Santpoort Zuid | I30: =IFERROR(VLOOKUP(H30, Locaties!$A$2:$G$15, 7, FALSE), "0") -> 18.9 | J30: =SUM(I30/60)*C30 -> 18.9
A31: Vrijdag | B31: 0.625 | C31: 60 | D31: Selectie Hiphop 8+ | E31: Eigenaar | F31: =IFERROR(VLOOKUP(E31, Docenten!$A$2:$G$30, 7, FALSE), "0") -> 0 | G31: =SUM(F31/60)*C31 -> 0 | H31: Santpoort Zuid | I31: =IFERROR(VLOOKUP(H31, Locaties!$A$2:$G$15, 7, FALSE), "0") -> 18.9 | J31: =SUM(I31/60)*C31 -> 18.9
A32: Vrijdag | B32: 0.66666667 | C32: 60 | D32: Cheer 8+ | E32: Eigenaar | F32: =IFERROR(VLOOKUP(E32, Docenten!$A$2:$G$30, 7, FALSE), "0") -> 0 | G32: =SUM(F32/60)*C32 -> 0 | H32: Santpoort Zuid | I32: =IFERROR(VLOOKUP(H32, Locaties!$A$2:$G$15, 7, FALSE), "0") -> 18.9 | J32: =SUM(I32/60)*C32 -> 18.9
A33: Vrijdag | B33: 0.70833333 | C33: 60 | D33: Cheer 12+ | E33: Eigenaar | F33: =IFERROR(VLOOKUP(E33, Docenten!$A$2:$G$30, 7, FALSE), "0") -> 0 | G33: =SUM(F33/60)*C33 -> 0 | H33: Santpoort Zuid | I33: =IFERROR(VLOOKUP(H33, Locaties!$A$2:$G$15, 7, FALSE), "0") -> 18.9 | J33: =SUM(I33/60)*C33 -> 18.9
A34: Vrijdag | B34: 0.75 | C34: 60 | D34: Urban-pop-Show 11+ | E34: Eigenaar | F34: =IFERROR(VLOOKUP(E34, Docenten!$A$2:$G$30, 7, FALSE), "0") -> 0 | G34: =SUM(F34/60)*C34 -> 0 | H34: Santpoort Noord | I34: =IFERROR(VLOOKUP(H34, Locaties!$A$2:$G$15, 7, FALSE), "0") -> 14.2 | J34: =SUM(I34/60)*C34 -> 14.2
A35: Zaterdag | B35: 0.375 | C35: 60 | D35: Peuters | E35: Frederique | F35: =IFERROR(VLOOKUP(E35, Docenten!$A$2:$G$30, 7, FALSE), "0") -> 12.5 | G35: =SUM(F35/60)*C35 -> 12.5 | H35: Santpoort Noord | I35: =IFERROR(VLOOKUP(H35, Locaties!$A$2:$G$15, 7, FALSE), "0") -> 14.2 | J35: =SUM(I35/60)*C35 -> 14.2
A36: Zaterdag | B36: 0.40625 | C36: 60 | D36: Kleuters | E36: Frederique | F36: =IFERROR(VLOOKUP(E36, Docenten!$A$2:$G$30, 7, FALSE), "0") -> 12.5 | G36: =SUM(F36/60)*C36 -> 12.5 | H36: Santpoort Noord | I36: =IFERROR(VLOOKUP(H36, Locaties!$A$2:$G$15, 7, FALSE), "0") -> 14.2 | J36: =SUM(I36/60)*C36 -> 14.2
... A40: Zaterdag | B40: 0.44791667 | C40: 60 | D40: Kleuters | E40: Tess | F40: =IFERROR(VLOOKUP(E40, Docenten!$A$2:$G$30, 7, FALSE), "0") -> 17.5 | G40: =SUM(F40/60)*C40 -> 17.5 | H40: Santpoort Zuid | I40: =IFERROR(VLOOKUP(H40, Locaties!$A$2:$G$15, 7, FALSE), "0") -> 18.9 | J40: =SUM(I40/60)*C40 -> 18.9
F41: =IFERROR(VLOOKUP(E41, Docenten!$A$2:$G$30, 7, FALSE), "0") -> 0 | G41: =SUM(F41/60)*C41 -> 0 | I41: =IFERROR(VLOOKUP(H41, Locaties!$A$2:$G$15, 7, FALSE), "0") -> 0 | J41: =SUM(I41/60)*C41 -> 0
F42: =IFERROR(VLOOKUP(E42, Docenten!$A$2:$G$30, 7, FALSE), "0") -> 0 | G42: =SUM(F42/60)*C42 -> 0 | I42: =IFERROR(VLOOKUP(H42, Locaties!$A$2:$G$15, 7, FALSE), "0") -> 0 | J42: =SUM(I42/60)*C42 -> 0
A43: Maandag | B43: 0.39583333 | C43: 60 | D43: Kinderopvang | E43: Opvang T | F43: =IFERROR(VLOOKUP(E43, Docenten!$A$2:$G$30, 7, FALSE), "0") -> 45 | G43: =SUM(F43/60)*C43 -> 45 | I43: =IFERROR(VLOOKUP(H43, Locaties!$A$2:$G$15, 7, FALSE), "0") -> 0 | J43: =SUM(I43/60)*C43 -> 0
A44: Vrijdag | B44: 0.79166667 | C44: 0.83333333 | D44: Prive training | E44: Eigenaar | F44: =IFERROR(VLOOKUP(E44, Docenten!$A$2:$G$30, 7, FALSE), "0") -> 0 | G44: =SUM(F44/60)*C44 -> 0 | I44: =IFERROR(VLOOKUP(H44, Locaties!$A$2:$G$15, 7, FALSE), "0") -> 0 | J44: =SUM(I44/60)*C44 -> 0
A45: Zaterdag | B45: 0.5625 | C45: 0.60416667 | D45: Prive training | E45: Eigenaar | F45: =IFERROR(VLOOKUP(E45, Docenten!$A$2:$G$30, 7, FALSE), "0") -> 0 | G45: =SUM(F45/60)*C45 -> 0 | I45: =IFERROR(VLOOKUP(H45, Locaties!$A$2:$G$15, 7, FALSE), "0") -> 0 | J45: =SUM(I45/60)*C45 -> 0
F46: =IFERROR(VLOOKUP(E46, Docenten!$A$2:$G$30, 7, FALSE), "0") -> 0 | G46: =SUM(F46/60)*C46 -> 0 | I46: =IFERROR(VLOOKUP(H46, Locaties!$A$2:$G$15, 7, FALSE), "0") -> 0 | J46: =SUM(I46/60)*C46 -> 0
F47: =IFERROR(VLOOKUP(E47, Docenten!$A$2:$G$30, 7, FALSE), "0") -> 0 | G47: =SUM(F47/60)*C47 -> 0 | I47: =IFERROR(VLOOKUP(H47, Locaties!$A$2:$G$15, 7, FALSE), "0") -> 0 | J47: =SUM(I47/60)*C47 -> 0
A48: Donderdag | B48: 0.75 | C48: 60 | D48: Turnen 6+ | E48: Dion + 3 | F48: =IFERROR(VLOOKUP(E48, Docenten!$A$2:$G$30, 7, FALSE), "0") -> 34 | G48: =SUM(F48/60)*C48 -> 34 | H48: Santpoort Noord | I48: =IFERROR(VLOOKUP(H48, Locaties!$A$2:$G$15, 7, FALSE), "0") -> 14.2 | J48: =SUM(I48/60)*C48 -> 14.2
A49: Donderdag | B49: 0.79166667 | C49: 60 | D49: Turnen 12+ | E49: Dion + 3 | F49: =IFERROR(VLOOKUP(E49, Docenten!$A$2:$G$30, 7, FALSE), "0") -> 34 | G49: =SUM(F49/60)*C49 -> 34 | H49: Santpoort Noord | I49: =IFERROR(VLOOKUP(H49, Locaties!$A$2:$G$15, 7, FALSE), "0") -> 14.2 | J49: =SUM(I49/60)*C49 -> 14.2
F50: =IFERROR(VLOOKUP(E50, Docenten!$A$2:$G$30, 7, FALSE), "0") -> 0 | G50: =SUM(F50/60)*C50 -> 0 | I50: =IFERROR(VLOOKUP(H50, Locaties!$A$2:$G$15, 7, FALSE), "0") -> 0 | J50: =SUM(I50/60)*C50 -> 0
F51: =IFERROR(VLOOKUP(E51, Docenten!$A$2:$G$30, 7, FALSE), "0") -> 0 | G51: =SUM(F51/60)*C51 -> 0 | I51: =IFERROR(VLOOKUP(H51, Locaties!$A$2:$G$15, 7, FALSE), "0") -> 0 | J51: =SUM(I51/60)*C51 -> 0
F52: =IFERROR(VLOOKUP(E52, Docenten!$A$2:$G$30, 7, FALSE), "0") -> 0 | G52: =SUM(F52/60)*C52 -> 0 | I52: =IFERROR(VLOOKUP(H52, Locaties!$A$2:$G$15, 7, FALSE), "0") -> 0 | J52: =SUM(I52/60)*C52 -> 0
F53: =IFERROR(VLOOKUP(E53, Docenten!$A$2:$G$30, 7, FALSE), "0") -> 0 | G53: =SUM(F53/60)*C53 -> 0 | I53: =IFERROR(VLOOKUP(H53, Locaties!$A$2:$G$15, 7, FALSE), "0") -> 0 | J53: =SUM(I53/60)*C53 -> 0
F54: =IFERROR(VLOOKUP(E54, Docenten!$A$2:$G$30, 7, FALSE), "0") -> 0 | G54: =SUM(F54/60)*C54 -> 0 | I54: =IFERROR(VLOOKUP(H54, Locaties!$A$2:$G$15, 7, FALSE), "0") -> 0 | J54: =SUM(I54/60)*C54 -> 0
F55: =IFERROR(VLOOKUP(E55, Docenten!$A$2:$G$30, 7, FALSE), "0") -> 0 | G55: =SUM(F55/60)*C55 -> 0 | I55: =IFERROR(VLOOKUP(H55, Locaties!$A$2:$G$15, 7, FALSE), "0") -> 0 | J55: =SUM(I55/60)*C55 -> 0
F56: =IFERROR(VLOOKUP(E56, Docenten!$A$2:$G$30, 7, FALSE), "0") -> 0 | G56: =SUM(F56/60)*C56 -> 0 | I56: =IFERROR(VLOOKUP(H56, Locaties!$A$2:$G$15, 7, FALSE), "0") -> 0 | J56: =SUM(I56/60)*C56 -> 0
F57: =IFERROR(VLOOKUP(E57, Docenten!$A$2:$G$30, 7, FALSE), "0") -> 0 | G57: =SUM(F57/60)*C57 -> 0 | I57: =IFERROR(VLOOKUP(H57, Locaties!$A$2:$G$15, 7, FALSE), "0") -> 0 | J57: =SUM(I57/60)*C57 -> 0
F58: =IFERROR(VLOOKUP(E58, Docenten!$A$2:$G$30, 7, FALSE), "0") -> 0 | G58: =SUM(F58/60)*C58 -> 0 | I58: =IFERROR(VLOOKUP(H58, Locaties!$A$2:$G$15, 7, FALSE), "0") -> 0 | J58: =SUM(I58/60)*C58 -> 0
F59: =IFERROR(VLOOKUP(E59, Docenten!$A$2:$G$30, 7, FALSE), "0") -> 0 | G59: =SUM(F59/60)*C59 -> 0 | I59: =IFERROR(VLOOKUP(H59, Locaties!$A$2:$G$15, 7, FALSE), "0") -> 0 | J59: =SUM(I59/60)*C59 -> 0
F60: =IFERROR(VLOOKUP(E60, Docenten!$A$2:$G$30, 7, FALSE), "0") -> 0 | G60: =SUM(F60/60)*C60 -> 0 | I60: =IFERROR(VLOOKUP(H60, Locaties!$A$2:$G$15, 7, FALSE), "0") -> 0 | J60: =SUM(I60/60)*C60 -> 0
F61: =IFERROR(VLOOKUP(E61, Docenten!$A$2:$G$30, 7, FALSE), "0") -> 0 | G61: =SUM(F61/60)*C61 -> 0 | I61: =IFERROR(VLOOKUP(H61, Locaties!$A$2:$G$15, 7, FALSE), "0") -> 0 | J61: =SUM(I61/60)*C61 -> 0
... F100: =IFERROR(VLOOKUP(E100, Docenten!$A$2:$G$30, 7, FALSE), "0") -> 0 | G100: =SUM(F100/60)*C100 -> 0 | I100: =IFERROR(VLOOKUP(H100, Locaties!$A$2:$G$15, 7, FALSE), "0") -> 0 | J100: =SUM(I100/60)*C100 -> 0

Sheet Kosten
A1: Kosten | B1: Augustus | C1: September | D1: Oktober | E1: November | F1: December | G1: Januari | H1: Februari | I1: Maart | J1: April | K1: Mei | L1: Juni | M1: Juli
A2: Abbonementen | B2: (Voor Nederland) Let op! Vul de bedragen excl BTW in.
A3: Ledenadministratie | B3: 77.44 | C3: 77.44 | D3: 77.44 | E3: 77.44 | F3: 77.44 | G3: 77.44 | H3: 77.44 | I3: 77.44 | J3: 77.44 | K3: 77.44 | L3: 77.44 | M3: 77.44
A4: ChatGTP | D4: 24.5 | E4: 24.5 | F4: 24.5 | G4: 24.5 | H4: 24.5 | I4: 24.5 | J4: 24.5 | K4: 24.5 | L4: 24.5 | M4: 24.5
A5: Spotify | B5: 10.99 | C5: 10.99 | D5: 10.99 | E5: 10.99 | F5: 10.99 | G5: 10.99 | H5: 10.99 | I5: 10.99 | J5: 10.99 | K5: 10.99 | L5: 10.99 | M5: 10.99
A6: Opslag Kostuums | B6: 213 | C6: 213 | D6: 213 | E6: 213 | F6: 213 | G6: 213 | H6: 213 | I6: 213 | J6: 213 | K6: 213 | L6: 213 | M6: 213
A7: Wix/Canva/Overig | E7: 160 | H7: 109 | L7: 376
A8: Extra zaal huur
A10: Personeel
A11: Administratief medewerker fulltime
A12: Kleding docenten | I12: 130.85
A14: Administratiekosten
A15: kantoorkosten | D15: =110+15.8 -> 125.8 | E15: =15.43+46+274 -> 335.43 | F15: 97 | G15: =130+141+70+13 -> 354 | H15: =276+37.4+347+122++69+9.4 -> 860.8 | I15: =84+37.97+26.99+31+8.75+16.49+209.8 -> 415 | L15: =20+30+186 -> 236
A16: telefoonkosten | B16: 20.56 | C16: 20.56 | D16: 20.56 | E16: 20.56 | F16: 20.56 | G16: 20.56 | H16: 20.56 | I16: 20.56 | J16: 20.56 | K16: 20.56 | L16: 20.56 | M16: 20.56
A17: computerkosten | B17: 639 | L17: 155 | M17: 155
A18: Verzekering | B18: 72.25 | C18: 72.25 | D18: 72.25 | E18: 72.25 | F18: 72.25 | G18: 72.25 | H18: 72.25 | I18: 72.25 | J18: 72.25 | K18: 72.25 | L18: 72.25 | M18: 72.25
A20: Kosten leden
A21: Kostuums aangekocht doorheen jaar | B21: =64+79+10 -> 153 | D21: 63 | E21: =75+22+25+29 -> 151 | F21: =15+170+34+34+37+87+25+92+60 -> 554 | G21: =28.95+21.76+44 -> 94.71 | H21: 610 | L21: =50.64+66.3 -> 116.94
A22: kostuums aangekocht periode show | G22: =74+33+100 -> 207
A23: Selectie teams | B23: =33+245+112+152.3+175+55+96+135 -> 1003.3 | C23: =128+169+99+64+138+152.7-+51+33+29+112.28+119.3+290+13.93+550+30+1630+518+230 -> 4255.21 | D23: =29.66+24.24+24+44 -> 121.9 | F23: 826 | G23: =820+102+200 -> 1122 | H23: 811 | I23: =1000+960+30 -> 1990
A25: Voorstellingskosten | K25: 27200
A29: Marketing en verkoopkosten
A30: advertentie per maand | B30: 50 | E30: 86 | G30: 207 | K30: 50 | L30: 50 | M30: 50
A31: kosten overig werk | B31: =31+27+35 -> 93 | C31: =28+23+10+39.9 -> 100.9 | D31: =36+40+23+22+129 -> 250 | E31: =54+150+90+97+27+78+27+6+20+17 -> 566 | F31: =13+23+79+39+78+40+15+25+30+26+29 -> 397 | G31: =35+25.45+81+63+93+23 -> 320.45 | H31: 222 | I31: =21.15+129 -> 150.15 | J31: =175+20+250 -> 445
A32: representatiekosten | B32: =280.65+240 -> 520.65 | C32: =137+130 -> 267 | D32: =52+277+80+12 -> 421 | E32: =165+107.5+46 -> 318.5 | F32: =155+177 -> 332 | G32: =250+65.5+132+30 -> 477.5 | H32: 125 | I32: =125.8+39.5+43 -> 208.3 | J32: =65+171+55 -> 291
A33: promotiemateriaal | B33: =150+30+91 -> 271 | C33: 921 | D33: 53 | G33: =47.53+56.5 -> 104.03
A34: overige verkoopkosten | L34: 108
A35: coaching | B35: 544.5 | C35: 544.5 | D35: 544.5 | E35: 544.5 | F35: 544.5 | G35: 544.5 | H35: 544.5 | I35: 544.5 | J35: 544.5 | K35: 544.5 | L35: 544.5 | M35: 544.5
A36: Merchandise | C36: 1592 | D36: 294
A38: Vervoerskosten
A39: Verzekering auto | B39: 143 | C39: 143 | D39: 121.75 | E39: 121.75 | F39: 121.75 | G39: 121.75 | H39: 121.75 | I39: 121.75 | J39: 121.75 | K39: 121.75 | L39: 121.75 | M39: 121.75
A40: benzine | B40: 122 | C40: =26+111 -> 137 | D40: =50+111+113 -> 274 | E40: =120+125 -> 245 | F40: =116+90 -> 206 | G40: 107 | H40: =116+121 -> 237 | I40: =35+100+145 -> 280 | J40: 139 | K40: 120 | L40: 120 | M40: 120
A41: Auto reperatie | F41: 1200 | J41: 743
A42: bankkosten | B42: =14+25+49 -> 88 | C42: =55+27 -> 82 | D42: =90+28 -> 118 | E42: 26 | F42: =231+26 -> 257 | G42: =102+465.85+261+40.79 -> 869.64 | H42: =120+28.99 -> 148.99 | I42: =116.52+31.06 -> 147.58 | K42: 100 | L42: 100 | M42: 100
A44: Belasting | I44: 374
A46: teamvergaderingen huur zaaltje en eten / drank
A48: boekhouder | C48: 1742 | D48: =371+78+155 -> 604 | I48: 435.85 | M48: 450
A50: klein materiaal voor danslessen
A51: Les benodigdheden
A52: Activiteiten | B52: =23.4+29.37+169.9+178+176.22+46 -> 622.89 | D52: =100+143+22+104+61+21+60+601+44+65+35 -> 1256 | E52: =94+122 -> 216 | F52: 128 | G52: =450+250 -> 700 | H52: 89.29 | I52: =25+60+388+275+210 -> 958 | L52: 800
A53: thema-materiaal | C53: =53.45+21.35+90+11 -> 175.8 | M53: =26+16+20+78+100 -> 240
A69: Totaal: | B69: =SUM(B2:B54) -> 4644.58 | C69: =SUM(C2:C54) -> 10354.65 | D69: =SUM(D2:D54) -> 4665.69 | E69: =SUM(E2:E54) -> 3188.92 | F69: =SUM(F2:F54) -> 5081.99 | G69: =SUM(G2:G54) -> 5648.32 | H69: =SUM(H2:H54) -> 4298.07 | I69: =SUM(I2:I54) -> 6174.72 | ... M69: =SUM(M2:M54) -> 2199.99

Sheet Extra activiteiten
A1: Maand | B1: Activiteit | C1: Verwachte verkoop | D1: Prijs per activiteit | E1: Verwachte omzet | F1: Marketingstrategie | G1: Verkochte aantal | H1: Totaal | J1: Maand | K1: Totaal per maand
A2: September | B2: Selectie bijdrage | C2: 1 | D2: 8730 | E2: =C2*D2 -> 8730 | G2: 1 | H2: =G2*D2 -> 8730 | J2: augustus
A3: September | B3: Inschrijfkosten | C3: 80 | D3: 10 | E3: =C3*D3 -> 800 | F3: (Voor het hele jaar) | G3: 70 | H3: =G3*D3 -> 700 | J3: september | K3: =H2+H3+H4 -> 11430
A4: September | B4: Sponsoring Selectie | C4: 2 | D4: 1000 | E4: =C4*D4 -> 2000 | G4: 2 | H4: =G4*D4 -> 2000 | J4: oktober | K4: =H6+H7+H8+H9+H10+H11 -> 695.5
J5: november | K5: =H12+H13+H14 -> 1206
A6: Oktober | B6: Partijtje | C6: 1 | D6: 235 | E6: =C6*D6 -> 235 | G6: 1 | H6: =G6*D6 -> 235 | J6: december | K6: =H16+H17+H18+H19 -> 9975
A7: Oktober | B7: Herfst 6+ | C7: 25 | D7: 12.5 | E7: =C7*D7 -> 312.5 | G7: 25 | H7: =G7*D7 -> 312.5 | J7: januari | K7: =H20+H21+H22+H23 -> 425
A8: Oktober | B8: Herfst kleuters | C8: 12 | D8: 6.5 | E8: =C8*D8 -> 78 | G8: 12 | H8: =G8*D8 -> 78 | J8: februari | K8: =H25+H26+H27+H28 -> 220
E9: =C9*D9 -> 0 | H9: =G9*D9 -> 0 | J9: maart | K9: =H30+H31+H32+H33 -> 2195
E10: =C10*D10 -> 0 | H10: =G10*D10 -> 0 | J10: april | K10: =H35+H36+H37 -> 220
A11: November | B11: Kinderopvang | C11: 1 | D11: 70 | E11: =C11*D11 -> 70 | G11: 1 | H11: =G11*D11 -> 70 | J11: mei | K11: =H38+H39+H40+H41 -> 41040
A12: November | B12: Merchendise | C12: 1 | D12: 550 | E12: =C12*D12 -> 550 | G12: 1 | H12: =G12*D12 -> 550 | J12: juni | K12: =H43+H44 -> 422.5
A13: November | B13: Halloween | C13: 56 | D13: 8.5 | E13: =C13*D13 -> 476 | G13: 56 | H13: =G13*D13 -> 476 | J13: juli
A14: November | B14: Lessen Ichthus | C14: 2 | D14: 90 | E14: =C14*D14 -> 180 | G14: 2 | H14: =G14*D14 -> 180
E15: =C15*D15 -> 0 | H15: =G15*D15 -> 0
A16: December | B16: Pietenochtend | C16: 40 | D16: 6.5 | E16: =C16*D16 -> 260 | G16: 50 | H16: =G16*D16 -> 325
A17: December | B17: Kerstshow | C17: 800 | D17: 11 | E17: =C17*D17 -> 8800 | G17: 800 | H17: =G17*D17 -> 8800
A18: December | B18: Merchandise | C18: 1 | D18: 780 | E18: =C18*D18 -> 780 | G18: 1 | H18: =G18*D18 -> 780
A19: December | B19: Kinderopvang | C19: 1 | D19: 70 | E19: =C19*D19 -> 70 | G19: 1 | H19: =G19*D19 -> 70
E20: =C20*D20 -> 0 | H20: =G20*D20 -> 0
A21: Januari | B21: Partijtje | C21: 1 | D21: 425 | E21: =C21*D21 -> 425 | G21: 1 | H21: =G21*D21 -> 425
A22: Januari | B22: Merch | C22: 1 | D22: 12.5 | E22: =C22*D22 -> 12.5 | H22: =G22*D22 -> 0
E23: =C23*D23 -> 0 | G23: 1 | H23: =G23*D23 -> 0
E24: =C24*D24 -> 0 | H24: =G24*D24 -> 0
A25: Februari | B25: Merchandise | E25: =C25*D25 -> 0 | H25: =G25*D25 -> 0
A26: Februari | B26: Partijtje | C26: 1 | D26: 220 | E26: =C26*D26 -> 220 | G26: 1 | H26: =G26*D26 -> 220
E27: =C27*D27 -> 0 | H27: =G27*D27 -> 0
E28: =C28*D28 -> 0 | H28: =G28*D28 -> 0
E29: =C29*D29 -> 0 | H29: =G29*D29 -> 0
A30: Maart | B30: Partijtje | C30: 1 | D30: 220 | E30: =C30*D30 -> 220 | G30: 1 | H30: =G30*D30 -> 220
A31: Maart | B31: FL Wedstrijd | C31: 43 | D31: 5.5 | E31: =C31*D31 -> 236.5 | G31: 50 | H31: =G31*D31 -> 275
A32: Maart | B32: FL Wedstrijd | C32: 150 | D32: 10 | E32: =C32*D32 -> 1500 | G32: 170 | H32: =G32*D32 -> 1700
A33: Maart | B33: Merchandise | E33: =C33*D33 -> 0 | H33: =G33*D33 -> 0
E34: =C34*D34 -> 0 | H34: =G34*D34 -> 0
A35: April | B35: Partijtje | C35: 1 | D35: 220 | E35: =C35*D35 -> 220 | G35: 1 | H35: =G35*D35 -> 220
A36: April | B36: Merchandise | E36: =C36*D36 -> 0 | H36: =G36*D36 -> 0
A37: April | E37: =C37*D37 -> 0 | H37: =G37*D37 -> 0
E38: =C38*D38 -> 0 | H38: =G38*D38 -> 0
A39: Mei | B39: Merchandise | C39: 1 | D39: 500 | E39: =C39*D39 -> 500 | G39: 1 | H39: =G39*D39 -> 500
A40: Mei | B40: Voorstelling | C40: 1 | D40: 40540 | E40: =C40*D40 -> 40540 | G40: 1 | H40: =G40*D40 -> 40540
E41: =C41*D41 -> 0 | H41: =G41*D41 -> 0
E42: =C42*D42 -> 0 | H42: =G42*D42 -> 0
A43: Juni | B43: Afsluiting | C43: 65 | D43: 6.5 | E43: =C43*D43 -> 422.5 | G43: 65 | H43: =G43*D43 -> 422.5
A44: Juni | B44: Merchandise | E44: =C44*D44 -> 0 | H44: =G44*D44 -> 0
E45: =C45*D45 -> 0 | H45: =G45*D45 -> 0
E46: =C46*D46 -> 0 | H46: =G46*D46 -> 0
E47: =C47*D47 -> 0 | H47: =G47*D47 -> 0
E48: =C48*D48 -> 0 | H48: =G48*D48 -> 0
E49: =C49*D49 -> 0 | H49: =G49*D49 -> 0
E50: =C50*D50 -> 0 | H50: =G50*D50 -> 0
E51: =C51*D51 -> 0 | H51: =G51*D51 -> 0
E52: =C52*D52 -> 0 | H52: =G52*D52 -> 0
E53: =C53*D53 -> 0 | H53: =G53*D53 -> 0
E54: =C54*D54 -> 0 | H54: =G54*D54 -> 0
E55: =C55*D55 -> 0 | H55: =G55*D55 -> 0
E56: =C56*D56 -> 0 | H56: =G56*D56 -> 0
... E1038: =C1038*D1038 -> 0 | H1038: =G1038*D1038 -> 0

Sheet Inkomstenbelasting
A1: Inkomstenbelasting Nederland
A2: Op dit tabblad zie je hoe de berekening voor de inkomstenbelasting is opgebouwd. Let op: Dit is een inschatting!
A4: Heb je recht op startersaftrek in 2025? | C4: Nee | E4: Heb je recht op startersaftrek in 2025? | G4: Nee
A6: Financieel plan - Doelen | C6: 2025 | E6: Financieel plan - Werkelijkheid | G6: 2025
A7: Winst uit onderneming | C7: ='Doel vs Werkelijkheid'!D14 | E7: Winst uit onderneming | G7: ='Doel vs Werkelijkheid'!K14 -> 86454.555
A8: Zelfstandigenaftrek | C8: -2470 | E8: Zelfstandigenaftrek | G8: -2470
A9: Startersaftrek | C9: =IF(C4="Ja",-2123,0) -> 0 | E9: Startersaftrek | G9: =IF(G4="Ja",-2123,0) -> 0
A10: MKB-winstvrijstelling | C10: =MIN(0,-(C7+SUM(C8:C9))*0.127) -> 0 | E10: MKB-winstvrijstelling | G10: =MIN(0,-(G7+SUM(G8:G9))*0.127) -> -10666.039
A11: Belastbaar inkomen box 1 | C11: =MAX(C7+SUM(C8:C10),0) -> 0 | E11: Belastbaar inkomen box 1 | G11: =MAX(G7+SUM(G8:G10),0) -> 73318.517
A13: Belasting box 1 | C13: =MIN(76817,C11)*0.3664 + MAX(C11-76817,0)*0.495 -> 0 | E13: Belasting box 1 | G13: =MIN(76817,G11)*0.3664 + MAX(G11-76817,0)*0.495 -> 26863.905
A14: Algemene heffingskorting | C14: =-IF(AND(C11<24813,C11>0),3362,IF(AND(C11>=24818,C11<75518),(3362-0.0663*(C11-24812)),0)) -> 0 | E14: Algemene heffingskorting | G14: =-IF(AND(G11<24813,G11>0),3362,IF(AND(G11>=24818,G11<75518),(3362-0.0663*(G11-24812)),0)) -> -146.01794
A15: Arbeidskorting | C15: =-IF(AND(C7<11491,C7>0),0.08425*C7,IF(AND(C7>=11491,C7<24821),(968+0.31433*(C7-11490)),IF(AND(C7>=24821,C7<39958),(5158+0.02471*(C7-24820)),IF(AND(C7>=39958,C7<124935),(5532-0.0651*(C7-39958)),0)))) -> 0 | E15: Arbeidskorting | G15: =-IF(AND(G7<11491,G7>0),0.08425*G7,IF(AND(G7>=11491,G7<24821),(968+0.31433*(G7-11490)),IF(AND(G7>=24821,G7<39958),(5158+0.02471*(G7-24820)),IF(AND(G7>=39958,G7<124935),(5532-0.0651*(G7-39958)),0)))) -> -2505.0742
A16: Verschuldigde inkomensbelasting | C16: =MAX(0,C13+C14+C15) -> 0 | E16: Verschuldigde inkomensbelasting | G16: =MAX(0,G13+G14+G15) -> 24212.812
A17: Inkomensafhankelijk bijdrage Zvw | C17: =MIN(C11,71628)*0.0532 -> 0 | E17: Inkomensafhankelijk bijdrage Zvw | G17: =MIN(G11,71628)*0.0532 -> 3810.6096
A18: Totaal inkomstenbelasting en premie Zvw | C18: =C16+C17 -> 0 | E18: Totaal inkomstenbelasting en premie Zvw | G18: =G16+G17 -> 28023.422
A19: % van de winst | C19: =IFERROR(C18/C7,"") | E19: % van de winst | G19: =IFERROR(G18/G7,"") -> 0.32414049 | H19: =G19 -> 0.32414049
A21: Inkomstenbelasting Belgie
A22: Op dit tabblad zie je hoe de berekening voor de inkomstenbelasting is opgebouwd. Let op: Dit is een inschatting!
A24: Financieel plan - Doelen | C24: 2025 | E24: Financieel plan - Werkelijkheid | G24: 2025
A25: Winst uit onderneming | C25: ='Doel vs Werkelijkheid'!D32 | E25: Winst uit onderneming | G25: ='Doel vs Werkelijkheid'!K32
A26: Sociale bijdrage | C26: =IFS(C25<16861.46, 898.28*4,AND(C25>16861.46,C25<72810.95),20.5%*C25,AND(C25>72810.95,C25<107300.3),14.16%*C25,C25>107300.3,5148.1*4) -> 3593.12 | E26: Sociale bijdrage | G26: =IFS(G25<16861.46, 898.28*4,AND(G25>16861.46,G25<72810.95),20.5%*G25,AND(G25>72810.95,G25<107300.3),14.16%*G25,G25>107300.3,5148.1*4) -> 3593.12
A27: Belastbaar inkomen box 1 | C27: =MAX(C25-C26,0) -> 0 | E27: Belastbaar inkomen box 1 | G27: =MAX(G25-G26,0) -> 0
A29: Schijf 1 | C29: =MIN(C27,15200)*25% -> 0 | E29: Schijf 1 | G29: =MIN(G27,15200)*25% -> 0
A30: Schijf 2 | C30: =max(0,(MIN(C27,26830)-15200)*40%) -> 0 | E30: Schijf 2 | G30: =max(0,(MIN(G27,26830)-15200)*40%) -> 0
A31: Schijf 3 | C31: =MAX(0,(MIN(C27,46440)-26830)*45%) -> 0 | E31: Schijf 3 | G31: =MAX(0,(MIN(G27,46440)-26830)*45%) -> 0
A32: Schijf 4 | C32: =Max(C27-46440,0)*50% -> 0 | E32: Schijf 4 | G32: =Max(G27-46440,0)*50% -> 0
A33: Sociale bijdrage | C33: =C26 -> 3593.12 | E33: Sociale bijdrage | G33: =G26 -> 3593.12
A34: Belastingvrije som | C34: =IF(C27<10160,0,-10160*25%) -> 0 | E34: Belastingvrije som | G34: =IF(G27<10160,0,-10160*25%) -> 0
A35: Totaal inkomstenbelasting en premie Zvw | C35: =SUM(C29:C34) -> 3593.12 | E35: Totaal inkomstenbelasting en premie Zvw | G35: =SUM(G29:G34) -> 3593.12
A36: % van de winst | C36: =IFERROR(C35/C25,"") | E36: % van de winst | G36: =IFERROR(G35/G25,"")

Sheet Jaarbetalingen
A1: Lesdag | B1: Lestijd | C1: Minuten les | D1: Naam les | E1: Aantal lessen deze maand | F1: Docent | G1: Tarief docent | H1: Tarief docent per les | I1: Locatie | J1: Zaalhuur per uur | K1: Zaalhuur per les | L1: Aantal leden tarief 1 | M1: Type lidmaatschap (Letop! alleen jaarbetalingen!!) | N1: Tarief 1 | O1: Aantal leden tarief 2 | P1: Type lidmaatschap (Letop! alleen jaarbetalingen!!) 2 | Q1: Tarief 2 | R1: Aantal leden tarief 3 | S1: Type lidmaatschap (Letop! alleen jaarbetalingen!!) 3 | T1: Tarief 3 | U1: Aantal leden tarief 4 | V1: Type lidmaatschap (Letop! alleen jaarbetalingen!!) 4 | W1: Tarief 4 | X1: Aantal leden tarief 5 | Y1: Type lidmaatschap (Letop! alleen jaarbetalingen!!) 5 | Z1: Tarief 5 | AA1: Aantal leden tarief 6 | AB1: Type lidmaatschap (Letop! alleen jaarbetalingen!!) 6 | AC1: Tarief 6 | AD1: Totaal aantal leden | AE1: Kosten per maand | AF1: Inkomsten voor komend seizoen | AG1: Winst per maand
A2: =Rooster!A3 | B2: =Rooster!B3 | C2: =Rooster!C3 | D2: =Rooster!D3 | N2: =IFERROR(VLOOKUP(M2, Tarieven[#ALL], 10, FALSE), "0") -> 0 | Q2: =IFERROR(VLOOKUP(P2, Tarieven[#ALL], 10, FALSE), "0") -> 0 | T2: =IFERROR(VLOOKUP(S2, Tarieven[#ALL], 10, FALSE), "0") -> 0 | W2: =IFERROR(VLOOKUP(V2, Tarieven!$A$1:$J$150, 10, FALSE), "0") -> 0 | Z2: =IFERROR(VLOOKUP(Y2, Tarieven[#ALL], 10, FALSE), "0") -> 0 | AC2: =IFERROR(VLOOKUP(AB2, Tarieven[#ALL], 10, FALSE), "0") -> 0 | AD2: =SUM(L2+O2+R2+U2+X2+AA2) -> 0 | AE2: =SUM(H2+K2)*E2 -> 0 | AF2: =SUM((L2*N2)+(O2*Q2)+(R2*T2)+(U2*W2)+(X2*Z2)+(AA2*AC2)) -> 0 | AG2: =SUM(AF2-AE2) -> 0
A3: =Rooster!A4 | B3: =Rooster!B4 | C3: =Rooster!C4 | D3: =Rooster!D4 | N3: =IFERROR(VLOOKUP(M3, Tarieven[#ALL], 10, FALSE), "0") -> 0 | Q3: =IFERROR(VLOOKUP(P3, Tarieven[#ALL], 10, FALSE), "0") -> 0 | T3: =IFERROR(VLOOKUP(S3, Tarieven[#ALL], 10, FALSE), "0") -> 0 | W3: =IFERROR(VLOOKUP(V3, Tarieven!$A$1:$J$150, 10, FALSE), "0") -> 0 | Z3: =IFERROR(VLOOKUP(Y3, Tarieven[#ALL], 10, FALSE), "0") -> 0 | AC3: =IFERROR(VLOOKUP(AB3, Tarieven[#ALL], 10, FALSE), "0") -> 0 | AD3: =SUM(L3+O3+R3+U3+X3+AA3) -> 0 | AE3: =SUM(H3+K3)*E3 -> 0 | AF3: =SUM((L3*N3)+(O3*Q3)+(R3*T3)+(U3*W3)+(X3*Z3)+(AA3*AC3)) -> 0 | AG3: =SUM(AF3-AE3) -> 0 | AI3: =SUM(Tabel2[Inkomsten voor komend seizoen]) -> 57241.19
A4: =Rooster!A5 -> Maandag | B4: =Rooster!B5 -> 0.625 | C4: =Rooster!C5 -> 60 | D4: =Rooster!D5 -> Kleuterdans | N4: =IFERROR(VLOOKUP(M4, Tarieven[#ALL], 10, FALSE), "0") -> 0 | Q4: =IFERROR(VLOOKUP(P4, Tarieven[#ALL], 10, FALSE), "0") -> 0 | T4: =IFERROR(VLOOKUP(S4, Tarieven[#ALL], 10, FALSE), "0") -> 0 | W4: =IFERROR(VLOOKUP(V4, Tarieven!$A$1:$J$150, 10, FALSE), "0") -> 0 | Z4: =IFERROR(VLOOKUP(Y4, Tarieven[#ALL], 10, FALSE), "0") -> 0 | AC4: =IFERROR(VLOOKUP(AB4, Tarieven[#ALL], 10, FALSE), "0") -> 0 | AD4: =SUM(L4+O4+R4+U4+X4+AA4) -> 0 | AE4: =SUM(H4+K4)*E4 -> 0 | AF4: =SUM((L4*N4)+(O4*Q4)+(R4*T4)+(U4*W4)+(X4*Z4)+(AA4*AC4)) -> 0 | AG4: =SUM(AF4-AE4) -> 0
A5: =Rooster!A6 -> Maandag | B5: =Rooster!B6 -> 0.625 | C5: =Rooster!C6 -> 60 | D5: =Rooster!D6 -> Streetdance 6+ | N5: =IFERROR(VLOOKUP(M5, Tarieven!$A$1:$J$150, 10, FALSE), "0") -> 0 | Q5: =IFERROR(VLOOKUP(P5, Tarieven!$A$1:$J$150, 10, FALSE), "0") -> 0 | T5: =IFERROR(VLOOKUP(S5, Tarieven!$A$1:$J$150, 10, FALSE), "0") -> 0 | W5: =IFERROR(VLOOKUP(V5, Tarieven!$A$1:$J$150, 10, FALSE), "0") -> 0 | Z5: =IFERROR(VLOOKUP(Y5, Tarieven[#ALL], 10, FALSE), "0") -> 0 | AC5: =IFERROR(VLOOKUP(AB5, Tarieven[#ALL], 10, FALSE), "0") -> 0 | AD5: =SUM(L5+O5+R5+U5+X5+AA5) -> 0 | AF5: =SUM((L5*N5)+(O5*Q5)+(R5*T5)+(U5*W5)+(X5*Z5)+(AA5*AC5)) -> 0 | AG5: =SUM(L5+O5+R5+AD5) -> 0
A6: =Rooster!A7 -> Maandag | B6: =Rooster!B7 -> 0.66666667 | C6: =Rooster!C7 -> 60 | D6: =Rooster!D7 -> Urban-Pop-Show 10+ | L6: 3 | M6: 1x per week | N6: =IFERROR(VLOOKUP(M6, Tarieven!$A$1:$J$150, 10, FALSE), "0") -> 279 | O6: 1 | P6: Cheer regulier +1 | Q6: =IFERROR(VLOOKUP(P6, Tarieven!$A$1:$J$150, 10, FALSE), "0") -> 289.5 | T6: =IFERROR(VLOOKUP(S6, Tarieven!$A$1:$J$150, 10, FALSE), "0") -> 0 | W6: =IFERROR(VLOOKUP(V6, Tarieven!$A$1:$J$150, 10, FALSE), "0") -> 0 | Z6: =IFERROR(VLOOKUP(Y6, Tarieven[#ALL], 10, FALSE), "0") -> 0 | AC6: =IFERROR(VLOOKUP(AB6, Tarieven[#ALL], 10, FALSE), "0") -> 0 | AD6: =SUM(L6+O6+R6+U6+X6+AA6) -> 4 | AE6: 1x per week | AF6: =SUM((L6*N6)+(O6*Q6)+(R6*T6)+(U6*W6)+(X6*Z6)+(AA6*AC6)) -> 1126.5 | AG6: =SUM(L6+O6+R6+AD6) -> 8
A7: =Rooster!A8 -> Maandag | B7: =Rooster!B8 -> 0.70833333 | C7: =Rooster!C8 -> 60 | D7: =Rooster!D8 -> Urban-Pop-Show 12+ | L7: 4 | M7: 1x per week | N7: =IFERROR(VLOOKUP(M7, Tarieven!$A$1:$J$150, 10, FALSE), "0") -> 279 | O7: 2 | P7: 2x per week | Q7: =IFERROR(VLOOKUP(P7, Tarieven!$A$1:$J$150, 10, FALSE), "0") -> 279 | R7: 1 | S7: Cheer regulier +1 | T7: =IFERROR(VLOOKUP(S7, Tarieven!$A$1:$J$150, 10, FALSE), "0") -> 289.5 | U7: 4 | V7: Cheer selectie onbeperkt | W7: =IFERROR(VLOOKUP(V7, Tarieven!$A$1:$J$150, 10, FALSE), "0") -> 235 | Z7: =IFERROR(VLOOKUP(Y7, Tarieven[#ALL], 10, FALSE), "0") -> 0 | AC7: =IFERROR(VLOOKUP(AB7, Tarieven[#ALL], 10, FALSE), "0") -> 0 | AD7: =SUM(L7+O7+R7+U7+X7+AA7) -> 11 | AF7: =SUM((L7*N7)+(O7*Q7)+(R7*T7)+(U7*W7)+(X7*Z7)+(AA7*AC7)) -> 2903.5 | AG7: =SUM(L7+O7+R7+AD7) -> 18
A8: =Rooster!A9 -> Maandag | B8: =Rooster!B9 -> 0.75 | C8: =Rooster!C9 -> 60 | D8: =Rooster!D9 -> Selectie Show | N8: =IFERROR(VLOOKUP(M8, Tarieven!$A$1:$J$150, 10, FALSE), "0") -> 0 | O8: 3 | P8: Onbeperkt | Q8: =IFERROR(VLOOKUP(P8, Tarieven!$A$1:$J$150, 10, FALSE), "0") -> 263.625 | R8: 1 | S8: Geen betaling | T8: =IFERROR(VLOOKUP(S8, Tarieven!$A$1:$J$150, 10, FALSE), "0") -> 0 | W8: =IFERROR(VLOOKUP(V8, Tarieven!$A$1:$J$150, 10, FALSE), "0") -> 0 | Z8: =IFERROR(VLOOKUP(Y8, Tarieven[#ALL], 10, FALSE), "0") -> 0 | AC8: =IFERROR(VLOOKUP(AB8, Tarieven[#ALL], 10, FALSE), "0") -> 0 | AD8: =SUM(L8+O8+R8+U8+X8+AA8) -> 4 | AF8: =SUM((L8*N8)+(O8*Q8)+(R8*T8)+(U8*W8)+(X8*Z8)+(AA8*AC8)) -> 790.875 | AG8: =SUM(L8+O8+R8+AD8) -> 8
A9: =Rooster!A10 -> Maandag | B9: =Rooster!B10 -> 0.79166667 | C9: =Rooster!C10 -> 60 | D9: =Rooster!D10 -> Commercial 16+ | L9: 1 | M9: 1x per week | N9: =IFERROR(VLOOKUP(M9, Tarieven!$A$1:$J$150, 10, FALSE), "0") -> 279 | O9: 2 | P9: Onbeperkt | Q9: =IFERROR(VLOOKUP(P9, Tarieven!$A$1:$J$150, 10, FALSE), "0") -> 263.625 | R9: 1 | S9: 3x per week | T9: =IFERROR(VLOOKUP(S9, Tarieven!$A$1:$J$150, 10, FALSE), "0") -> 279 | U9: 1 | V9: Geen betaling | W9: =IFERROR(VLOOKUP(V9, Tarieven!$A$1:$J$150, 10, FALSE), "0") -> 0 | Z9: =IFERROR(VLOOKUP(Y9, Tarieven[#ALL], 10, FALSE), "0") -> 0 | AC9: =IFERROR(VLOOKUP(AB9, Tarieven[#ALL], 10, FALSE), "0") -> 0 | AD9: =SUM(L9+O9+R9+U9+X9+AA9) -> 5 | AF9: =SUM((L9*N9)+(O9*Q9)+(R9*T9)+(U9*W9)+(X9*Z9)+(AA9*AC9)) -> 1085.25 | AG9: =SUM(L9+O9+R9+AD9) -> 9
A10: =Rooster!A11 -> Maandag | B10: =Rooster!B11 -> 0.83333333 | C10: =Rooster!C11 -> 60 | D10: =Rooster!D11 -> Commercial 20+ | L10: 1 | M10: Volwassenen 2x | N10: =IFERROR(VLOOKUP(M10, Tarieven!$A$1:$J$150, 10, FALSE), "0") -> 266.625 | O10: 3 | P10: Volwassenen 1x | Q10: =IFERROR(VLOOKUP(P10, Tarieven!$A$1:$J$150, 10, FALSE), "0") -> 266.23 | R10: 4 | S10: Geen betaling | T10: =IFERROR(VLOOKUP(S10, Tarieven!$A$1:$J$150, 10, FALSE), "0") -> 0 | W10: =IFERROR(VLOOKUP(V10, Tarieven!$A$1:$J$150, 10, FALSE), "0") -> 0 | Z10: =IFERROR(VLOOKUP(Y10, Tarieven[#ALL], 10, FALSE), "0") -> 0 | AC10: =IFERROR(VLOOKUP(AB10, Tarieven[#ALL], 10, FALSE), "0") -> 0 | AD10: =SUM(L10+O10+R10+U10+X10+AA10) -> 8 | AF10: =SUM((L10*N10)+(O10*Q10)+(R10*T10)+(U10*W10)+(X10*Z10)+(AA10*AC10)) -> 1065.315 | AG10: =SUM(L10+O10+R10+AD10) -> 16
A11: =Rooster!A12 -> Maandag | B11: =Rooster!B12 -> 0.875 | C11: =Rooster!C12 -> 60 | D11: =Rooster!D12 -> Jazz 20+ | L11: 1 | M11: Volwassenen 2x | N11: =IFERROR(VLOOKUP(M11, Tarieven!$A$1:$J$150, 10, FALSE), "0") -> 266.625 | Q11: =IFERROR(VLOOKUP(P11, Tarieven!$A$1:$J$150, 10, FALSE), "0") -> 0 | R11: 3 | S11: Geen betaling | T11: =IFERROR(VLOOKUP(S11, Tarieven!$A$1:$J$150, 10, FALSE), "0") -> 0 | W11: =IFERROR(VLOOKUP(V11, Tarieven!$A$1:$J$150, 10, FALSE), "0") -> 0 | Z11: =IFERROR(VLOOKUP(Y11, Tarieven[#ALL], 10, FALSE), "0") -> 0 | AC11: =IFERROR(VLOOKUP(AB11, Tarieven[#ALL], 10, FALSE), "0") -> 0 | AD11: =SUM(L11+O11+R11+U11+X11+AA11) -> 4 | AE11: 1x per week | AF11: =SUM((L11*N11)+(O11*Q11)+(R11*T11)+(U11*W11)+(X11*Z11)+(AA11*AC11)) -> 266.625 | AG11: =SUM(L11+O11+R11+AD11) -> 8
A12: =Rooster!A13 -> Maandag | B12: =Rooster!B13 -> 0.66666667 | C12: =Rooster!C13 -> 60 | D12: =Rooster!D13 -> Streetdance 6+ | L12: 2 | M12: 1x per week | N12: =IFERROR(VLOOKUP(M12, Tarieven!$A$1:$J$150, 10, FALSE), "0") -> 279 | Q12: =IFERROR(VLOOKUP(P12, Tarieven!$A$1:$J$150, 10, FALSE), "0") -> 0 | T12: =IFERROR(VLOOKUP(S12, Tarieven!$A$1:$J$150, 10, FALSE), "0") -> 0 | W12: =IFERROR(VLOOKUP(V12, Tarieven!$A$1:$J$150, 10, FALSE), "0") -> 0 | Z12: =IFERROR(VLOOKUP(Y12, Tarieven[#ALL], 10, FALSE), "0") -> 0 | AC12: =IFERROR(VLOOKUP(AB12, Tarieven[#ALL], 10, FALSE), "0") -> 0 | AD12: =SUM(L12+O12+R12+U12+X12+AA12) -> 2 | AF12: =SUM((L12*N12)+(O12*Q12)+(R12*T12)+(U12*W12)+(X12*Z12)+(AA12*AC12)) -> 558 | AG12: =SUM(L12+O12+R12+AD12) -> 4
A13: =Rooster!A14 -> Maandag | B13: =Rooster!B14 -> 0.70833333 | C13: =Rooster!C14 -> 60 | D13: =Rooster!D14 -> Streetdance 8+ | L13: 10 | M13: 1x per week | N13: =IFERROR(VLOOKUP(M13, Tarieven!$A$1:$J$150, 10, FALSE), "0") -> 279 | O13: 3 | P13: 2x per week | Q13: =IFERROR(VLOOKUP(P13, Tarieven!$A$1:$J$150, 10, FALSE), "0") -> 279 | T13: =IFERROR(VLOOKUP(S13, Tarieven!$A$1:$J$150, 10, FALSE), "0") -> 0 | W13: =IFERROR(VLOOKUP(V13, Tarieven!$A$1:$J$150, 10, FALSE), "0") -> 0 | Z13: =IFERROR(VLOOKUP(Y13, Tarieven[#ALL], 10, FALSE), "0") -> 0 | AC13: =IFERROR(VLOOKUP(AB13, Tarieven[#ALL], 10, FALSE), "0") -> 0 | AD13: =SUM(L13+O13+R13+U13+X13+AA13) -> 13 | AE13: 1x per week | AF13: =SUM((L13*N13)+(O13*Q13)+(R13*T13)+(U13*W13)+(X13*Z13)+(AA13*AC13)) -> 3627 | AG13: =SUM(L13+O13+R13+AD13) -> 26
A14: =Rooster!A15 -> Dinsdag | B14: =Rooster!B15 -> 0.66666667 | C14: =Rooster!C15 -> 60 | D14: =Rooster!D15 -> Modern 8+ | L14: 4 | M14: 2x per week | N14: =IFERROR(VLOOKUP(M14, Tarieven!$A$1:$J$150, 10, FALSE), "0") -> 279 | O14: 2 | P14: Cheer regulier +2 | Q14: =IFERROR(VLOOKUP(P14, Tarieven!$A$1:$J$150, 10, FALSE), "0") -> 270.16667 | R14: 2 | S14: 1x per week | T14: =IFERROR(VLOOKUP(S14, Tarieven!$A$1:$J$150, 10, FALSE), "0") -> 279 | W14: =IFERROR(VLOOKUP(V14, Tarieven!$A$1:$J$150, 10, FALSE), "0") -> 0 | Z14: =IFERROR(VLOOKUP(Y14, Tarieven[#ALL], 10, FALSE), "0") -> 0 | AC14: =IFERROR(VLOOKUP(AB14, Tarieven[#ALL], 10, FALSE), "0") -> 0 | AD14: =SUM(L14+O14+R14+U14+X14+AA14) -> 8 | AF14: =SUM((L14*N14)+(O14*Q14)+(R14*T14)+(U14*W14)+(X14*Z14)+(AA14*AC14)) -> 2214.3333 | AG14: =SUM(L14+O14+R14+AD14) -> 16
A15: =Rooster!A16 -> Dinsdag | B15: =Rooster!B16 -> 0.70833333 | C15: =Rooster!C16 -> 60 | D15: =Rooster!D16 -> Selectie show 8+ | F15: =Rooster!E16 -> Eigenaar | G15: =IFERROR(VLOOKUP(F15, Docenten!$A$2:$G$30, 7, FALSE), "0") -> 0 | H15: =SUM(G15/60)*C15 -> 0 | I15: =Rooster!H16 -> Santpoort Zuid | J15: =IFERROR(VLOOKUP(I15, Locaties!$A$2:$G$15, 7, FALSE), "0") -> 18.9 | K15: =SUM(J15/60)*C15 -> 18.9 | L15: 4 | M15: Cheer regulier +2 | N15: =IFERROR(VLOOKUP(M15, Tarieven!$A$1:$J$150, 10, FALSE), "0") -> 270.16667 | O15: 2 | P15: Cheer regulier +1 | Q15: =IFERROR(VLOOKUP(P15, Tarieven!$A$1:$J$150, 10, FALSE), "0") -> 289.5 | R15: 1 | S15: 2x per week | T15: =IFERROR(VLOOKUP(S15, Tarieven!$A$1:$J$150, 10, FALSE), "0") -> 279 | W15: =IFERROR(VLOOKUP(V15, Tarieven!$A$1:$J$150, 10, FALSE), "0") -> 0 | Z15: =IFERROR(VLOOKUP(Y15, Tarieven[#ALL], 10, FALSE), "0") -> 0 | AC15: =IFERROR(VLOOKUP(AB15, Tarieven[#ALL], 10, FALSE), "0") -> 0 | AD15: =SUM(L15+O15+R15+U15+X15+AA15) -> 7 | AF15: =SUM((L15*N15)+(O15*Q15)+(R15*T15)+(U15*W15)+(X15*Z15)+(AA15*AC15)) -> 1938.6667 | AG15: =SUM(L15+O15+R15+AD15) -> 14
A16: =Rooster!A17 -> Dinsdag | B16: =Rooster!B17 -> 0.75 | C16: =Rooster!C17 -> 90 | D16: =Rooster!D17 -> Selectie Cheer | F16: =Rooster!E17 -> Eigenaar | G16: =IFERROR(VLOOKUP(F16, Docenten!$A$2:$G$30, 7, FALSE), "0") -> 0 | H16: =SUM(G16/60)*C16 -> 0 | I16: =Rooster!H17 -> Santpoort Zuid | J16: =IFERROR(VLOOKUP(I16, Locaties!$A$2:$G$15, 7, FALSE), "0") -> 18.9 | K16: =SUM(J16/60)*C16 -> 28.35 | L16: 1 | M16: Cheer selecie +1 | N16: =IFERROR(VLOOKUP(M16, Tarieven!$A$1:$J$150, 10, FALSE), "0") -> 308.5 | O16: 2 | P16: Cheer selectie +2 | Q16: =IFERROR(VLOOKUP(P16, Tarieven!$A$1:$J$150, 10, FALSE), "0") -> 298.66667 | T16: =IFERROR(VLOOKUP(S16, Tarieven!$A$1:$J$150, 10, FALSE), "0") -> 0 | U16: 5 | V16: Cheer selectie onbeperkt | W16: =IFERROR(VLOOKUP(V16, Tarieven!$A$1:$J$150, 10, FALSE), "0") -> 235 | Z16: =IFERROR(VLOOKUP(Y16, Tarieven[#ALL], 10, FALSE), "0") -> 0 | AC16: =IFERROR(VLOOKUP(AB16, Tarieven[#ALL], 10, FALSE), "0") -> 0 | AD16: =SUM(L16+O16+R16+U16+X16+AA16) -> 8 | AE16: 2x per week | AF16: =SUM((L16*N16)+(O16*Q16)+(R16*T16)+(U16*W16)+(X16*Z16)+(AA16*AC16)) -> 2080.8333 | AG16: =SUM(L16+O16+R16+AD16) -> 11
A17: =Rooster!A18 -> Dinsdag | B17: =Rooster!B18 -> 0.8125 | C17: =Rooster!C18 -> 60 | D17: =Rooster!D18 -> Hiphop 15+ | F17: =Rooster!E18 -> Eigenaar | G17: =IFERROR(VLOOKUP(F17, Docenten!$A$2:$G$30, 7, FALSE), "0") -> 0 | H17: =SUM(G17/60)*C17 -> 0 | I17: =Rooster!H18 -> Santpoort Zuid | J17: =IFERROR(VLOOKUP(I17, Locaties!$A$2:$G$15, 7, FALSE), "0") -> 18.9 | K17: =SUM(J17/60)*C17 -> 18.9 | L17: 1 | M17: Cheer selectie onbeperkt | N17: =IFERROR(VLOOKUP(M17, Tarieven!$A$1:$J$150, 10, FALSE), "0") -> 235 | O17: 3 | P17: 2x per week | Q17: =IFERROR(VLOOKUP(P17, Tarieven!$A$1:$J$150, 10, FALSE), "0") -> 279 | R17: 2 | S17: 3x per week | T17: =IFERROR(VLOOKUP(S17, Tarieven!$A$1:$J$150, 10, FALSE), "0") -> 279 | U17: 1 | V17: 1x per week | W17: =IFERROR(VLOOKUP(V17, Tarieven!$A$1:$J$150, 10, FALSE), "0") -> 279 | X17: 2 | Y17: Onbeperkt | Z17: =IFERROR(VLOOKUP(Y17, Tarieven[#ALL], 10, FALSE), "0") -> 263.625 | AC17: =IFERROR(VLOOKUP(AB17, Tarieven[#ALL], 10, FALSE), "0") -> 0 | AD17: =SUM(L17+O17+R17+U17+X17+AA17) -> 9 | AE17: Cheer regulier +1 | AF17: =SUM((L17*N17)+(O17*Q17)+(R17*T17)+(U17*W17)+(X17*Z17)+(AA17*AC17)) -> 2436.25 | AG17: =SUM(L17+O17+R17+AD17) -> 15
A18: =Rooster!A19 -> Woensdag | B18: =Rooster!B19 -> 0.60416667 | C18: =Rooster!C19 -> 60 | D18: =Rooster!D19 -> Streetdance 6+ | F18: =Rooster!E19 -> Julia | G18: =IFERROR(VLOOKUP(F18, Docenten!$A$2:$G$30, 7, FALSE), "0") -> 15 | H18: =SUM(G18/60)*C18 -> 15 | I18: =Rooster!H19 -> Santpoort Noord | J18: =IFERROR(VLOOKUP(I18, Locaties!$A$2:$G$15, 7, FALSE), "0") -> 14.2 | K18: =SUM(J18/60)*C18 -> 14.2 | L18: 9 | M18: 1x per week | N18: =IFERROR(VLOOKUP(M18, Tarieven!$A$1:$J$150, 10, FALSE), "0") -> 279 | Q18: =IFERROR(VLOOKUP(P18, Tarieven!$A$1:$J$150, 10, FALSE), "0") -> 0 | T18: =IFERROR(VLOOKUP(S18, Tarieven!$A$1:$J$150, 10, FALSE), "0") -> 0 | W18: =IFERROR(VLOOKUP(V18, Tarieven!$A$1:$J$150, 10, FALSE), "0") -> 0 | Z18: =IFERROR(VLOOKUP(Y18, Tarieven[#ALL], 10, FALSE), "0") -> 0 | AC18: =IFERROR(VLOOKUP(AB18, Tarieven[#ALL], 10, FALSE), "0") -> 0 | AD18: =SUM(L18+O18+R18+U18+X18+AA18) -> 9 | AF18: =SUM((L18*N18)+(O18*Q18)+(R18*T18)+(U18*W18)+(X18*Z18)+(AA18*AC18)) -> 2511 | AG18: =SUM(L18+O18+R18+AD18) -> 18
A19: =Rooster!A20 -> Woensdag | B19: =Rooster!B20 -> 0.64583333 | C19: =Rooster!C20 -> 60 | D19: =Rooster!D20 -> Streetdance 8+ | F19: =Rooster!E20 -> Julia | G19: =IFERROR(VLOOKUP(F19, Docenten!$A$2:$G$30, 7, FALSE), "0") -> 15 | H19: =SUM(G19/60)*C19 -> 15 | I19: =Rooster!H20 -> Santpoort Noord | J19: =IFERROR(VLOOKUP(I19, Locaties!$A$2:$G$15, 7, FALSE), "0") -> 14.2 | K19: =SUM(J19/60)*C19 -> 14.2 | L19: 9 | M19: 1x per week | N19: =IFERROR(VLOOKUP(M19, Tarieven!$A$1:$J$150, 10, FALSE), "0") -> 279 | O19: 1 | P19: 2x per week | Q19: =IFERROR(VLOOKUP(P19, Tarieven!$A$1:$J$150, 10, FALSE), "0") -> 279 | R19: 1 | S19: Cheer regulier +2 | T19: =IFERROR(VLOOKUP(S19, Tarieven!$A$1:$J$150, 10, FALSE), "0") -> 270.16667 | W19: =IFERROR(VLOOKUP(V19, Tarieven!$A$1:$J$150, 10, FALSE), "0") -> 0 | Z19: =IFERROR(VLOOKUP(Y19, Tarieven[#ALL], 10, FALSE), "0") -> 0 | AC19: =IFERROR(VLOOKUP(AB19, Tarieven[#ALL], 10, FALSE), "0") -> 0 | AD19: =SUM(L19+O19+R19+U19+X19+AA19) -> 11 | AF19: =SUM((L19*N19)+(O19*Q19)+(R19*T19)+(U19*W19)+(X19*Z19)+(AA19*AC19)) -> 3060.1667 | AG19: =SUM(L19+O19+R19+AD19) -> 22
A20: =Rooster!A21 -> Woensdag | B20: =Rooster!B21 -> 0.6875 | C20: =Rooster!C21 -> 60 | D20: =Rooster!D21 -> Modern 11+ | F20: =Rooster!E21 -> Julia | G20: =IFERROR(VLOOKUP(F20, Docenten!$A$2:$G$30, 7, FALSE), "0") -> 15 | H20: =SUM(G20/60)*C20 -> 15 | I20: =Rooster!H21 -> Santpoort Noord | J20: =IFERROR(VLOOKUP(I20, Locaties!$A$2:$G$15, 7, FALSE), "0") -> 14.2 | K20: =SUM(J20/60)*C20 -> 14.2 | L20: 4 | M20: 2x per week | N20: =IFERROR(VLOOKUP(M20, Tarieven!$A$1:$J$150, 10, FALSE), "0") -> 279 | O20: 1 | P20: Cheer regulier +1 | Q20: =IFERROR(VLOOKUP(P20, Tarieven!$A$1:$J$150, 10, FALSE), "0") -> 289.5 | R20: 4 | S20: Cheer selectie onbeperkt | T20: =IFERROR(VLOOKUP(S20, Tarieven!$A$1:$J$150, 10, FALSE), "0") -> 235 | W20: =IFERROR(VLOOKUP(V20, Tarieven!$A$1:$J$150, 10, FALSE), "0") -> 0 | Z20: =IFERROR(VLOOKUP(Y20, Tarieven[#ALL], 10, FALSE), "0") -> 0 | AC20: =IFERROR(VLOOKUP(AB20, Tarieven[#ALL], 10, FALSE), "0") -> 0 | AD20: =SUM(L20+O20+R20+U20+X20+AA20) -> 9 | AF20: =SUM((L20*N20)+(O20*Q20)+(R20*T20)+(U20*W20)+(X20*Z20)+(AA20*AC20)) -> 2345.5 | AG20: =SUM(L20+O20+R20+AD20) -> 18
A21: =Rooster!A22 -> Woensdag | B21: =Rooster!B22 -> 0.72916667 | C21: =Rooster!C22 -> 60 | D21: =Rooster!D22 -> Selectie Hiphop 11+ | F21: =Rooster!E22 -> Eigenaar | G21: =IFERROR(VLOOKUP(F21, Docenten!$A$2:$G$30, 7, FALSE), "0") -> 0 | H21: =SUM(G21/60)*C21 -> 0 | I21: =Rooster!H22 -> Santpoort Noord | J21: =IFERROR(VLOOKUP(I21, Locaties!$A$2:$G$15, 7, FALSE), "0") -> 14.2 | K21: =SUM(J21/60)*C21 -> 14.2 | L21: 5 | M21: 2x per week | N21: =IFERROR(VLOOKUP(M21, Tarieven!$A$1:$J$150, 10, FALSE), "0") -> 279 | O21: 2 | P21: Cheer selecie +1 | Q21: =IFERROR(VLOOKUP(P21, Tarieven!$A$1:$J$150, 10, FALSE), "0") -> 308.5 | R21: 1 | S21: Cheer selectie +2 | T21: =IFERROR(VLOOKUP(S21, Tarieven!$A$1:$J$150, 10, FALSE), "0") -> 298.66667 | U21: 3 | V21: Cheer selectie onbeperkt | W21: =IFERROR(VLOOKUP(V21, Tarieven!$A$1:$J$150, 10, FALSE), "0") -> 235 | Z21: =IFERROR(VLOOKUP(Y21, Tarieven[#ALL], 10, FALSE), "0") -> 0 | AC21: =IFERROR(VLOOKUP(AB21, Tarieven[#ALL], 10, FALSE), "0") -> 0 | AD21: =SUM(L21+O21+R21+U21+X21+AA21) -> 11 | AE21: Cheer selecie +1 | AF21: =SUM((L21*N21)+(O21*Q21)+(R21*T21)+(U21*W21)+(X21*Z21)+(AA21*AC21)) -> 3015.6667 | AG21: =SUM(L21+O21+R21+AD21) -> 19
A22: =Rooster!A23 -> Woensdag | B22: =Rooster!B23 -> 0.77083333 | C22: =Rooster!C23 -> 60 | D22: =Rooster!D23 -> Show 12+ | F22: =Rooster!E23 -> Eigenaar | G22: =IFERROR(VLOOKUP(F22, Docenten!$A$2:$G$30, 7, FALSE), "0") -> 0 | H22: =SUM(G22/60)*C22 -> 0 | I22: =Rooster!H23 -> Santpoort Noord | J22: =IFERROR(VLOOKUP(I22, Locaties!$A$2:$G$15, 7, FALSE), "0") -> 14.2 | K22: =SUM(J22/60)*C22 -> 14.2 | L22: 1 | M22: Cheer selecie +1 | N22: =IFERROR(VLOOKUP(M22, Tarieven!$A$1:$J$150, 10, FALSE), "0") -> 308.5 | O22: 3 | P22: 1x per week | Q22: =IFERROR(VLOOKUP(P22, Tarieven!$A$1:$J$150, 10, FALSE), "0") -> 279 | R22: 1 | S22: 3x per week | T22: =IFERROR(VLOOKUP(S22, Tarieven!$A$1:$J$150, 10, FALSE), "0") -> 279 | U22: 3 | V22: Cheer selectie onbeperkt | W22: =IFERROR(VLOOKUP(V22, Tarieven!$A$1:$J$150, 10, FALSE), "0") -> 235 | X22: 1 | Y22: Cheer regulier + onbeperkt | Z22: =IFERROR(VLOOKUP(Y22, Tarieven[#ALL], 10, FALSE), "0") -> 286.75 | AC22: =IFERROR(VLOOKUP(AB22, Tarieven[#ALL], 10, FALSE), "0") -> 0 | AD22: =SUM(L22+O22+R22+U22+X22+AA22) -> 9 | AE22: 2x per week | AF22: =SUM((L22*N22)+(O22*Q22)+(R22*T22)+(U22*W22)+(X22*Z22)+(AA22*AC22)) -> 2416.25 | AG22: =SUM(L22+O22+R22+AD22) -> 14
A23: =Rooster!A24 | B23: =Rooster!B24 | C23: =Rooster!C24 | D23: =Rooster!D24 | F23: =Rooster!E24 | G23: =IFERROR(VLOOKUP(F23, Docenten!$A$2:$G$30, 7, FALSE), "0") -> 0 | H23: =SUM(G23/60)*C23 -> 0 | I23: =Rooster!H24 | J23: =IFERROR(VLOOKUP(I23, Locaties!$A$2:$G$15, 7, FALSE), "0") -> 0 | K23: =SUM(J23/60)*C23 -> 0 | N23: =IFERROR(VLOOKUP(M23, Tarieven!$A$1:$J$150, 10, FALSE), "0") -> 0 | Q23: =IFERROR(VLOOKUP(P23, Tarieven!$A$1:$J$150, 10, FALSE), "0") -> 0 | T23: =IFERROR(VLOOKUP(S23, Tarieven!$A$1:$J$150, 10, FALSE), "0") -> 0 | W23: =IFERROR(VLOOKUP(V23, Tarieven!$A$1:$J$150, 10, FALSE), "0") -> 0 | Z23: =IFERROR(VLOOKUP(Y23, Tarieven[#ALL], 10, FALSE), "0") -> 0 | AC23: =IFERROR(VLOOKUP(AB23, Tarieven[#ALL], 10, FALSE), "0") -> 0 | AD23: =SUM(L23+O23+R23+U23+X23+AA23) -> 0 | AF23: =SUM((L23*N23)+(O23*Q23)+(R23*T23)+(U23*W23)+(X23*Z23)+(AA23*AC23)) -> 0 | AG23: =SUM(L23+O23+R23+AD23) -> 0
A24: =Rooster!A25 -> Donderdag | B24: =Rooster!B25 -> 0.64583333 | C24: =Rooster!C25 -> 60 | D24: =Rooster!D25 -> Showdance 6+ | F24: =Rooster!E25 -> Eigenaar | G24: =IFERROR(VLOOKUP(F24, Docenten!$A$2:$G$30, 7, FALSE), "0") -> 0 | H24: =SUM(G24/60)*C24 -> 0 | I24: =Rooster!H25 -> Santpoort Zuid | J24: =IFERROR(VLOOKUP(I24, Locaties!$A$2:$G$15, 7, FALSE), "0") -> 18.9 | K24: =SUM(J24/60)*C24 -> 18.9 | L24: 4 | M24: 1x per week | N24: =IFERROR(VLOOKUP(M24, Tarieven!$A$1:$J$150, 10, FALSE), "0") -> 279 | Q24: =IFERROR(VLOOKUP(P24, Tarieven!$A$1:$J$150, 10, FALSE), "0") -> 0 | T24: =IFERROR(VLOOKUP(S24, Tarieven!$A$1:$J$150, 10, FALSE), "0") -> 0 | W24: =IFERROR(VLOOKUP(V24, Tarieven!$A$1:$J$150, 10, FALSE), "0") -> 0 | Z24: =IFERROR(VLOOKUP(Y24, Tarieven[#ALL], 10, FALSE), "0") -> 0 | AC24: =IFERROR(VLOOKUP(AB24, Tarieven[#ALL], 10, FALSE), "0") -> 0 | AD24: =SUM(L24+O24+R24+U24+X24+AA24) -> 4 | AF24: =SUM((L24*N24)+(O24*Q24)+(R24*T24)+(U24*W24)+(X24*Z24)+(AA24*AC24)) -> 1116 | AG24: =SUM(L24+O24+R24+AD24) -> 8
A25: =Rooster!A26 -> Donderdag | B25: =Rooster!B26 -> 0.6875 | C25: =Rooster!C26 -> 60 | D25: =Rooster!D26 -> Showdance 8+ | F25: =Rooster!E26 -> Eigenaar | G25: =IFERROR(VLOOKUP(F25, Docenten!$A$2:$G$30, 7, FALSE), "0") -> 0 | H25: =SUM(G25/60)*C25 -> 0 | I25: =Rooster!H26 -> Santpoort Zuid | J25: =IFERROR(VLOOKUP(I25, Locaties!$A$2:$G$15, 7, FALSE), "0") -> 18.9 | K25: =SUM(J25/60)*C25 -> 18.9 | M25: 1x per week | N25: =IFERROR(VLOOKUP(M25, Tarieven!$A$1:$J$150, 10, FALSE), "0") -> 279 | O25: 3 | P25: 2x per week | Q25: =IFERROR(VLOOKUP(P25, Tarieven!$A$1:$J$150, 10, FALSE), "0") -> 279 | R25: 1 | S25: Cheer regulier +2 | T25: =IFERROR(VLOOKUP(S25, Tarieven!$A$1:$J$150, 10, FALSE), "0") -> 270.16667 | W25: =IFERROR(VLOOKUP(V25, Tarieven!$A$1:$J$150, 10, FALSE), "0") -> 0 | Z25: =IFERROR(VLOOKUP(Y25, Tarieven[#ALL], 10, FALSE), "0") -> 0 | AC25: =IFERROR(VLOOKUP(AB25, Tarieven[#ALL], 10, FALSE), "0") -> 0 | AD25: =SUM(L25+O25+R25+U25+X25+AA25) -> 4 | AF25: =SUM((L25*N25)+(O25*Q25)+(R25*T25)+(U25*W25)+(X25*Z25)+(AA25*AC25)) -> 1107.1667 | AG25: =SUM(L25+O25+R25+AD25) -> 8
A26: =Rooster!A27 -> Donderdag | B26: =Rooster!B27 -> 0.72916667 | C26: =Rooster!C27 -> 60 | D26: =Rooster!D27 -> Modern 14+ | F26: =Rooster!E27 -> Eigenaar | G26: =IFERROR(VLOOKUP(F26, Docenten!$A$2:$G$30, 7, FALSE), "0") -> 0 | H26: =SUM(G26/60)*C26 -> 0 | I26: =Rooster!H27 -> Santpoort Zuid | J26: =IFERROR(VLOOKUP(I26, Locaties!$A$2:$G$15, 7, FALSE), "0") -> 18.9 | K26: =SUM(J26/60)*C26 -> 18.9 | L26: 2 | M26: 3x per week | N26: =IFERROR(VLOOKUP(M26, Tarieven!$A$1:$J$150, 10, FALSE), "0") -> 279 | Q26: =IFERROR(VLOOKUP(P26, Tarieven!$A$1:$J$150, 10, FALSE), "0") -> 0 | R26: 2 | S26: Onbeperkt | T26: =IFERROR(VLOOKUP(S26, Tarieven!$A$1:$J$150, 10, FALSE), "0") -> 263.625 | U26: 2 | V26: 1x per week | W26: =IFERROR(VLOOKUP(V26, Tarieven!$A$1:$J$150, 10, FALSE), "0") -> 279 | X26: 1 | Y26: Cheer selectie onbeperkt | Z26: =IFERROR(VLOOKUP(Y26, Tarieven[#ALL], 10, FALSE), "0") -> 235 | AC26: =IFERROR(VLOOKUP(AB26, Tarieven[#ALL], 10, FALSE), "0") -> 0 | AD26: =SUM(L26+O26+R26+U26+X26+AA26) -> 7 | AF26: =SUM((L26*N26)+(O26*Q26)+(R26*T26)+(U26*W26)+(X26*Z26)+(AA26*AC26)) -> 1878.25 | AG26: =SUM(L26+O26+R26+AD26) -> 11
A27: =Rooster!A28 -> Donderdag | B27: =Rooster!B28 -> 0.77083333 | C27: =Rooster!C28 -> 60 | D27: =Rooster!D28 -> Commercial 14+ | F27: =Rooster!E28 -> Nova | G27: =IFERROR(VLOOKUP(F27, Docenten!$A$2:$G$30, 7, FALSE), "0") -> 22.5 | H27: =SUM(G27/60)*C27 -> 22.5 | I27: =Rooster!H28 -> Santpoort Zuid | J27: =IFERROR(VLOOKUP(I27, Locaties!$A$2:$G$15, 7, FALSE), "0") -> 18.9 | K27: =SUM(J27/60)*C27 -> 18.9 | L27: 1 | M27: 1x per week | N27: =IFERROR(VLOOKUP(M27, Tarieven!$A$1:$J$150, 10, FALSE), "0") -> 279 | O27: 3 | P27: Onbeperkt | Q27: =IFERROR(VLOOKUP(P27, Tarieven!$A$1:$J$150, 10, FALSE), "0") -> 263.625 | R27: 4 | S27: 3x per week | T27: =IFERROR(VLOOKUP(S27, Tarieven!$A$1:$J$150, 10, FALSE), "0") -> 279 | U27: 1 | V27: 2x per week | W27: =IFERROR(VLOOKUP(V27, Tarieven!$A$1:$J$150, 10, FALSE), "0") -> 279 | X27: 1 | Y27: 1x per week | Z27: =IFERROR(VLOOKUP(Y27, Tarieven[#ALL], 10, FALSE), "0") -> 279 | AC27: =IFERROR(VLOOKUP(AB27, Tarieven[#ALL], 10, FALSE), "0") -> 0 | AD27: =SUM(L27+O27+R27+U27+X27+AA27) -> 10 | AF27: =SUM((L27*N27)+(O27*Q27)+(R27*T27)+(U27*W27)+(X27*Z27)+(AA27*AC27)) -> 2743.875 | AG27: =SUM(L27+O27+R27+AD27) -> 18
A28: =Rooster!A29 -> Donderdag | B28: =Rooster!B29 -> 0.8125 | C28: =Rooster!C29 -> 60 | D28: =Rooster!D29 -> Selectie Hiphop 16+ | F28: =Rooster!E29 -> Nova | G28: =IFERROR(VLOOKUP(F28, Docenten!$A$2:$G$30, 7, FALSE), "0") -> 22.5 | H28: =SUM(G28/60)*C28 -> 22.5 | I28: =Rooster!H29 -> Santpoort Zuid | J28: =IFERROR(VLOOKUP(I28, Locaties!$A$2:$G$15, 7, FALSE), "0") -> 18.9 | K28: =SUM(J28/60)*C28 -> 18.9 | L28: 2 | M28: Onbeperkt | N28: =IFERROR(VLOOKUP(M28, Tarieven!$A$1:$J$150, 10, FALSE), "0") -> 263.625 | O28: 4 | P28: 3x per week | Q28: =IFERROR(VLOOKUP(P28, Tarieven!$A$1:$J$150, 10, FALSE), "0") -> 279 | R28: 2 | S28: 2x per week | T28: =IFERROR(VLOOKUP(S28, Tarieven!$A$1:$J$150, 10, FALSE), "0") -> 279 | W28: =IFERROR(VLOOKUP(V28, Tarieven!$A$1:$J$150, 10, FALSE), "0") -> 0 | Z28: =IFERROR(VLOOKUP(Y28, Tarieven[#ALL], 10, FALSE), "0") -> 0 | AC28: =IFERROR(VLOOKUP(AB28, Tarieven[#ALL], 10, FALSE), "0") -> 0 | AD28: =SUM(L28+O28+R28+U28+X28+AA28) -> 8 | AF28: =SUM((L28*N28)+(O28*Q28)+(R28*T28)+(U28*W28)+(X28*Z28)+(AA28*AC28)) -> 2201.25 | AG28: =SUM(L28+O28+R28+AD28) -> 16
A29: =Rooster!A30 -> Donderdag | B29: =Rooster!B30 -> 0.85416667 | C29: =Rooster!C30 -> 60 | D29: =Rooster!D30 -> Modern 16+ | F29: =Rooster!E30 -> Nova | G29: =IFERROR(VLOOKUP(F29, Docenten!$A$2:$G$30, 7, FALSE), "0") -> 22.5 | H29: =SUM(G29/60)*C29 -> 22.5 | I29: =Rooster!H30 -> Santpoort Zuid | J29: =IFERROR(VLOOKUP(I29, Locaties!$A$2:$G$15, 7, FALSE), "0") -> 18.9 | K29: =SUM(J29/60)*C29 -> 18.9 | L29: 4 | M29: Onbeperkt | N29: =IFERROR(VLOOKUP(M29, Tarieven!$A$1:$J$150, 10, FALSE), "0") -> 263.625 | O29: 1 | P29: 2x per week | Q29: =IFERROR(VLOOKUP(P29, Tarieven!$A$1:$J$150, 10, FALSE), "0") -> 279 | T29: =IFERROR(VLOOKUP(S29, Tarieven!$A$1:$J$150, 10, FALSE), "0") -> 0 | W29: =IFERROR(VLOOKUP(V29, Tarieven!$A$1:$J$150, 10, FALSE), "0") -> 0 | Z29: =IFERROR(VLOOKUP(Y29, Tarieven[#ALL], 10, FALSE), "0") -> 0 | AC29: =IFERROR(VLOOKUP(AB29, Tarieven[#ALL], 10, FALSE), "0") -> 0 | AD29: =SUM(L29+O29+R29+U29+X29+AA29) -> 5 | AF29: =SUM((L29*N29)+(O29*Q29)+(R29*T29)+(U29*W29)+(X29*Z29)+(AA29*AC29)) -> 1333.5 | AG29: =SUM(L29+O29+R29+AD29) -> 10
A30: =Rooster!A31 -> Vrijdag | B30: =Rooster!B31 -> 0.625 | C30: =Rooster!C31 -> 60 | D30: =Rooster!D31 -> Selectie Hiphop 8+ | F30: =Rooster!E31 -> Eigenaar | G30: =IFERROR(VLOOKUP(F30, Docenten!$A$2:$G$30, 7, FALSE), "0") -> 0 | H30: =SUM(G30/60)*C30 -> 0 | I30: =Rooster!H31 -> Santpoort Zuid | J30: =IFERROR(VLOOKUP(I30, Locaties!$A$2:$G$15, 7, FALSE), "0") -> 18.9 | K30: =SUM(J30/60)*C30 -> 18.9 | N30: =IFERROR(VLOOKUP(M30, Tarieven!$A$1:$J$150, 10, FALSE), "0") -> 0 | O30: 3 | P30: Cheer regulier +2 | Q30: =IFERROR(VLOOKUP(P30, Tarieven!$A$1:$J$150, 10, FALSE), "0") -> 270.16667 | R30: 1 | S30: 2x per week | T30: =IFERROR(VLOOKUP(S30, Tarieven!$A$1:$J$150, 10, FALSE), "0") -> 279 | W30: =IFERROR(VLOOKUP(V30, Tarieven!$A$1:$J$150, 10, FALSE), "0") -> 0 | Z30: =IFERROR(VLOOKUP(Y30, Tarieven[#ALL], 10, FALSE), "0") -> 0 | AC30: =IFERROR(VLOOKUP(AB30, Tarieven[#ALL], 10, FALSE), "0") -> 0 | AD30: =SUM(L30+O30+R30+U30+X30+AA30) -> 4 | AF30: =SUM((L30*N30)+(O30*Q30)+(R30*T30)+(U30*W30)+(X30*Z30)+(AA30*AC30)) -> 1089.5 | AG30: =SUM(L30+O30+R30+AD30) -> 8
A31: =Rooster!A32 -> Vrijdag | B31: =Rooster!B32 -> 0.66666667 | C31: =Rooster!C32 -> 60 | D31: =Rooster!D32 -> Cheer 8+ | F31: =Rooster!E32 -> Eigenaar | G31: =IFERROR(VLOOKUP(F31, Docenten!$A$2:$G$30, 7, FALSE), "0") -> 0 | H31: =SUM(G31/60)*C31 -> 0 | I31: =Rooster!H32 -> Santpoort Zuid | J31: =IFERROR(VLOOKUP(I31, Locaties!$A$2:$G$15, 7, FALSE), "0") -> 18.9 | K31: =SUM(J31/60)*C31 -> 18.9 | L31: 2 | M31: Cheer regulier +1 | N31: =IFERROR(VLOOKUP(M31, Tarieven!$A$1:$J$150, 10, FALSE), "0") -> 289.5 | O31: 6 | P31: Cheer regulier +2 | Q31: =IFERROR(VLOOKUP(P31, Tarieven!$A$1:$J$150, 10, FALSE), "0") -> 270.16667 | R31: 3 | S31: Cheer regulier | T31: =IFERROR(VLOOKUP(S31, Tarieven!$A$1:$J$150, 10, FALSE), "0") -> 300 | W31: =IFERROR(VLOOKUP(V31, Tarieven!$A$1:$J$150, 10, FALSE), "0") -> 0 | Z31: =IFERROR(VLOOKUP(Y31, Tarieven[#ALL], 10, FALSE), "0") -> 0 | AC31: =IFERROR(VLOOKUP(AB31, Tarieven[#ALL], 10, FALSE), "0") -> 0 | AD31: =SUM(L31+O31+R31+U31+X31+AA31) -> 11 | AF31: =SUM((L31*N31)+(O31*Q31)+(R31*T31)+(U31*W31)+(X31*Z31)+(AA31*AC31)) -> 3100 | AG31: =SUM(L31+O31+R31+AD31) -> 22
A32: =Rooster!A33 -> Vrijdag | B32: =Rooster!B33 -> 0.70833333 | C32: =Rooster!C33 -> 60 | D32: =Rooster!D33 -> Cheer 12+ | F32: =Rooster!E33 -> Eigenaar | G32: =IFERROR(VLOOKUP(F32, Docenten!$A$2:$G$30, 7, FALSE), "0") -> 0 | H32: =SUM(G32/60)*C32 -> 0 | I32: =Rooster!H33 -> Santpoort Zuid | J32: =IFERROR(VLOOKUP(I32, Locaties!$A$2:$G$15, 7, FALSE), "0") -> 18.9 | K32: =SUM(J32/60)*C32 -> 18.9 | L32: 2 | M32: Cheer regulier +1 | N32: =IFERROR(VLOOKUP(M32, Tarieven!$A$1:$J$150, 10, FALSE), "0") -> 289.5 | O32: 1 | P32: Cheer regulier + onbeperkt | Q32: =IFERROR(VLOOKUP(P32, Tarieven!$A$1:$J$150, 10, FALSE), "0") -> 286.75 | R32: 1 | S32: Cheer selectie onbeperkt | U32: 1 | V32: Geen betaling | W32: =IFERROR(VLOOKUP(V32, Tarieven!$A$1:$J$150, 10, FALSE), "0") -> 0 | Z32: =IFERROR(VLOOKUP(Y32, Tarieven[#ALL], 10, FALSE), "0") -> 0 | AC32: =IFERROR(VLOOKUP(AB32, Tarieven[#ALL], 10, FALSE), "0") -> 0 | AD32: =SUM(L32+O32+R32+U32+X32+AA32) -> 5 | AF32: =SUM((L32*N32)+(O32*Q32)+(R32*T32)+(U32*W32)+(X32*Z32)+(AA32*AC32)) -> 865.75 | AG32: =SUM(L32+O32+R32+AD32) -> 9
A33: =Rooster!A34 -> Vrijdag | B33: =Rooster!B34 -> 0.75 | C33: =Rooster!C34 -> 60 | D33: =Rooster!D34 -> Urban-pop-Show 11+ | F33: =Rooster!E34 -> Eigenaar | G33: =IFERROR(VLOOKUP(F33, Docenten!$A$2:$G$30, 7, FALSE), "0") -> 0 | H33: =SUM(G33/60)*C33 -> 0 | I33: =Rooster!H34 -> Santpoort Noord | J33: =IFERROR(VLOOKUP(I33, Locaties!$A$2:$G$15, 7, FALSE), "0") -> 14.2 | K33: =SUM(J33/60)*C33 -> 14.2 | L33: 4 | M33: 1x per week | N33: =IFERROR(VLOOKUP(M33, Tarieven!$A$1:$J$150, 10, FALSE), "0") -> 279 | O33: 1 | P33: Cheer selectie +2 | Q33: =IFERROR(VLOOKUP(P33, Tarieven!$A$1:$J$150, 10, FALSE), "0") -> 298.66667 | R33: 1 | S33: 2x per week | T33: =IFERROR(VLOOKUP(S33, Tarieven!$A$1:$J$150, 10, FALSE), "0") -> 279 | U33: 1 | V33: Cheer regulier +1 | W33: =IFERROR(VLOOKUP(V33, Tarieven!$A$1:$J$150, 10, FALSE), "0") -> 289.5 | X33: 1 | Y33: 1x per week | Z33: =IFERROR(VLOOKUP(Y33, Tarieven[#ALL], 10, FALSE), "0") -> 279 | AC33: =IFERROR(VLOOKUP(AB33, Tarieven[#ALL], 10, FALSE), "0") -> 0 | AD33: =SUM(L33+O33+R33+U33+X33+AA33) -> 8 | AF33: =SUM((L33*N33)+(O33*Q33)+(R33*T33)+(U33*W33)+(X33*Z33)+(AA33*AC33)) -> 2262.1667 | AG33: =SUM(L33+O33+R33+AD33) -> 14
A34: =Rooster!A35 -> Zaterdag | B34: =Rooster!B35 -> 0.375 | C34: =Rooster!C35 -> 60 | D34: =Rooster!D35 -> Peuters | F34: =Rooster!E35 -> Frederique | G34: =IFERROR(VLOOKUP(F34, Docenten!$A$2:$G$30, 7, FALSE), "0") -> 12.5 | H34: =SUM(G34/60)*C34 -> 12.5 | I34: =Rooster!H35 -> Santpoort Noord | J34: =IFERROR(VLOOKUP(I34, Locaties!$A$2:$G$15, 7, FALSE), "0") -> 14.2 | K34: =SUM(J34/60)*C34 -> 14.2 | L34: 4 | M34: 1x per week | N34: =IFERROR(VLOOKUP(M34, Tarieven!$A$1:$J$150, 10, FALSE), "0") -> 279 | Q34: =IFERROR(VLOOKUP(P34, Tarieven!$A$1:$J$150, 10, FALSE), "0") -> 0 | T34: =IFERROR(VLOOKUP(S34, Tarieven!$A$1:$J$150, 10, FALSE), "0") -> 0 | W34: =IFERROR(VLOOKUP(V34, Tarieven!$A$1:$J$150, 10, FALSE), "0") -> 0 | Z34: =IFERROR(VLOOKUP(Y34, Tarieven[#ALL], 10, FALSE), "0") -> 0 | AC34: =IFERROR(VLOOKUP(AB34, Tarieven[#ALL], 10, FALSE), "0") -> 0 | AD34: =SUM(L34+O34+R34+U34+X34+AA34) -> 4 | AF34: =SUM((L34*N34)+(O34*Q34)+(R34*T34)+(U34*W34)+(X34*Z34)+(AA34*AC34)) -> 1116 | AG34: =SUM(L34+O34+R34+AD34) -> 8
A35: =Rooster!A36 -> Zaterdag | B35: =Rooster!B36 -> 0.40625 | C35: =Rooster!C36 -> 60 | D35: =Rooster!D36 -> Kleuters | F35: =Rooster!E36 -> Frederique | G35: =IFERROR(VLOOKUP(F35, Docenten!$A$2:$G$30, 7, FALSE), "0") -> 12.5 | H35: =SUM(G35/60)*C35 -> 12.5 | I35: =Rooster!H36 -> Santpoort Noord | J35: =IFERROR(VLOOKUP(I35, Locaties!$A$2:$G$15, 7, FALSE), "0") -> 14.2 | K35: =SUM(J35/60)*C35 -> 14.2 | L35: 5 | M35: 1x per week | N35: =IFERROR(VLOOKUP(M35, Tarieven!$A$1:$J$150, 10, FALSE), "0") -> 279 | Q35: =IFERROR(VLOOKUP(P35, Tarieven!$A$1:$J$150, 10, FALSE), "0") -> 0 | T35: =IFERROR(VLOOKUP(S35, Tarieven!$A$1:$J$150, 10, FALSE), "0") -> 0 | W35: =IFERROR(VLOOKUP(V35, Tarieven!$A$1:$J$150, 10, FALSE), "0") -> 0 | Z35: =IFERROR(VLOOKUP(Y35, Tarieven[#ALL], 10, FALSE), "0") -> 0 | AC35: =IFERROR(VLOOKUP(AB35, Tarieven[#ALL], 10, FALSE), "0") -> 0 | AD35: =SUM(L35+O35+R35+U35+X35+AA35) -> 5 | AF35: =SUM((L35*N35)+(O35*Q35)+(R35*T35)+(U35*W35)+(X35*Z35)+(AA35*AC35)) -> 1395 | AG35: =SUM(L35+O35+R35+AD35) -> 10
A36: =Rooster!A37 -> Zaterdag | B36: =Rooster!B37 -> 0.4375 | C36: =Rooster!C37 -> 60 | D36: =Rooster!D37 -> Showdance 5-6 | F36: =Rooster!E37 -> Frederique | G36: =IFERROR(VLOOKUP(F36, Docenten!$A$2:$G$30, 7, FALSE), "0") -> 12.5 | H36: =SUM(G36/60)*C36 -> 12.5 | I36: =Rooster!H37 -> Santpoort Noord | J36: =IFERROR(VLOOKUP(I36, Locaties!$A$2:$G$15, 7, FALSE), "0") -> 14.2 | K36: =SUM(J36/60)*C36 -> 14.2 | L36: 7 | M36: 1x per week | N36: =IFERROR(VLOOKUP(M36, Tarieven!$A$1:$J$150, 10, FALSE), "0") -> 279 | O36: 2 | P36: Jeugdfonds | Q36: =IFERROR(VLOOKUP(P36, Tarieven!$A$1:$J$150, 10, FALSE), "0") -> 261 | T36: =IFERROR(VLOOKUP(S36, Tarieven!$A$1:$J$150, 10, FALSE), "0") -> 0 | W36: =IFERROR(VLOOKUP(V36, Tarieven!$A$1:$J$150, 10, FALSE), "0") -> 0 | Z36: =IFERROR(VLOOKUP(Y36, Tarieven[#ALL], 10, FALSE), "0") -> 0 | AC36: =IFERROR(VLOOKUP(AB36, Tarieven[#ALL], 10, FALSE), "0") -> 0 | AD36: =SUM(L36+O36+R36+U36+X36+AA36) -> 9 | AF36: =SUM((L36*N36)+(O36*Q36)+(R36*T36)+(U36*W36)+(X36*Z36)+(AA36*AC36)) -> 2475 | AG36: =SUM(L36+O36+R36+AD36) -> 18
A37: =Rooster!A38 -> Zaterdag | B37: =Rooster!B38 -> 0.47916667 | C37: =Rooster!C38 -> 60 | D37: =Rooster!D38 -> Showdance 7+ | F37: =Rooster!E38 -> Frederique | G37: =IFERROR(VLOOKUP(F37, Docenten!$A$2:$G$30, 7, FALSE), "0") -> 12.5 | H37: =SUM(G37/60)*C37 -> 12.5 | I37: =Rooster!H38 -> Santpoort Noord | J37: =IFERROR(VLOOKUP(I37, Locaties!$A$2:$G$15, 7, FALSE), "0") -> 14.2 | K37: =SUM(J37/60)*C37 -> 14.2 | L37: 3 | M37: 1x per week | N37: =IFERROR(VLOOKUP(M37, Tarieven!$A$1:$J$150, 10, FALSE), "0") -> 279 | O37: 1 | P37: 2x per week | Q37: =IFERROR(VLOOKUP(P37, Tarieven!$A$1:$J$150, 10, FALSE), "0") -> 279 | T37: =IFERROR(VLOOKUP(S37, Tarieven!$A$1:$J$150, 10, FALSE), "0") -> 0 | W37: =IFERROR(VLOOKUP(V37, Tarieven!$A$1:$J$150, 10, FALSE), "0") -> 0 | Z37: =IFERROR(VLOOKUP(Y37, Tarieven[#ALL], 10, FALSE), "0") -> 0 | AC37: =IFERROR(VLOOKUP(AB37, Tarieven[#ALL], 10, FALSE), "0") -> 0 | AD37: =SUM(L37+O37+R37+U37+X37+AA37) -> 4 | AF37: =SUM((L37*N37)+(O37*Q37)+(R37*T37)+(U37*W37)+(X37*Z37)+(AA37*AC37)) -> 1116 | AG37: =SUM(L37+O37+R37+AD37) -> 8
A38: =Rooster!A39 -> Zaterdag | B38: =Rooster!B39 -> 0.41666667 | C38: =Rooster!C39 -> 60 | D38: =Rooster!D39 -> Peuters | F38: =Rooster!E39 -> Tess | G38: =IFERROR(VLOOKUP(F38, Docenten!$A$2:$G$30, 7, FALSE), "0") -> 17.5 | H38: =SUM(G38/60)*C38 -> 17.5 | I38: =Rooster!H39 -> Santpoort Zuid | J38: =IFERROR(VLOOKUP(I38, Locaties!$A$2:$G$15, 7, FALSE), "0") -> 18.9 | K38: =SUM(J38/60)*C38 -> 18.9 | N38: =IFERROR(VLOOKUP(M38, Tarieven!$A$1:$J$150, 10, FALSE), "0") -> 0 | Q38: =IFERROR(VLOOKUP(P38, Tarieven!$A$1:$J$150, 10, FALSE), "0") -> 0 | T38: =IFERROR(VLOOKUP(S38, Tarieven!$A$1:$J$150, 10, FALSE), "0") -> 0 | W38: =IFERROR(VLOOKUP(V38, Tarieven!$A$1:$J$150, 10, FALSE), "0") -> 0 | Z38: =IFERROR(VLOOKUP(Y38, Tarieven[#ALL], 10, FALSE), "0") -> 0 | AC38: =IFERROR(VLOOKUP(AB38, Tarieven[#ALL], 10, FALSE), "0") -> 0 | AD38: =SUM(L38+O38+R38+U38+X38+AA38) -> 0 | AF38: =SUM((L38*N38)+(O38*Q38)+(R38*T38)+(U38*W38)+(X38*Z38)+(AA38*AC38)) -> 0 | AG38: =SUM(L38+O38+R38+AD38) -> 0
A39: =Rooster!A40 -> Zaterdag | B39: =Rooster!B40 -> 0.44791667 | C39: =Rooster!C40 -> 60 | D39: =Rooster!D40 -> Kleuters | F39: =Rooster!E40 -> Tess | G39: =IFERROR(VLOOKUP(F39, Docenten!$A$2:$G$30, 7, FALSE), "0") -> 17.5 | H39: =SUM(G39/60)*C39 -> 17.5 | I39: =Rooster!H40 -> Santpoort Zuid | J39: =IFERROR(VLOOKUP(I39, Locaties!$A$2:$G$15, 7, FALSE), "0") -> 18.9 | K39: =SUM(J39/60)*C39 -> 18.9 | N39: =IFERROR(VLOOKUP(M39, Tarieven!$A$1:$J$150, 10, FALSE), "0") -> 0 | Q39: =IFERROR(VLOOKUP(P39, Tarieven!$A$1:$J$150, 10, FALSE), "0") -> 0 | T39: =IFERROR(VLOOKUP(S39, Tarieven!$A$1:$J$150, 10, FALSE), "0") -> 0 | W39: =IFERROR(VLOOKUP(V39, Tarieven!$A$1:$J$150, 10, FALSE), "0") -> 0 | Z39: =IFERROR(VLOOKUP(Y39, Tarieven[#ALL], 10, FALSE), "0") -> 0 | AC39: =IFERROR(VLOOKUP(AB39, Tarieven[#ALL], 10, FALSE), "0") -> 0 | AD39: =SUM(L39+O39+R39+U39+X39+AA39) -> 0 | AF39: =SUM((L39*N39)+(O39*Q39)+(R39*T39)+(U39*W39)+(X39*Z39)+(AA39*AC39)) -> 0 | AG39: =SUM(L39+O39+R39+AD39) -> 0
A40: =Rooster!A41 | B40: =Rooster!B41 | C40: =Rooster!C41 | D40: =Rooster!D41 | F40: =Rooster!E41 | G40: =IFERROR(VLOOKUP(F40, Docenten!$A$2:$G$30, 7, FALSE), "0") -> 0 | H40: =SUM(G40/60)*C40 -> 0 | I40: =Rooster!H41 | J40: =IFERROR(VLOOKUP(I40, Locaties!$A$2:$G$15, 7, FALSE), "0") -> 0 | K40: =SUM(J40/60)*C40 -> 0 | N40: =IFERROR(VLOOKUP(M40, Tarieven!$A$1:$J$150, 10, FALSE), "0") -> 0 | Q40: =IFERROR(VLOOKUP(P40, Tarieven!$A$1:$J$150, 10, FALSE), "0") -> 0 | T40: =IFERROR(VLOOKUP(S40, Tarieven!$A$1:$J$150, 10, FALSE), "0") -> 0 | W40: =IFERROR(VLOOKUP(V40, Tarieven!$A$1:$J$150, 10, FALSE), "0") -> 0 | Z40: =IFERROR(VLOOKUP(Y40, Tarieven[#ALL], 10, FALSE), "0") -> 0 | AC40: =IFERROR(VLOOKUP(AB40, Tarieven[#ALL], 10, FALSE), "0") -> 0 | AD40: =SUM(L40+O40+R40+U40+X40+AA40) -> 0 | AF40: =SUM((L40*N40)+(O40*Q40)+(R40*T40)+(U40*W40)+(X40*Z40)+(AA40*AC40)) -> 0 | AG40: =SUM(L40+O40+R40+AD40) -> 0
A41: =Rooster!A42 | B41: =Rooster!B42 | C41: =Rooster!C42 | D41: =Rooster!D42 | F41: =Rooster!E42 | G41: =IFERROR(VLOOKUP(F41, Docenten!$A$2:$G$30, 7, FALSE), "0") -> 0 | H41: =SUM(G41/60)*C41 -> 0 | I41: =Rooster!H42 | J41: =IFERROR(VLOOKUP(I41, Locaties!$A$2:$G$15, 7, FALSE), "0") -> 0 | K41: =SUM(J41/60)*C41 -> 0 | N41: =IFERROR(VLOOKUP(M41, Tarieven!$A$1:$J$150, 10, FALSE), "0") -> 0 | Q41: =IFERROR(VLOOKUP(P41, Tarieven!$A$1:$J$150, 10, FALSE), "0") -> 0 | T41: =IFERROR(VLOOKUP(S41, Tarieven!$A$1:$J$150, 10, FALSE), "0") -> 0 | W41: =IFERROR(VLOOKUP(V41, Tarieven!$A$1:$J$150, 10, FALSE), "0") -> 0 | Z41: =IFERROR(VLOOKUP(Y41, Tarieven[#ALL], 10, FALSE), "0") -> 0 | AC41: =IFERROR(VLOOKUP(AB41, Tarieven[#ALL], 10, FALSE), "0") -> 0 | AD41: =SUM(L41+O41+R41+U41+X41+AA41) -> 0 | AF41: =SUM((L41*N41)+(O41*Q41)+(R41*T41)+(U41*W41)+(X41*Z41)+(AA41*AC41)) -> 0 | AG41: =SUM(L41+O41+R41+AD41) -> 0
A42: =Rooster!A43 -> Maandag | B42: =Rooster!B43 -> 0.39583333 | C42: =Rooster!C43 -> 60 | D42: =Rooster!D43 -> Kinderopvang | F42: =Rooster!E43 -> Opvang T | G42: =IFERROR(VLOOKUP(F42, Docenten!$A$2:$G$30, 7, FALSE), "0") -> 45 | H42: =SUM(G42/60)*C42 -> 45 | I42: =Rooster!H43 | J42: =IFERROR(VLOOKUP(I42, Locaties!$A$2:$G$15, 7, FALSE), "0") -> 0 | K42: =SUM(J42/60)*C42 -> 0 | N42: =IFERROR(VLOOKUP(M42, Tarieven!$A$1:$J$150, 10, FALSE), "0") -> 0 | Q42: =IFERROR(VLOOKUP(P42, Tarieven!$A$1:$J$150, 10, FALSE), "0") -> 0 | T42: =IFERROR(VLOOKUP(S42, Tarieven!$A$1:$J$150, 10, FALSE), "0") -> 0 | W42: =IFERROR(VLOOKUP(V42, Tarieven!$A$1:$J$150, 10, FALSE), "0") -> 0 | Z42: =IFERROR(VLOOKUP(Y42, Tarieven[#ALL], 10, FALSE), "0") -> 0 | AC42: =IFERROR(VLOOKUP(AB42, Tarieven[#ALL], 10, FALSE), "0") -> 0 | AD42: =SUM(L42+O42+R42+U42+X42+AA42) -> 0 | AF42: =SUM((L42*N42)+(O42*Q42)+(R42*T42)+(U42*W42)+(X42*Z42)+(AA42*AC42)) -> 0 | AG42: =SUM(L42+O42+R42+AD42) -> 0
F43: =Rooster!E44 -> Eigenaar | G43: =IFERROR(VLOOKUP(F43, Docenten!$A$2:$G$30, 7, FALSE), "0") -> 0 | H43: =SUM(G43/60)*C43 -> 0 | I43: =Rooster!H44 | J43: =IFERROR(VLOOKUP(I43, Locaties!$A$2:$G$15, 7, FALSE), "0") -> 0 | K43: =SUM(J43/60)*C43 -> 0 | N43: =IFERROR(VLOOKUP(M43, Tarieven!$A$1:$J$150, 10, FALSE), "0") -> 0 | Q43: =IFERROR(VLOOKUP(P43, Tarieven!$A$1:$J$150, 10, FALSE), "0") -> 0 | T43: =IFERROR(VLOOKUP(S43, Tarieven!$A$1:$J$150, 10, FALSE), "0") -> 0 | W43: =IFERROR(VLOOKUP(V43, Tarieven!$A$1:$J$150, 10, FALSE), "0") -> 0 | Z43: =IFERROR(VLOOKUP(Y43, Tarieven[#ALL], 10, FALSE), "0") -> 0 | AC43: =IFERROR(VLOOKUP(AB43, Tarieven[#ALL], 10, FALSE), "0") -> 0 | AD43: =SUM(L43+O43+R43+U43+X43+AA43) -> 0 | AF43: =SUM((L43*N43)+(O43*Q43)+(R43*T43)+(U43*W43)+(X43*Z43)+(AA43*AC43)) -> 0 | AG43: =SUM(L43+O43+R43+AD43) -> 0
F44: =Rooster!E45 -> Eigenaar | G44: =IFERROR(VLOOKUP(F44, Docenten!$A$2:$G$30, 7, FALSE), "0") -> 0 | H44: =SUM(G44/60)*C44 -> 0 | I44: =Rooster!H45 | J44: =IFERROR(VLOOKUP(I44, Locaties!$A$2:$G$15, 7, FALSE), "0") -> 0 | K44: =SUM(J44/60)*C44 -> 0 | N44: =IFERROR(VLOOKUP(M44, Tarieven!$A$1:$J$150, 10, FALSE), "0") -> 0 | Q44: =IFERROR(VLOOKUP(P44, Tarieven!$A$1:$J$150, 10, FALSE), "0") -> 0 | T44: =IFERROR(VLOOKUP(S44, Tarieven!$A$1:$J$150, 10, FALSE), "0") -> 0 | W44: =IFERROR(VLOOKUP(V44, Tarieven!$A$1:$J$150, 10, FALSE), "0") -> 0 | Z44: =IFERROR(VLOOKUP(Y44, Tarieven[#ALL], 10, FALSE), "0") -> 0 | AC44: =IFERROR(VLOOKUP(AB44, Tarieven[#ALL], 10, FALSE), "0") -> 0 | AD44: =SUM(L44+O44+R44+U44+X44+AA44) -> 0 | AF44: =SUM((L44*N44)+(O44*Q44)+(R44*T44)+(U44*W44)+(X44*Z44)+(AA44*AC44)) -> 0 | AG44: =SUM(L44+O44+R44+AD44) -> 0
A45: =Rooster!A46 | B45: =Rooster!B46 | C45: =Rooster!C46 | D45: =Rooster!D46 | F45: =Rooster!E46 | G45: =IFERROR(VLOOKUP(F45, Docenten!$A$2:$G$30, 7, FALSE), "0") -> 0 | H45: =SUM(G45/60)*C45 -> 0 | I45: =Rooster!H46 | J45: =IFERROR(VLOOKUP(I45, Locaties!$A$2:$G$15, 7, FALSE), "0") -> 0 | K45: =SUM(J45/60)*C45 -> 0 | N45: =IFERROR(VLOOKUP(M45, Tarieven!$A$1:$J$150, 10, FALSE), "0") -> 0 | Q45: =IFERROR(VLOOKUP(P45, Tarieven!$A$1:$J$150, 10, FALSE), "0") -> 0 | T45: =IFERROR(VLOOKUP(S45, Tarieven!$A$1:$J$150, 10, FALSE), "0") -> 0 | W45: =IFERROR(VLOOKUP(V45, Tarieven!$A$1:$J$150, 10, FALSE), "0") -> 0 | Z45: =IFERROR(VLOOKUP(Y45, Tarieven[#ALL], 10, FALSE), "0") -> 0 | AC45: =IFERROR(VLOOKUP(AB45, Tarieven[#ALL], 10, FALSE), "0") -> 0 | AD45: =SUM(L45+O45+R45+U45+X45+AA45) -> 0 | AF45: =SUM((L45*N45)+(O45*Q45)+(R45*T45)+(U45*W45)+(X45*Z45)+(AA45*AC45)) -> 0 | AG45: =SUM(L45+O45+R45+AD45) -> 0
A46: =Rooster!A47 | B46: =Rooster!B47 | C46: =Rooster!C47 | D46: =Rooster!D47 | F46: =Rooster!E47 | G46: =IFERROR(VLOOKUP(F46, Docenten!$A$2:$G$30, 7, FALSE), "0") -> 0 | H46: =SUM(G46/60)*C46 -> 0 | I46: =Rooster!H47 | J46: =IFERROR(VLOOKUP(I46, Locaties!$A$2:$G$15, 7, FALSE), "0") -> 0 | K46: =SUM(J46/60)*C46 -> 0 | N46: =IFERROR(VLOOKUP(M46, Tarieven!$A$1:$J$150, 10, FALSE), "0") -> 0 | Q46: =IFERROR(VLOOKUP(P46, Tarieven!$A$1:$J$150, 10, FALSE), "0") -> 0 | T46: =IFERROR(VLOOKUP(S46, Tarieven!$A$1:$J$150, 10, FALSE), "0") -> 0 | W46: =IFERROR(VLOOKUP(V46, Tarieven!$A$1:$J$150, 10, FALSE), "0") -> 0 | Z46: =IFERROR(VLOOKUP(Y46, Tarieven[#ALL], 10, FALSE), "0") -> 0 | AC46: =IFERROR(VLOOKUP(AB46, Tarieven[#ALL], 10, FALSE), "0") -> 0 | AD46: =SUM(L46+O46+R46+U46+X46+AA46) -> 0 | AF46: =SUM((L46*N46)+(O46*Q46)+(R46*T46)+(U46*W46)+(X46*Z46)+(AA46*AC46)) -> 0 | AG46: =SUM(L46+O46+R46+AD46) -> 0
A47: =Rooster!A48 -> Donderdag | B47: =Rooster!B48 -> 0.75 | C47: =Rooster!C48 -> 60 | D47: =Rooster!D48 -> Turnen 6+ | F47: =Rooster!E48 -> Dion + 3 | G47: =IFERROR(VLOOKUP(F47, Docenten!$A$2:$G$30, 7, FALSE), "0") -> 34 | H47: =SUM(G47/60)*C47 -> 34 | I47: =Rooster!H48 -> Santpoort Noord | J47: =IFERROR(VLOOKUP(I47, Locaties!$A$2:$G$15, 7, FALSE), "0") -> 14.2 | K47: =SUM(J47/60)*C47 -> 14.2 | N47: =IFERROR(VLOOKUP(M47, Tarieven!$A$1:$J$150, 10, FALSE), "0") -> 0 | Q47: =IFERROR(VLOOKUP(P47, Tarieven!$A$1:$J$150, 10, FALSE), "0") -> 0 | T47: =IFERROR(VLOOKUP(S47, Tarieven!$A$1:$J$150, 10, FALSE), "0") -> 0 | W47: =IFERROR(VLOOKUP(V47, Tarieven!$A$1:$J$150, 10, FALSE), "0") -> 0 | Z47: =IFERROR(VLOOKUP(Y47, Tarieven[#ALL], 10, FALSE), "0") -> 0 | AC47: =IFERROR(VLOOKUP(AB47, Tarieven[#ALL], 10, FALSE), "0") -> 0 | AD47: =SUM(L47+O47+R47+U47+X47+AA47) -> 0 | AF47: =SUM((L47*N47)+(O47*Q47)+(R47*T47)+(U47*W47)+(X47*Z47)+(AA47*AC47)) -> 0 | AG47: =SUM(L47+O47+R47+AD47) -> 0
A48: =Rooster!A49 -> Donderdag | B48: =Rooster!B49 -> 0.79166667 | C48: =Rooster!C49 -> 60 | D48: =Rooster!D49 -> Turnen 12+ | F48: =Rooster!E49 -> Dion + 3 | G48: =IFERROR(VLOOKUP(F48, Docenten!$A$2:$G$30, 7, FALSE), "0") -> 34 | H48: =SUM(G48/60)*C48 -> 34 | I48: =Rooster!H49 -> Santpoort Noord | J48: =IFERROR(VLOOKUP(I48, Locaties!$A$2:$G$15, 7, FALSE), "0") -> 14.2 | K48: =SUM(J48/60)*C48 -> 14.2 | N48: =IFERROR(VLOOKUP(M48, Tarieven!$A$1:$J$150, 10, FALSE), "0") -> 0 | Q48: =IFERROR(VLOOKUP(P48, Tarieven!$A$1:$J$150, 10, FALSE), "0") -> 0 | T48: =IFERROR(VLOOKUP(S48, Tarieven!$A$1:$J$150, 10, FALSE), "0") -> 0 | W48: =IFERROR(VLOOKUP(V48, Tarieven!$A$1:$J$150, 10, FALSE), "0") -> 0 | Z48: =IFERROR(VLOOKUP(Y48, Tarieven[#ALL], 10, FALSE), "0") -> 0 | AC48: =IFERROR(VLOOKUP(AB48, Tarieven[#ALL], 10, FALSE), "0") -> 0 | AD48: =SUM(L48+O48+R48+U48+X48+AA48) -> 0 | AF48: =SUM((L48*N48)+(O48*Q48)+(R48*T48)+(U48*W48)+(X48*Z48)+(AA48*AC48)) -> 0 | AG48: =SUM(L48+O48+R48+AD48) -> 0
A49: =Rooster!A50 | B49: =Rooster!B50 | C49: =Rooster!C50 | D49: =Rooster!D50 | F49: =Rooster!E50 | G49: =IFERROR(VLOOKUP(F49, Docenten!$A$2:$G$30, 7, FALSE), "0") -> 0 | H49: =SUM(G49/60)*C49 -> 0 | I49: =Rooster!H50 | J49: =IFERROR(VLOOKUP(I49, Locaties!$A$2:$G$15, 7, FALSE), "0") -> 0 | K49: =SUM(J49/60)*C49 -> 0 | N49: =IFERROR(VLOOKUP(M49, Tarieven!$A$1:$J$150, 10, FALSE), "0") -> 0 | Q49: =IFERROR(VLOOKUP(P49, Tarieven!$A$1:$J$150, 10, FALSE), "0") -> 0 | T49: =IFERROR(VLOOKUP(S49, Tarieven!$A$1:$J$150, 10, FALSE), "0") -> 0 | W49: =IFERROR(VLOOKUP(V49, Tarieven!$A$1:$J$150, 10, FALSE), "0") -> 0 | Z49: =IFERROR(VLOOKUP(Y49, Tarieven[#ALL], 10, FALSE), "0") -> 0 | AC49: =IFERROR(VLOOKUP(AB49, Tarieven[#ALL], 10, FALSE), "0") -> 0 | AD49: =SUM(L49+O49+R49+U49+X49+AA49) -> 0 | AF49: =SUM((L49*N49)+(O49*Q49)+(R49*T49)+(U49*W49)+(X49*Z49)+(AA49*AC49)) -> 0 | AG49: =SUM(L49+O49+R49+AD49) -> 0
A50: =Rooster!A51 | B50: =Rooster!B51 | C50: =Rooster!C51 | D50: =Rooster!D51 | F50: =Rooster!E51 | G50: =IFERROR(VLOOKUP(F50, Docenten!$A$2:$G$30, 7, FALSE), "0") -> 0 | H50: =SUM(G50/60)*C50 -> 0 | I50: =Rooster!H51 | J50: =IFERROR(VLOOKUP(I50, Locaties!$A$2:$G$15, 7, FALSE), "0") -> 0 | K50: =SUM(J50/60)*C50 -> 0 | N50: =IFERROR(VLOOKUP(M50, Tarieven!$A$1:$J$150, 10, FALSE), "0") -> 0 | Q50: =IFERROR(VLOOKUP(P50, Tarieven!$A$1:$J$150, 10, FALSE), "0") -> 0 | T50: =IFERROR(VLOOKUP(S50, Tarieven!$A$1:$J$150, 10, FALSE), "0") -> 0 | W50: =IFERROR(VLOOKUP(V50, Tarieven!$A$1:$J$150, 10, FALSE), "0") -> 0 | Z50: =IFERROR(VLOOKUP(Y50, Tarieven[#ALL], 10, FALSE), "0") -> 0 | AC50: =IFERROR(VLOOKUP(AB50, Tarieven[#ALL], 10, FALSE), "0") -> 0 | AD50: =SUM(L50+O50+R50+U50+X50+AA50) -> 0 | AF50: =SUM((L50*N50)+(O50*Q50)+(R50*T50)+(U50*W50)+(X50*Z50)+(AA50*AC50)) -> 0 | AG50: =SUM(L50+O50+R50+AD50) -> 0
A51: =Rooster!A52 | B51: =Rooster!B52 | C51: =Rooster!C52 | D51: =Rooster!D52 | F51: =Rooster!E52 | G51: =IFERROR(VLOOKUP(F51, Docenten!$A$2:$G$30, 7, FALSE), "0") -> 0 | H51: =SUM(G51/60)*C51 -> 0 | I51: =Rooster!H52 | J51: =IFERROR(VLOOKUP(I51, Locaties!$A$2:$G$15, 7, FALSE), "0") -> 0 | K51: =SUM(J51/60)*C51 -> 0 | N51: =IFERROR(VLOOKUP(M51, Tarieven!$A$1:$J$150, 10, FALSE), "0") -> 0 | Q51: =IFERROR(VLOOKUP(P51, Tarieven!$A$1:$J$150, 10, FALSE), "0") -> 0 | T51: =IFERROR(VLOOKUP(S51, Tarieven!$A$1:$J$150, 10, FALSE), "0") -> 0 | W51: =IFERROR(VLOOKUP(V51, Tarieven!$A$1:$J$150, 10, FALSE), "0") -> 0 | Z51: =IFERROR(VLOOKUP(Y51, Tarieven[#ALL], 10, FALSE), "0") -> 0 | AC51: =IFERROR(VLOOKUP(AB51, Tarieven[#ALL], 10, FALSE), "0") -> 0 | AD51: =SUM(L51+O51+R51+U51+X51+AA51) -> 0 | AF51: =SUM((L51*N51)+(O51*Q51)+(R51*T51)+(U51*W51)+(X51*Z51)+(AA51*AC51)) -> 0 | AG51: =SUM(L51+O51+R51+AD51) -> 0
A52: =Rooster!A53 | B52: =Rooster!B53 | C52: =Rooster!C53 | D52: =Rooster!D53 | F52: =Rooster!E53 | G52: =IFERROR(VLOOKUP(F52, Docenten!$A$2:$G$30, 7, FALSE), "0") -> 0 | H52: =SUM(G52/60)*C52 -> 0 | I52: =Rooster!H53 | J52: =IFERROR(VLOOKUP(I52, Locaties!$A$2:$G$15, 7, FALSE), "0") -> 0 | K52: =SUM(J52/60)*C52 -> 0 | N52: =IFERROR(VLOOKUP(M52, Tarieven!$A$1:$J$150, 10, FALSE), "0") -> 0 | Q52: =IFERROR(VLOOKUP(P52, Tarieven!$A$1:$J$150, 10, FALSE), "0") -> 0 | T52: =IFERROR(VLOOKUP(S52, Tarieven!$A$1:$J$150, 10, FALSE), "0") -> 0 | W52: =IFERROR(VLOOKUP(V52, Tarieven!$A$1:$J$150, 10, FALSE), "0") -> 0 | Z52: =IFERROR(VLOOKUP(Y52, Tarieven[#ALL], 10, FALSE), "0") -> 0 | AC52: =IFERROR(VLOOKUP(AB52, Tarieven[#ALL], 10, FALSE), "0") -> 0 | AD52: =SUM(L52+O52+R52+U52+X52+AA52) -> 0 | AF52: =SUM((L52*N52)+(O52*Q52)+(R52*T52)+(U52*W52)+(X52*Z52)+(AA52*AC52)) -> 0 | AG52: =SUM(L52+O52+R52+AD52) -> 0
A53: =Rooster!A54 | B53: =Rooster!B54 | C53: =Rooster!C54 | D53: =Rooster!D54 | F53: =Rooster!E54 | G53: =IFERROR(VLOOKUP(F53, Docenten!$A$2:$G$30, 7, FALSE), "0") -> 0 | H53: =SUM(G53/60)*C53 -> 0 | I53: =Rooster!H54 | J53: =IFERROR(VLOOKUP(I53, Locaties!$A$2:$G$15, 7, FALSE), "0") -> 0 | K53: =SUM(J53/60)*C53 -> 0 | N53: =IFERROR(VLOOKUP(M53, Tarieven!$A$1:$J$150, 10, FALSE), "0") -> 0 | Q53: =IFERROR(VLOOKUP(P53, Tarieven!$A$1:$J$150, 10, FALSE), "0") -> 0 | T53: =IFERROR(VLOOKUP(S53, Tarieven!$A$1:$J$150, 10, FALSE), "0") -> 0 | W53: =IFERROR(VLOOKUP(V53, Tarieven!$A$1:$J$150, 10, FALSE), "0") -> 0 | Z53: =IFERROR(VLOOKUP(Y53, Tarieven[#ALL], 10, FALSE), "0") -> 0 | AC53: =IFERROR(VLOOKUP(AB53, Tarieven[#ALL], 10, FALSE), "0") -> 0 | AD53: =SUM(L53+O53+R53+U53+X53+AA53) -> 0 | AF53: =SUM((L53*N53)+(O53*Q53)+(R53*T53)+(U53*W53)+(X53*Z53)+(AA53*AC53)) -> 0 | AG53: =SUM(L53+O53+R53+AD53) -> 0
A54: =Rooster!A55 | B54: =Rooster!B55 | C54: =Rooster!C55 | D54: =Rooster!D55 | F54: =Rooster!E55 | G54: =IFERROR(VLOOKUP(F54, Docenten!$A$2:$G$30, 7, FALSE), "0") -> 0 | H54: =SUM(G54/60)*C54 -> 0 | I54: =Rooster!H55 | J54: =IFERROR(VLOOKUP(I54, Locaties!$A$2:$G$15, 7, FALSE), "0") -> 0 | K54: =SUM(J54/60)*C54 -> 0 | N54: =IFERROR(VLOOKUP(M54, Tarieven!$A$1:$J$150, 10, FALSE), "0") -> 0 | Q54: =IFERROR(VLOOKUP(P54, Tarieven!$A$1:$J$150, 10, FALSE), "0") -> 0 | T54: =IFERROR(VLOOKUP(S54, Tarieven!$A$1:$J$150, 10, FALSE), "0") -> 0 | W54: =IFERROR(VLOOKUP(V54, Tarieven!$A$1:$J$150, 10, FALSE), "0") -> 0 | Z54: =IFERROR(VLOOKUP(Y54, Tarieven[#ALL], 10, FALSE), "0") -> 0 | AC54: =IFERROR(VLOOKUP(AB54, Tarieven[#ALL], 10, FALSE), "0") -> 0 | AD54: =SUM(L54+O54+R54+U54+X54+AA54) -> 0 | AF54: =SUM((L54*N54)+(O54*Q54)+(R54*T54)+(U54*W54)+(X54*Z54)+(AA54*AC54)) -> 0 | AG54: =SUM(L54+O54+R54+AD54) -> 0
A55: =Rooster!A56 | B55: =Rooster!B56 | C55: =Rooster!C56 | D55: =Rooster!D56 | F55: =Rooster!E56 | G55: =IFERROR(VLOOKUP(F55, Docenten!$A$2:$G$30, 7, FALSE), "0") -> 0 | H55: =SUM(G55/60)*C55 -> 0 | I55: =Rooster!H56 | J55: =IFERROR(VLOOKUP(I55, Locaties!$A$2:$G$15, 7, FALSE), "0") -> 0 | K55: =SUM(J55/60)*C55 -> 0 | N55: =IFERROR(VLOOKUP(M55, Tarieven!$A$1:$J$150, 10, FALSE), "0") -> 0 | Q55: =IFERROR(VLOOKUP(P55, Tarieven!$A$1:$J$150, 10, FALSE), "0") -> 0 | T55: =IFERROR(VLOOKUP(S55, Tarieven!$A$1:$J$150, 10, FALSE), "0") -> 0 | W55: =IFERROR(VLOOKUP(V55, Tarieven!$A$1:$J$150, 10, FALSE), "0") -> 0 | Z55: =IFERROR(VLOOKUP(Y55, Tarieven[#ALL], 10, FALSE), "0") -> 0 | AC55: =IFERROR(VLOOKUP(AB55, Tarieven[#ALL], 10, FALSE), "0") -> 0 | AD55: =SUM(L55+O55+R55+U55+X55+AA55) -> 0 | AF55: =SUM((L55*N55)+(O55*Q55)+(R55*T55)+(U55*W55)+(X55*Z55)+(AA55*AC55)) -> 0 | AG55: =SUM(L55+O55+R55+AD55) -> 0
A56: =Rooster!A57 | B56: =Rooster!B57 | C56: =Rooster!C57 | D56: =Rooster!D57 | F56: =Rooster!E57 | G56: =IFERROR(VLOOKUP(F56, Docenten!$A$2:$G$30, 7, FALSE), "0") -> 0 | H56: =SUM(G56/60)*C56 -> 0 | I56: =Rooster!H57 | J56: =IFERROR(VLOOKUP(I56, Locaties!$A$2:$G$15, 7, FALSE), "0") -> 0 | K56: =SUM(J56/60)*C56 -> 0 | N56: =IFERROR(VLOOKUP(M56, Tarieven!$A$1:$J$150, 10, FALSE), "0") -> 0 | Q56: =IFERROR(VLOOKUP(P56, Tarieven!$A$1:$J$150, 10, FALSE), "0") -> 0 | T56: =IFERROR(VLOOKUP(S56, Tarieven!$A$1:$J$150, 10, FALSE), "0") -> 0 | W56: =IFERROR(VLOOKUP(V56, Tarieven!$A$1:$J$150, 10, FALSE), "0") -> 0 | Z56: =IFERROR(VLOOKUP(Y56, Tarieven[#ALL], 10, FALSE), "0") -> 0 | AC56: =IFERROR(VLOOKUP(AB56, Tarieven[#ALL], 10, FALSE), "0") -> 0 | AD56: =SUM(L56+O56+R56+U56+X56+AA56) -> 0 | AF56: =SUM((L56*N56)+(O56*Q56)+(R56*T56)+(U56*W56)+(X56*Z56)+(AA56*AC56)) -> 0 | AG56: =SUM(L56+O56+R56+AD56) -> 0
... A64: =Rooster!A65 | B64: =Rooster!B65 | C64: =Rooster!C65 | D64: =Rooster!D65 | F64: =Rooster!E65 | G64: =IFERROR(VLOOKUP(F64, Docenten!$A$2:$G$30, 7, FALSE), "0") -> 0 | H64: =SUM(G64/60)*C64 -> 0 | I64: =Rooster!H65 | J64: =IFERROR(VLOOKUP(I64, Locaties!$A$2:$G$15, 7, FALSE), "0") -> 0 | K64: =SUM(J64/60)*C64 -> 0 | N64: =IFERROR(VLOOKUP(M64, Tarieven!$A$1:$J$150, 10, FALSE), "0") -> 0 | Q64: =IFERROR(VLOOKUP(P64, Tarieven!$A$1:$J$150, 10, FALSE), "0") -> 0 | T64: =IFERROR(VLOOKUP(S64, Tarieven!$A$1:$J$150, 10, FALSE), "0") -> 0 | W64: =IFERROR(VLOOKUP(V64, Tarieven!$A$1:$J$150, 10, FALSE), "0") -> 0 | Z64: =IFERROR(VLOOKUP(Y64, Tarieven[#ALL], 10, FALSE), "0") -> 0 | AC64: =IFERROR(VLOOKUP(AB64, Tarieven[#ALL], 10, FALSE), "0") -> 0 | AD64: =SUM(L64+O64+R64+U64+X64+AA64) -> 0 | AF64: =SUM((L64*N64)+(O64*Q64)+(R64*T64)+(U64*W64)+(X64*Z64)+(AA64*AC64)) -> 0 | AG64: =SUM(L64+O64+R64+AD64) -> 0
A65: =Rooster!A66 | B65: =Rooster!B66 | C65: =Rooster!C66 | D65: =Rooster!D66 | E65: 1 | F65: =Rooster!E66 | G65: =IFERROR(VLOOKUP(F65, Docenten!$A$2:$G$30, 7, FALSE), "0") -> 0 | H65: =SUM(G65/60)*C65 -> 0 | I65: =Rooster!H66 | J65: =IFERROR(VLOOKUP(I65, Locaties!$A$2:$G$15, 7, FALSE), "0") -> 0 | K65: =SUM(J65/60)*C65 -> 0 | N65: =IFERROR(VLOOKUP(M65, Tarieven[#ALL], 10, FALSE), "0") -> 0 | Q65: =IFERROR(VLOOKUP(P65, Tarieven[#ALL], 10, FALSE), "0") -> 0 | T65: =IFERROR(VLOOKUP(S65, Tarieven[#ALL], 10, FALSE), "0") -> 0 | W65: =IFERROR(VLOOKUP(V65, Tarieven!$A$1:$J$150, 10, FALSE), "0") -> 0 | Z65: =IFERROR(VLOOKUP(Y65, Tarieven[#ALL], 10, FALSE), "0") -> 0 | AC65: =IFERROR(VLOOKUP(AB65, Tarieven[#ALL], 10, FALSE), "0") -> 0 | AD65: =SUM(L65+O65+R65+U65+X65+AA65) -> 0 | AE65: =SUM(H65+K65)*E65 -> 0 | AF65: =SUM((L65*N65)+(O65*Q65)+(R65*T65)+(U65*W65)+(X65*Z65)+(AA65*AC65)) -> 0 | AG65: =SUM(AF65-AE65) -> 0
A66: =Rooster!A67 | B66: =Rooster!B67 | C66: =Rooster!C67 | D66: =Rooster!D67 | E66: 1 | F66: =Rooster!E67 | G66: =IFERROR(VLOOKUP(F66, Docenten!$A$2:$G$30, 7, FALSE), "0") -> 0 | H66: =SUM(G66/60)*C66 -> 0 | I66: =Rooster!H67 | J66: =IFERROR(VLOOKUP(I66, Locaties!$A$2:$G$15, 7, FALSE), "0") -> 0 | K66: =SUM(J66/60)*C66 -> 0 | N66: =IFERROR(VLOOKUP(M66, Tarieven[#ALL], 10, FALSE), "0") -> 0 | Q66: =IFERROR(VLOOKUP(P66, Tarieven[#ALL], 10, FALSE), "0") -> 0 | T66: =IFERROR(VLOOKUP(S66, Tarieven[#ALL], 10, FALSE), "0") -> 0 | W66: =IFERROR(VLOOKUP(V66, Tarieven!$A$1:$J$150, 10, FALSE), "0") -> 0 | Z66: =IFERROR(VLOOKUP(Y66, Tarieven[#ALL], 10, FALSE), "0") -> 0 | AC66: =IFERROR(VLOOKUP(AB66, Tarieven[#ALL], 10, FALSE), "0") -> 0 | AD66: =SUM(L66+O66+R66+U66+X66+AA66) -> 0 | AE66: =SUM(H66+K66)*E66 -> 0 | AF66: =SUM((L66*N66)+(O66*Q66)+(R66*T66)+(U66*W66)+(X66*Z66)+(AA66*AC66)) -> 0 | AG66: =SUM(AF66-AE66) -> 0
A67: =Rooster!A68 | B67: =Rooster!B68 | C67: =Rooster!C68 | D67: =Rooster!D68 | E67: 1 | F67: =Rooster!E68 | G67: =IFERROR(VLOOKUP(F67, Docenten!$A$2:$G$30, 7, FALSE), "0") -> 0 | H67: =SUM(G67/60)*C67 -> 0 | I67: =Rooster!H68 | J67: =IFERROR(VLOOKUP(I67, Locaties!$A$2:$G$15, 7, FALSE), "0") -> 0 | K67: =SUM(J67/60)*C67 -> 0 | N67: =IFERROR(VLOOKUP(M67, Tarieven[#ALL], 10, FALSE), "0") -> 0 | Q67: =IFERROR(VLOOKUP(P67, Tarieven[#ALL], 10, FALSE), "0") -> 0 | T67: =IFERROR(VLOOKUP(S67, Tarieven[#ALL], 10, FALSE), "0") -> 0 | W67: =IFERROR(VLOOKUP(V67, Tarieven!$A$1:$J$150, 10, FALSE), "0") -> 0 | Z67: =IFERROR(VLOOKUP(Y67, Tarieven[#ALL], 10, FALSE), "0") -> 0 | AC67: =IFERROR(VLOOKUP(AB67, Tarieven[#ALL], 10, FALSE), "0") -> 0 | AD67: =SUM(L67+O67+R67+U67+X67+AA67) -> 0 | AE67: =SUM(H67+K67)*E67 -> 0 | AF67: =SUM((L67*N67)+(O67*Q67)+(R67*T67)+(U67*W67)+(X67*Z67)+(AA67*AC67)) -> 0 | AG67: =SUM(AF67-AE67) -> 0
A68: =Rooster!A69 | B68: =Rooster!B69 | C68: =Rooster!C69 | D68: =Rooster!D69 | E68: 1 | F68: =Rooster!E69 | G68: =IFERROR(VLOOKUP(F68, Docenten!$A$2:$G$30, 7, FALSE), "0") -> 0 | H68: =SUM(G68/60)*C68 -> 0 | I68: =Rooster!H69 | J68: =IFERROR(VLOOKUP(I68, Locaties!$A$2:$G$15, 7, FALSE), "0") -> 0 | K68: =SUM(J68/60)*C68 -> 0 | N68: =IFERROR(VLOOKUP(M68, Tarieven[#ALL], 10, FALSE), "0") -> 0 | Q68: =IFERROR(VLOOKUP(P68, Tarieven[#ALL], 10, FALSE), "0") -> 0 | T68: =IFERROR(VLOOKUP(S68, Tarieven[#ALL], 10, FALSE), "0") -> 0 | W68: =IFERROR(VLOOKUP(V68, Tarieven!$A$1:$J$150, 10, FALSE), "0") -> 0 | Z68: =IFERROR(VLOOKUP(Y68, Tarieven[#ALL], 10, FALSE), "0") -> 0 | AC68: =IFERROR(VLOOKUP(AB68, Tarieven[#ALL], 10, FALSE), "0") -> 0 | AD68: =SUM(L68+O68+R68+U68+X68+AA68) -> 0 | AE68: =SUM(H68+K68)*E68 -> 0 | AF68: =SUM((L68*N68)+(O68*Q68)+(R68*T68)+(U68*W68)+(X68*Z68)+(AA68*AC68)) -> 0 | AG68: =SUM(AF68-AE68) -> 0
A69: =Rooster!A70 | B69: =Rooster!B70 | C69: =Rooster!C70 | D69: =Rooster!D70 | E69: 1 | F69: =Rooster!E70 | G69: =IFERROR(VLOOKUP(F69, Docenten!$A$2:$G$30, 7, FALSE), "0") -> 0 | H69: =SUM(G69/60)*C69 -> 0 | I69: =Rooster!H70 | J69: =IFERROR(VLOOKUP(I69, Locaties!$A$2:$G$15, 7, FALSE), "0") -> 0 | K69: =SUM(J69/60)*C69 -> 0 | N69: =IFERROR(VLOOKUP(M69, Tarieven[#ALL], 10, FALSE), "0") -> 0 | Q69: =IFERROR(VLOOKUP(P69, Tarieven[#ALL], 10, FALSE), "0") -> 0 | T69: =IFERROR(VLOOKUP(S69, Tarieven[#ALL], 10, FALSE), "0") -> 0 | W69: =IFERROR(VLOOKUP(V69, Tarieven!$A$1:$J$150, 10, FALSE), "0") -> 0 | Z69: =IFERROR(VLOOKUP(Y69, Tarieven[#ALL], 10, FALSE), "0") -> 0 | AC69: =IFERROR(VLOOKUP(AB69, Tarieven[#ALL], 10, FALSE), "0") -> 0 | AD69: =SUM(L69+O69+R69+U69+X69+AA69) -> 0 | AE69: =SUM(H69+K69)*E69 -> 0 | AF69: =SUM((L69*N69)+(O69*Q69)+(R69*T69)+(U69*W69)+(X69*Z69)+(AA69*AC69)) -> 0 | AG69: =SUM(AF69-AE69) -> 0
A70: =Rooster!A71 | B70: =Rooster!B71 | C70: =Rooster!C71 | D70: =Rooster!D71 | E70: 1 | F70: =Rooster!E71 | G70: =IFERROR(VLOOKUP(F70, Docenten!$A$2:$G$30, 7, FALSE), "0") -> 0 | H70: =SUM(G70/60)*C70 -> 0 | I70: =Rooster!H71 | J70: =IFERROR(VLOOKUP(I70, Locaties!$A$2:$G$15, 7, FALSE), "0") -> 0 | K70: =SUM(J70/60)*C70 -> 0 | N70: =IFERROR(VLOOKUP(M70, Tarieven[#ALL], 10, FALSE), "0") -> 0 | Q70: =IFERROR(VLOOKUP(P70, Tarieven[#ALL], 10, FALSE), "0") -> 0 | T70: =IFERROR(VLOOKUP(S70, Tarieven[#ALL], 10, FALSE), "0") -> 0 | W70: =IFERROR(VLOOKUP(V70, Tarieven!$A$1:$J$150, 10, FALSE), "0") -> 0 | Z70: =IFERROR(VLOOKUP(Y70, Tarieven[#ALL], 10, FALSE), "0") -> 0 | AC70: =IFERROR(VLOOKUP(AB70, Tarieven[#ALL], 10, FALSE), "0") -> 0 | AD70: =SUM(L70+O70+R70+U70+X70+AA70) -> 0 | AE70: =SUM(H70+K70)*E70 -> 0 | AF70: =SUM((L70*N70)+(O70*Q70)+(R70*T70)+(U70*W70)+(X70*Z70)+(AA70*AC70)) -> 0 | AG70: =SUM(AF70-AE70) -> 0
A71: =Rooster!A72 | B71: =Rooster!B72 | C71: =Rooster!C72 | D71: =Rooster!D72 | E71: 1 | F71: =Rooster!E72 | G71: =IFERROR(VLOOKUP(F71, Docenten!$A$2:$G$30, 7, FALSE), "0") -> 0 | H71: =SUM(G71/60)*C71 -> 0 | I71: =Rooster!H72 | J71: =IFERROR(VLOOKUP(I71, Locaties!$A$2:$G$15, 7, FALSE), "0") -> 0 | K71: =SUM(J71/60)*C71 -> 0 | N71: =IFERROR(VLOOKUP(M71, Tarieven[#ALL], 10, FALSE), "0") -> 0 | Q71: =IFERROR(VLOOKUP(P71, Tarieven[#ALL], 10, FALSE), "0") -> 0 | T71: =IFERROR(VLOOKUP(S71, Tarieven[#ALL], 10, FALSE), "0") -> 0 | W71: =IFERROR(VLOOKUP(V71, Tarieven!$A$1:$J$150, 10, FALSE), "0") -> 0 | Z71: =IFERROR(VLOOKUP(Y71, Tarieven[#ALL], 10, FALSE), "0") -> 0 | AC71: =IFERROR(VLOOKUP(AB71, Tarieven[#ALL], 10, FALSE), "0") -> 0 | AD71: =SUM(L71+O71+R71+U71+X71+AA71) -> 0 | AE71: =SUM(H71+K71)*E71 -> 0 | AF71: =SUM((L71*N71)+(O71*Q71)+(R71*T71)+(U71*W71)+(X71*Z71)+(AA71*AC71)) -> 0 | AG71: =SUM(AF71-AE71) -> 0
A72: =Rooster!A73 | B72: =Rooster!B73 | C72: =Rooster!C73 | D72: =Rooster!D73 | E72: 1 | F72: =Rooster!E73 | G72: =IFERROR(VLOOKUP(F72, Docenten!$A$2:$G$30, 7, FALSE), "0") -> 0 | H72: =SUM(G72/60)*C72 -> 0 | I72: =Rooster!H73 | J72: =IFERROR(VLOOKUP(I72, Locaties!$A$2:$G$15, 7, FALSE), "0") -> 0 | K72: =SUM(J72/60)*C72 -> 0 | N72: =IFERROR(VLOOKUP(M72, Tarieven[#ALL], 10, FALSE), "0") -> 0 | Q72: =IFERROR(VLOOKUP(P72, Tarieven[#ALL], 10, FALSE), "0") -> 0 | T72: =IFERROR(VLOOKUP(S72, Tarieven[#ALL], 10, FALSE), "0") -> 0 | W72: =IFERROR(VLOOKUP(V72, Tarieven!$A$1:$J$150, 10, FALSE), "0") -> 0 | Z72: =IFERROR(VLOOKUP(Y72, Tarieven[#ALL], 10, FALSE), "0") -> 0 | AC72: =IFERROR(VLOOKUP(AB72, Tarieven[#ALL], 10, FALSE), "0") -> 0 | AD72: =SUM(L72+O72+R72+U72+X72+AA72) -> 0 | AE72: =SUM(H72+K72)*E72 -> 0 | AF72: =SUM((L72*N72)+(O72*Q72)+(R72*T72)+(U72*W72)+(X72*Z72)+(AA72*AC72)) -> 0 | AG72: =SUM(AF72-AE72) -> 0
A73: =Rooster!A74 | B73: =Rooster!B74 | C73: =Rooster!C74 | D73: =Rooster!D74 | E73: 1 | F73: =Rooster!E74 | G73: =IFERROR(VLOOKUP(F73, Docenten!$A$2:$G$30, 7, FALSE), "0") -> 0 | H73: =SUM(G73/60)*C73 -> 0 | I73: =Rooster!H74 | J73: =IFERROR(VLOOKUP(I73, Locaties!$A$2:$G$15, 7, FALSE), "0") -> 0 | K73: =SUM(J73/60)*C73 -> 0 | N73: =IFERROR(VLOOKUP(M73, Tarieven[#ALL], 10, FALSE), "0") -> 0 | Q73: =IFERROR(VLOOKUP(P73, Tarieven[#ALL], 10, FALSE), "0") -> 0 | T73: =IFERROR(VLOOKUP(S73, Tarieven[#ALL], 10, FALSE), "0") -> 0 | W73: =IFERROR(VLOOKUP(V73, Tarieven!$A$1:$J$150, 10, FALSE), "0") -> 0 | Z73: =IFERROR(VLOOKUP(Y73, Tarieven[#ALL], 10, FALSE), "0") -> 0 | AC73: =IFERROR(VLOOKUP(AB73, Tarieven[#ALL], 10, FALSE), "0") -> 0 | AD73: =SUM(L73+O73+R73+U73+X73+AA73) -> 0 | AE73: =SUM(H73+K73)*E73 -> 0 | AF73: =SUM((L73*N73)+(O73*Q73)+(R73*T73)+(U73*W73)+(X73*Z73)+(AA73*AC73)) -> 0 | AG73: =SUM(AF73-AE73) -> 0
A74: =Rooster!A75 | B74: =Rooster!B75 | C74: =Rooster!C75 | D74: =Rooster!D75 | E74: 1 | F74: =Rooster!E75 | G74: =IFERROR(VLOOKUP(F74, Docenten!$A$2:$G$30, 7, FALSE), "0") -> 0 | H74: =SUM(G74/60)*C74 -> 0 | I74: =Rooster!H75 | J74: =IFERROR(VLOOKUP(I74, Locaties!$A$2:$G$15, 7, FALSE), "0") -> 0 | K74: =SUM(J74/60)*C74 -> 0 | N74: =IFERROR(VLOOKUP(M74, Tarieven[#ALL], 10, FALSE), "0") -> 0 | Q74: =IFERROR(VLOOKUP(P74, Tarieven[#ALL], 10, FALSE), "0") -> 0 | T74: =IFERROR(VLOOKUP(S74, Tarieven[#ALL], 10, FALSE), "0") -> 0 | W74: =IFERROR(VLOOKUP(V74, Tarieven!$A$1:$J$150, 10, FALSE), "0") -> 0 | Z74: =IFERROR(VLOOKUP(Y74, Tarieven[#ALL], 10, FALSE), "0") -> 0 | AC74: =IFERROR(VLOOKUP(AB74, Tarieven[#ALL], 10, FALSE), "0") -> 0 | AD74: =SUM(L74+O74+R74+U74+X74+AA74) -> 0 | AE74: =SUM(H74+K74)*E74 -> 0 | AF74: =SUM((L74*N74)+(O74*Q74)+(R74*T74)+(U74*W74)+(X74*Z74)+(AA74*AC74)) -> 0 | AG74: =SUM(AF74-AE74) -> 0
A75: =Rooster!A76 | B75: =Rooster!B76 | C75: =Rooster!C76 | D75: =Rooster!D76 | E75: 1 | F75: =Rooster!E76 | G75: =IFERROR(VLOOKUP(F75, Docenten!$A$2:$G$30, 7, FALSE), "0") -> 0 | H75: =SUM(G75/60)*C75 -> 0 | I75: =Rooster!H76 | J75: =IFERROR(VLOOKUP(I75, Locaties!$A$2:$G$15, 7, FALSE), "0") -> 0 | K75: =SUM(J75/60)*C75 -> 0 | N75: =IFERROR(VLOOKUP(M75, Tarieven[#ALL], 10, FALSE), "0") -> 0 | Q75: =IFERROR(VLOOKUP(P75, Tarieven[#ALL], 10, FALSE), "0") -> 0 | T75: =IFERROR(VLOOKUP(S75, Tarieven[#ALL], 10, FALSE), "0") -> 0 | W75: =IFERROR(VLOOKUP(V75, Tarieven!$A$1:$J$150, 10, FALSE), "0") -> 0 | Z75: =IFERROR(VLOOKUP(Y75, Tarieven[#ALL], 10, FALSE), "0") -> 0 | AC75: =IFERROR(VLOOKUP(AB75, Tarieven[#ALL], 10, FALSE), "0") -> 0 | AD75: =SUM(L75+O75+R75+U75+X75+AA75) -> 0 | AE75: =SUM(H75+K75)*E75 -> 0 | AF75: =SUM((L75*N75)+(O75*Q75)+(R75*T75)+(U75*W75)+(X75*Z75)+(AA75*AC75)) -> 0 | AG75: =SUM(AF75-AE75) -> 0
A76: =Rooster!A77 | B76: =Rooster!B77 | C76: =Rooster!C77 | D76: =Rooster!D77 | E76: 1 | F76: =Rooster!E77 | G76: =IFERROR(VLOOKUP(F76, Docenten!$A$2:$G$30, 7, FALSE), "0") -> 0 | H76: =SUM(G76/60)*C76 -> 0 | I76: =Rooster!H77 | J76: =IFERROR(VLOOKUP(I76, Locaties!$A$2:$G$15, 7, FALSE), "0") -> 0 | K76: =SUM(J76/60)*C76 -> 0 | N76: =IFERROR(VLOOKUP(M76, Tarieven[#ALL], 10, FALSE), "0") -> 0 | Q76: =IFERROR(VLOOKUP(P76, Tarieven[#ALL], 10, FALSE), "0") -> 0 | T76: =IFERROR(VLOOKUP(S76, Tarieven[#ALL], 10, FALSE), "0") -> 0 | W76: =IFERROR(VLOOKUP(V76, Tarieven!$A$1:$J$150, 10, FALSE), "0") -> 0 | Z76: =IFERROR(VLOOKUP(Y76, Tarieven[#ALL], 10, FALSE), "0") -> 0 | AC76: =IFERROR(VLOOKUP(AB76, Tarieven[#ALL], 10, FALSE), "0") -> 0 | AD76: =SUM(L76+O76+R76+U76+X76+AA76) -> 0 | AE76: =SUM(H76+K76)*E76 -> 0 | AF76: =SUM((L76*N76)+(O76*Q76)+(R76*T76)+(U76*W76)+(X76*Z76)+(AA76*AC76)) -> 0 | AG76: =SUM(AF76-AE76) -> 0
... A100: =Rooster!A101 | B100: =Rooster!B101 | C100: =Rooster!C101 | D100: =Rooster!D101 | E100: 1 | F100: =Rooster!E101 | G100: =IFERROR(VLOOKUP(F100, Docenten!$A$2:$G$30, 7, FALSE), "0") -> 0 | H100: =SUM(G100/60)*C100 -> 0 | I100: =Rooster!H101 | J100: =IFERROR(VLOOKUP(I100, Locaties!$A$2:$G$15, 7, FALSE), "0") -> 0 | K100: =SUM(J100/60)*C100 -> 0 | N100: =IFERROR(VLOOKUP(M100, Tarieven[#ALL], 10, FALSE), "0") -> 0 | Q100: =IFERROR(VLOOKUP(P100, Tarieven[#ALL], 10, FALSE), "0") -> 0 | T100: =IFERROR(VLOOKUP(S100, Tarieven[#ALL], 10, FALSE), "0") -> 0 | W100: =IFERROR(VLOOKUP(V100, Tarieven!$A$1:$J$150, 10, FALSE), "0") -> 0 | Z100: =IFERROR(VLOOKUP(Y100, Tarieven[#ALL], 10, FALSE), "0") -> 0 | AC100: =IFERROR(VLOOKUP(AB100, Tarieven[#ALL], 10, FALSE), "0") -> 0 | AD100: =SUM(L100+O100+R100+U100+X100+AA100) -> 0 | AE100: =SUM(H100+K100)*E100 -> 0 | AF100: =SUM((L100*N100)+(O100*Q100)+(R100*T100)+(U100*W100)+(X100*Z100)+(AA100*AC100)) -> 0 | AG100: =SUM(AF100-AE100) -> 0
A101: =Rooster!A102 | B101: =Rooster!B102 | C101: =Rooster!C102 | D101: =Rooster!D102 | E101: 1 | F101: =Rooster!E102 | G101: =IFERROR(VLOOKUP(F101, Docenten!$A$2:$G$30, 7, FALSE), "0") -> 0 | H101: =SUM(G101/60)*C101 -> 0 | I101: =Rooster!H102 | J101: =IFERROR(VLOOKUP(I101, Locaties!$A$2:$G$15, 7, FALSE), "0") -> 0 | K101: =SUM(J101/60)*C101 -> 0 | L101: =SUM(L2:L100) -> 100 | N101: =IFERROR(VLOOKUP(M101, Tarieven[#ALL], 10, FALSE), "0") -> 0 | O101: =SUM(O2:O100) -> 55 | Q101: =IFERROR(VLOOKUP(P101, Tarieven[#ALL], 10, FALSE), "0") -> 0 | R101: =SUM(R2:R100) -> 37 | T101: =IFERROR(VLOOKUP(S101, Tarieven[#ALL], 10, FALSE), "0") -> 0 | U101: =SUM(U2:U100) -> 22 | W101: =IFERROR(VLOOKUP(V101, Tarieven!$A$1:$J$150, 10, FALSE), "0") -> 0 | X101: =SUM(X2:X100) -> 6 | Z101: =IFERROR(VLOOKUP(Y101, Tarieven[#ALL], 10, FALSE), "0") -> 0 | AA101: =SUM(AA2:AA100) -> 0 | AC101: =IFERROR(VLOOKUP(AB101, Tarieven[#ALL], 10, FALSE), "0") -> 0 | AD101: =SUM(L101+O101+R101+U101+X101+AA101) -> 220 | AE101: =SUM(H101+K101)*E101 -> 0 | AF101: =SUM((L101*N101)+(O101*Q101)+(R101*T101)+(U101*W101)+(X101*Z101)+(AA101*AC101)) -> 0 | AG101: =SUM(AF101-AE101) -> 0

Sheet Augustus
A1: Lesdag | B1: Lestijd | C1: Minuten les | D1: Naam les | E1: Aantal lessen deze maand | F1: Docent | G1: Tarief docent | H1: Tarief docent per les | I1: Locatie | J1: Zaalhuur per uur | K1: Zaalhuur per les | L1: Aantal leden tarief 1 | M1: Type lidmaatschap 1 | N1: Tarief 1 (excl btw) | O1: Aantal leden tarief 2 | P1: Type lidmaatschap 2 | Q1: Tarief 2 (excl btw) | R1: Aantal leden tarief 3 | S1: Type lidmaatschap 3 | T1: Tarief 3 (excl btw) | U1: Aantal leden tarief 4 | V1: Type lidmaatschap 4 | W1: Tarief 4 (excl btw) | X1: Aantal leden met een jaarabb. | Y1: Is hij betaald in deze maand? Vul hieronder het bedrag in. | Z1: Totaal aantal leden | AA1: Kosten per maand | AB1: Inkomsten per maand | AC1: Winst per maand
A2: =Rooster!A3 | B2: =Rooster!B3 | C2: =Rooster!C3 | D2: =Rooster!D3 | F2: =Rooster!E3 | G2: =IFERROR(VLOOKUP(F2, Docenten!$A$2:$G$30, 7, FALSE), "0") -> 0 | H2: =SUM(G2/60)*C2 -> 0 | I2: =Rooster!H3 | J2: =IFERROR(VLOOKUP(I2, Locaties!$A$2:$G$15, 7, FALSE), "0") -> 0 | K2: =SUM(J2/60)*C2 -> 0 | L2: =September!L2 | N2: =IFERROR(VLOOKUP(M2, Tarieven!$A$1:$J$150, 10, FALSE), "0") -> 0 | O2: =September!O2 | Q2: =IFERROR(VLOOKUP(P2, Tarieven!$A$2:$J$150, 10, FALSE), "0") -> 0 | R2: =September!R2 | T2: =IFERROR(VLOOKUP(S2, Tarieven!$A$2:$J$150, 10, FALSE), "0") -> 0 | U2: =September!U2 | V2: =September!V2 | W2: =IFERROR(VLOOKUP(V2, Tarieven!$A$2:$J$150, 10, FALSE), "0") -> 0 | X2: =Jaarbetalingen!AD2 -> 0 | Y2: 0 | Z2: =SUM(L2+O2+R2+U2+X2) -> 0 | AA2: =SUM(H2+K2)*E2 -> 0 | AB2: =SUM((L2*N2)+(O2*Q2)+(R2*T2)+(U2*W2)+Y2) -> 0 | AC2: =SUM(AB2-AA2) -> 0 | AE2: Categorie | AF2: Bedrag | AG2: Kolom 1
A3: =Rooster!A4 | B3: =Rooster!B4 | C3: =Rooster!C4 | D3: =Rooster!D4 | F3: =Rooster!E4 | G3: =IFERROR(VLOOKUP(F3, Docenten!$A$2:$G$30, 7, FALSE), "0") -> 0 | H3: =SUM(G3/60)*C3 -> 0 | I3: =Rooster!H4 | J3: =IFERROR(VLOOKUP(I3, Locaties!$A$2:$G$15, 7, FALSE), "0") -> 0 | K3: =SUM(J3/60)*C3 -> 0 | L3: =September!L3 | N3: =IFERROR(VLOOKUP(M3, Tarieven!$A$1:$J$150, 10, FALSE), "0") -> 0 | O3: =September!O3 | Q3: =IFERROR(VLOOKUP(P3, Tarieven!$A$2:$J$150, 10, FALSE), "0") -> 0 | R3: =September!R3 | T3: =IFERROR(VLOOKUP(S3, Tarieven!$A$2:$J$150, 10, FALSE), "0") -> 0 | U3: =September!U3 | V3: =September!V3 | W3: =IFERROR(VLOOKUP(V3, Tarieven!$A$2:$J$150, 10, FALSE), "0") -> 0 | X3: =Jaarbetalingen!AD3 -> 0 | Y3: 0 | Z3: =SUM(L3+O3+R3+U3+X3) -> 0 | AA3: =SUM(H3+K3)*E3 -> 0 | AB3: =SUM((L3*N3)+(O3*Q3)+(R3*T3)+(U3*W3)+Y3) -> 0 | AC3: =SUM(AB3-AA3) -> 0 | AE3: Inkomsten lessen | AF3: =SUM(AB2:AB101) -> 2000
A4: =Rooster!A5 -> Maandag | B4: =Rooster!B5 -> 0.625 | C4: =Rooster!C5 -> 60 | D4: =Rooster!D5 -> Kleuterdans | F4: =Rooster!E5 -> Lotte | G4: =IFERROR(VLOOKUP(F4, Docenten!$A$2:$G$30, 7, FALSE), "0") -> 22.5 | H4: =SUM(G4/60)*C4 -> 22.5 | I4: =Rooster!H5 -> Santpoort Zuid | J4: =IFERROR(VLOOKUP(I4, Locaties!$A$2:$G$15, 7, FALSE), "0") -> 18.9 | K4: =SUM(J4/60)*C4 -> 18.9 | L4: =September!L4 | N4: =IFERROR(VLOOKUP(M4, Tarieven!$A$1:$J$150, 10, FALSE), "0") -> 0 | O4: =September!O4 | Q4: =IFERROR(VLOOKUP(P4, Tarieven!$A$2:$J$150, 10, FALSE), "0") -> 0 | R4: =September!R4 | T4: =IFERROR(VLOOKUP(S4, Tarieven!$A$2:$J$150, 10, FALSE), "0") -> 0 | U4: =September!U4 | V4: =September!V4 | W4: =IFERROR(VLOOKUP(V4, Tarieven!$A$2:$J$150, 10, FALSE), "0") -> 0 | X4: =Jaarbetalingen!AD4 -> 0 | Y4: 0 | Z4: =SUM(L4+O4+R4+U4+X4) -> 0 | AA4: =SUM(H4+K4)*E4 -> 0 | AB4: =SUM((L4*N4)+(O4*Q4)+(R4*T4)+(U4*W4)+Y4) -> 0 | AC4: =SUM(AB4-AA4) -> 0 | AE4: Inkomsten overige | AF4: ='Extra activiteiten'!K2
A5: =Rooster!A6 -> Maandag | B5: =Rooster!B6 -> 0.625 | C5: =Rooster!C6 -> 60 | D5: =Rooster!D6 -> Streetdance 6+ | F5: =Rooster!E6 -> Lotte | G5: =IFERROR(VLOOKUP(F5, Docenten!$A$2:$G$30, 7, FALSE), "0") -> 22.5 | H5: =SUM(G5/60)*C5 -> 22.5 | I5: =Rooster!H6 -> Santpoort Zuid | J5: =IFERROR(VLOOKUP(I5, Locaties!$A$2:$G$15, 7, FALSE), "0") -> 18.9 | K5: =SUM(J5/60)*C5 -> 18.9 | N5: =IFERROR(VLOOKUP(M5, Tarieven!$A$1:$J$150, 10, FALSE), "0") -> 0 | O5: =September!O5 | Q5: =IFERROR(VLOOKUP(P5, Tarieven!$A$2:$J$150, 10, FALSE), "0") -> 0 | R5: =September!R5 | T5: =IFERROR(VLOOKUP(S5, Tarieven!$A$2:$J$150, 10, FALSE), "0") -> 0 | U5: =September!U5 | V5: =September!V5 | W5: =IFERROR(VLOOKUP(V5, Tarieven!$A$2:$J$150, 10, FALSE), "0") -> 0 | X5: =Jaarbetalingen!AD5 -> 0 | Y5: 0 | Z5: =SUM(L5+O5+R5+U5+X5) -> 0 | AA5: =SUM(H5+K5)*E5 -> 0 | AB5: =SUM((L5*N5)+(O5*Q5)+(R5*T5)+(U5*W5)+Y5) -> 0 | AC5: =SUM(AB5-AA5) -> 0 | AE5: Kosten lessen | AF5: =SUM(Augustus[Kosten per maand]) -> 0
A6: =Rooster!A7 -> Maandag | B6: =Rooster!B7 -> 0.66666667 | C6: =Rooster!C7 -> 60 | D6: =Rooster!D7 -> Urban-Pop-Show 10+ | F6: =Rooster!E7 -> Lotte | G6: =IFERROR(VLOOKUP(F6, Docenten!$A$2:$G$30, 7, FALSE), "0") -> 22.5 | H6: =SUM(G6/60)*C6 -> 22.5 | I6: =Rooster!H7 -> Santpoort Zuid | J6: =IFERROR(VLOOKUP(I6, Locaties!$A$2:$G$15, 7, FALSE), "0") -> 18.9 | K6: =SUM(J6/60)*C6 -> 18.9 | L6: =September!L6 -> 1 | N6: =IFERROR(VLOOKUP(M6, Tarieven!$A$1:$J$150, 10, FALSE), "0") -> 0 | O6: =September!O6 -> 3 | Q6: =IFERROR(VLOOKUP(P6, Tarieven!$A$2:$J$150, 10, FALSE), "0") -> 0 | R6: =September!R6 -> 1 | T6: =IFERROR(VLOOKUP(S6, Tarieven!$A$2:$J$150, 10, FALSE), "0") -> 0 | U6: =September!U6 | V6: =September!V6 | W6: =IFERROR(VLOOKUP(V6, Tarieven!$A$2:$J$150, 10, FALSE), "0") -> 0 | X6: =Jaarbetalingen!AD6 -> 4 | Y6: 0 | Z6: =SUM(L6+O6+R6+U6+X6) -> 9 | AA6: =SUM(H6+K6)*E6 -> 0 | AB6: =SUM((L6*N6)+(O6*Q6)+(R6*T6)+(U6*W6)+Y6) -> 0 | AC6: =SUM(AB6-AA6) -> 0 | AE6: Kosten overige | AF6: =Kosten!B69 -> 4644.58 | AG6: Salaris doel
A7: =Rooster!A8 -> Maandag | B7: =Rooster!B8 -> 0.70833333 | C7: =Rooster!C8 -> 60 | D7: =Rooster!D8 -> Urban-Pop-Show 12+ | F7: =Rooster!E8 -> Nova | G7: =IFERROR(VLOOKUP(F7, Docenten!$A$2:$G$30, 7, FALSE), "0") -> 22.5 | H7: =SUM(G7/60)*C7 -> 22.5 | I7: =Rooster!H8 -> Santpoort Zuid | J7: =IFERROR(VLOOKUP(I7, Locaties!$A$2:$G$15, 7, FALSE), "0") -> 18.9 | K7: =SUM(J7/60)*C7 -> 18.9 | L7: =September!L7 -> 1 | N7: =IFERROR(VLOOKUP(M7, Tarieven!$A$1:$J$150, 10, FALSE), "0") -> 0 | O7: =September!O7 -> 1 | Q7: =IFERROR(VLOOKUP(P7, Tarieven!$A$2:$J$150, 10, FALSE), "0") -> 0 | R7: =September!R7 -> 1 | T7: =IFERROR(VLOOKUP(S7, Tarieven!$A$2:$J$150, 10, FALSE), "0") -> 0 | U7: =September!U7 | V7: =September!V7 | W7: =IFERROR(VLOOKUP(V7, Tarieven!$A$2:$J$150, 10, FALSE), "0") -> 0 | X7: =Jaarbetalingen!AD7 -> 11 | Y7: 0 | Z7: =SUM(L7+O7+R7+U7+X7) -> 14 | AA7: =SUM(H7+K7)*E7 -> 0 | AB7: =SUM((L7*N7)+(O7*Q7)+(R7*T7)+(U7*W7)+Y7) -> 0 | AC7: =SUM(AB7-AA7) -> 0 | AE7: Winst deze maand | AF7: =SUM(AF3+AF4)-AF5-AF6 -> -2644.58 | AG7: ='Doel vs Werkelijkheid'!B2 -> 3000
A8: =Rooster!A9 -> Maandag | B8: =Rooster!B9 -> 0.75 | C8: =Rooster!C9 -> 60 | D8: =Rooster!D9 -> Selectie Show | F8: =Rooster!E9 -> Nova | G8: =IFERROR(VLOOKUP(F8, Docenten!$A$2:$G$30, 7, FALSE), "0") -> 22.5 | H8: =SUM(G8/60)*C8 -> 22.5 | I8: =Rooster!H9 -> Santpoort Zuid | J8: =IFERROR(VLOOKUP(I8, Locaties!$A$2:$G$15, 7, FALSE), "0") -> 18.9 | K8: =SUM(J8/60)*C8 -> 18.9 | L8: =September!L8 -> 2 | N8: =IFERROR(VLOOKUP(M8, Tarieven!$A$1:$J$150, 10, FALSE), "0") -> 0 | O8: =September!O8 -> 3 | Q8: =IFERROR(VLOOKUP(P8, Tarieven!$A$2:$J$150, 10, FALSE), "0") -> 0 | R8: =September!R8 -> 2 | T8: =IFERROR(VLOOKUP(S8, Tarieven!$A$2:$J$150, 10, FALSE), "0") -> 0 | U8: =September!U8 | V8: =September!V8 | W8: =IFERROR(VLOOKUP(V8, Tarieven!$A$2:$J$150, 10, FALSE), "0") -> 0 | X8: =Jaarbetalingen!AD8 -> 4 | Y8: 0 | Z8: =SUM(L8+O8+R8+U8+X8) -> 11 | AA8: =SUM(H8+K8)*E8 -> 0 | AB8: =SUM((L8*N8)+(O8*Q8)+(R8*T8)+(U8*W8)+Y8) -> 0 | AC8: =SUM(AB8-AA8) -> 0
A9: =Rooster!A10 -> Maandag | B9: =Rooster!B10 -> 0.79166667 | C9: =Rooster!C10 -> 60 | D9: =Rooster!D10 -> Commercial 16+ | F9: =Rooster!E10 -> Nova | G9: =IFERROR(VLOOKUP(F9, Docenten!$A$2:$G$30, 7, FALSE), "0") -> 22.5 | H9: =SUM(G9/60)*C9 -> 22.5 | I9: =Rooster!H10 -> Santpoort Zuid | J9: =IFERROR(VLOOKUP(I9, Locaties!$A$2:$G$15, 7, FALSE), "0") -> 18.9 | K9: =SUM(J9/60)*C9 -> 18.9 | L9: =September!L9 -> 3 | N9: =IFERROR(VLOOKUP(M9, Tarieven!$A$1:$J$150, 10, FALSE), "0") -> 0 | O9: =September!O9 -> 1 | Q9: =IFERROR(VLOOKUP(P9, Tarieven!$A$2:$J$150, 10, FALSE), "0") -> 0 | R9: =September!R9 -> 3 | T9: =IFERROR(VLOOKUP(S9, Tarieven!$A$2:$J$150, 10, FALSE), "0") -> 0 | U9: =September!U9 | V9: =September!V9 | W9: =IFERROR(VLOOKUP(V9, Tarieven!$A$2:$J$150, 10, FALSE), "0") -> 0 | X9: =Jaarbetalingen!AD9 -> 5 | Y9: 0 | Z9: =SUM(L9+O9+R9+U9+X9) -> 12 | AA9: =SUM(H9+K9)*E9 -> 0 | AB9: =SUM((L9*N9)+(O9*Q9)+(R9*T9)+(U9*W9)+Y9) -> 0 | AC9: =SUM(AB9-AA9) -> 0 | AE9: Actieve leden | AF9: =Z101 -> 390
A10: =Rooster!A11 -> Maandag | B10: =Rooster!B11 -> 0.83333333 | C10: =Rooster!C11 -> 60 | D10: =Rooster!D11 -> Commercial 20+ | F10: =Rooster!E11 -> Nova | G10: =IFERROR(VLOOKUP(F10, Docenten!$A$2:$G$30, 7, FALSE), "0") -> 22.5 | H10: =SUM(G10/60)*C10 -> 22.5 | I10: =Rooster!H11 -> Santpoort Zuid | J10: =IFERROR(VLOOKUP(I10, Locaties!$A$2:$G$15, 7, FALSE), "0") -> 18.9 | K10: =SUM(J10/60)*C10 -> 18.9 | L10: =September!L10 -> 4 | N10: =IFERROR(VLOOKUP(M10, Tarieven!$A$1:$J$150, 10, FALSE), "0") -> 0 | O10: =September!O10 -> 3 | Q10: =IFERROR(VLOOKUP(P10, Tarieven!$A$2:$J$150, 10, FALSE), "0") -> 0 | R10: =September!R10 -> 1 | T10: =IFERROR(VLOOKUP(S10, Tarieven!$A$2:$J$150, 10, FALSE), "0") -> 0 | U10: =September!U10 | V10: =September!V10 | W10: =IFERROR(VLOOKUP(V10, Tarieven!$A$2:$J$150, 10, FALSE), "0") -> 0 | X10: =Jaarbetalingen!AD10 -> 8 | Y10: 0 | Z10: =SUM(L10+O10+R10+U10+X10) -> 16 | AA10: =SUM(H10+K10)*E10 -> 0 | AB10: =SUM((L10*N10)+(O10*Q10)+(R10*T10)+(U10*W10)+Y10) -> 0 | AC10: =SUM(AB10-AA10) -> 0
A11: =Rooster!A12 -> Maandag | B11: =Rooster!B12 -> 0.875 | C11: =Rooster!C12 -> 60 | D11: =Rooster!D12 -> Jazz 20+ | F11: =Rooster!E12 -> Nova | G11: =IFERROR(VLOOKUP(F11, Docenten!$A$2:$G$30, 7, FALSE), "0") -> 22.5 | H11: =SUM(G11/60)*C11 -> 22.5 | I11: =Rooster!H12 -> Santpoort Zuid | J11: =IFERROR(VLOOKUP(I11, Locaties!$A$2:$G$15, 7, FALSE), "0") -> 18.9 | K11: =SUM(J11/60)*C11 -> 18.9 | L11: =September!L11 -> 4 | N11: =IFERROR(VLOOKUP(M11, Tarieven!$A$1:$J$150, 10, FALSE), "0") -> 0 | O11: =September!O11 | Q11: =IFERROR(VLOOKUP(P11, Tarieven!$A$2:$J$150, 10, FALSE), "0") -> 0 | R11: =September!R11 | T11: =IFERROR(VLOOKUP(S11, Tarieven!$A$2:$J$150, 10, FALSE), "0") -> 0 | U11: =September!U11 | V11: =September!V11 | W11: =IFERROR(VLOOKUP(V11, Tarieven!$A$2:$J$150, 10, FALSE), "0") -> 0 | X11: =Jaarbetalingen!AD11 -> 4 | Y11: 0 | Z11: =SUM(L11+O11+R11+U11+X11) -> 8 | AA11: =SUM(H11+K11)*E11 -> 0 | AB11: =SUM((L11*N11)+(O11*Q11)+(R11*T11)+(U11*W11)+Y11) -> 0 | AC11: =SUM(AB11-AA11) -> 0
A12: =Rooster!A13 -> Maandag | B12: =Rooster!B13 -> 0.66666667 | C12: =Rooster!C13 -> 60 | D12: =Rooster!D13 -> Streetdance 6+ | F12: =Rooster!E13 -> Julia | G12: =IFERROR(VLOOKUP(F12, Docenten!$A$2:$G$30, 7, FALSE), "0") -> 15 | H12: =SUM(G12/60)*C12 -> 15 | I12: =Rooster!H13 -> Santpoort Noord | J12: =IFERROR(VLOOKUP(I12, Locaties!$A$2:$G$15, 7, FALSE), "0") -> 14.2 | K12: =SUM(J12/60)*C12 -> 14.2 | L12: =September!L12 -> 3 | N12: =IFERROR(VLOOKUP(M12, Tarieven!$A$1:$J$150, 10, FALSE), "0") -> 0 | O12: =September!O12 | Q12: =IFERROR(VLOOKUP(P12, Tarieven!$A$2:$J$150, 10, FALSE), "0") -> 0 | R12: =September!R12 | T12: =IFERROR(VLOOKUP(S12, Tarieven!$A$2:$J$150, 10, FALSE), "0") -> 0 | U12: =September!U12 | V12: =September!V12 | W12: =IFERROR(VLOOKUP(V12, Tarieven!$A$2:$J$150, 10, FALSE), "0") -> 0 | X12: =Jaarbetalingen!AD12 -> 2 | Y12: 0 | Z12: =SUM(L12+O12+R12+U12+X12) -> 5 | AA12: =SUM(H12+K12)*E12 -> 0 | AB12: =SUM((L12*N12)+(O12*Q12)+(R12*T12)+(U12*W12)+Y12) -> 0 | AC12: =SUM(AB12-AA12) -> 0
A13: =Rooster!A14 -> Maandag | B13: =Rooster!B14 -> 0.70833333 | C13: =Rooster!C14 -> 60 | D13: =Rooster!D14 -> Streetdance 8+ | F13: =Rooster!E14 -> Julia | G13: =IFERROR(VLOOKUP(F13, Docenten!$A$2:$G$30, 7, FALSE), "0") -> 15 | H13: =SUM(G13/60)*C13 -> 15 | I13: =Rooster!H14 -> Santpoort Noord | J13: =IFERROR(VLOOKUP(I13, Locaties!$A$2:$G$15, 7, FALSE), "0") -> 14.2 | K13: =SUM(J13/60)*C13 -> 14.2 | L13: =September!L13 -> 5 | N13: =IFERROR(VLOOKUP(M13, Tarieven!$A$1:$J$150, 10, FALSE), "0") -> 0 | O13: =September!O13 -> 1 | Q13: =IFERROR(VLOOKUP(P13, Tarieven!$A$2:$J$150, 10, FALSE), "0") -> 0 | R13: =September!R13 | T13: =IFERROR(VLOOKUP(S13, Tarieven!$A$2:$J$150, 10, FALSE), "0") -> 0 | U13: =September!U13 | V13: =September!V13 | W13: =IFERROR(VLOOKUP(V13, Tarieven!$A$2:$J$150, 10, FALSE), "0") -> 0 | X13: =Jaarbetalingen!AD13 -> 13 | Y13: 0 | Z13: =SUM(L13+O13+R13+U13+X13) -> 19 | AA13: =SUM(H13+K13)*E13 -> 0 | AB13: =SUM((L13*N13)+(O13*Q13)+(R13*T13)+(U13*W13)+Y13) -> 0 | AC13: =SUM(AB13-AA13) -> 0
A14: =Rooster!A15 -> Dinsdag | B14: =Rooster!B15 -> 0.66666667 | C14: =Rooster!C15 -> 60 | D14: =Rooster!D15 -> Modern 8+ | F14: =Rooster!E15 -> Eigenaar | G14: =IFERROR(VLOOKUP(F14, Docenten!$A$2:$G$30, 7, FALSE), "0") -> 0 | H14: =SUM(G14/60)*C14 -> 0 | I14: =Rooster!H15 -> Santpoort Zuid | J14: =IFERROR(VLOOKUP(I14, Locaties!$A$2:$G$15, 7, FALSE), "0") -> 18.9 | K14: =SUM(J14/60)*C14 -> 18.9 | L14: =September!L14 -> 3 | N14: =IFERROR(VLOOKUP(M14, Tarieven!$A$1:$J$150, 10, FALSE), "0") -> 0 | O14: =September!O14 -> 4 | Q14: =IFERROR(VLOOKUP(P14, Tarieven!$A$2:$J$150, 10, FALSE), "0") -> 0 | R14: =September!R14 -> 1 | T14: =IFERROR(VLOOKUP(S14, Tarieven!$A$2:$J$150, 10, FALSE), "0") -> 0 | U14: =September!U14 | V14: =September!V14 | W14: =IFERROR(VLOOKUP(V14, Tarieven!$A$2:$J$150, 10, FALSE), "0") -> 0 | X14: =Jaarbetalingen!AD14 -> 8 | Y14: 0 | Z14: =SUM(L14+O14+R14+U14+X14) -> 16 | AA14: =SUM(H14+K14)*E14 -> 0 | AB14: =SUM((L14*N14)+(O14*Q14)+(R14*T14)+(U14*W14)+Y14) -> 0 | AC14: =SUM(AB14-AA14) -> 0
A15: =Rooster!A16 -> Dinsdag | B15: =Rooster!B16 -> 0.70833333 | C15: =Rooster!C16 -> 60 | D15: =Rooster!D16 -> Selectie show 8+ | F15: =Rooster!E16 -> Eigenaar | G15: =IFERROR(VLOOKUP(F15, Docenten!$A$2:$G$30, 7, FALSE), "0") -> 0 | H15: =SUM(G15/60)*C15 -> 0 | I15: =Rooster!H16 -> Santpoort Zuid | J15: =IFERROR(VLOOKUP(I15, Locaties!$A$2:$G$15, 7, FALSE), "0") -> 18.9 | K15: =SUM(J15/60)*C15 -> 18.9 | L15: =September!L15 -> 2 | N15: =IFERROR(VLOOKUP(M15, Tarieven!$A$1:$J$150, 10, FALSE), "0") -> 0 | O15: =September!O15 -> 2 | Q15: =IFERROR(VLOOKUP(P15, Tarieven!$A$2:$J$150, 10, FALSE), "0") -> 0 | R15: =September!R15 -> 1 | T15: =IFERROR(VLOOKUP(S15, Tarieven!$A$2:$J$150, 10, FALSE), "0") -> 0 | U15: =September!U15 | V15: =September!V15 | W15: =IFERROR(VLOOKUP(V15, Tarieven!$A$2:$J$150, 10, FALSE), "0") -> 0 | X15: =Jaarbetalingen!AD15 -> 7 | Y15: 0 | Z15: =SUM(L15+O15+R15+U15+X15) -> 12 | AA15: =SUM(H15+K15)*E15 -> 0 | AB15: =SUM((L15*N15)+(O15*Q15)+(R15*T15)+(U15*W15)+Y15) -> 0 | AC15: =SUM(AB15-AA15) -> 0
A16: =Rooster!A17 -> Dinsdag | B16: =Rooster!B17 -> 0.75 | C16: =Rooster!C17 -> 90 | D16: =Rooster!D17 -> Selectie Cheer | F16: =Rooster!E17 -> Eigenaar | G16: =IFERROR(VLOOKUP(F16, Docenten!$A$2:$G$30, 7, FALSE), "0") -> 0 | H16: =SUM(G16/60)*C16 -> 0 | I16: =Rooster!H17 -> Santpoort Zuid | J16: =IFERROR(VLOOKUP(I16, Locaties!$A$2:$G$15, 7, FALSE), "0") -> 18.9 | K16: =SUM(J16/60)*C16 -> 28.35 | L16: =September!L16 -> 2 | N16: =IFERROR(VLOOKUP(M16, Tarieven!$A$1:$J$150, 10, FALSE), "0") -> 0 | O16: =September!O16 -> 1 | Q16: =IFERROR(VLOOKUP(P16, Tarieven!$A$2:$J$150, 10, FALSE), "0") -> 0 | R16: =September!R16 | T16: =IFERROR(VLOOKUP(S16, Tarieven!$A$2:$J$150, 10, FALSE), "0") -> 0 | U16: =September!U16 | V16: =September!V16 | W16: =IFERROR(VLOOKUP(V16, Tarieven!$A$2:$J$150, 10, FALSE), "0") -> 0 | X16: =Jaarbetalingen!AD16 -> 8 | Y16: 0 | Z16: =SUM(L16+O16+R16+U16+X16) -> 11 | AA16: =SUM(H16+K16)*E16 -> 0 | AB16: =SUM((L16*N16)+(O16*Q16)+(R16*T16)+(U16*W16)+Y16) -> 0 | AC16: =SUM(AB16-AA16) -> 0
A17: =Rooster!A18 -> Dinsdag | B17: =Rooster!B18 -> 0.8125 | C17: =Rooster!C18 -> 60 | D17: =Rooster!D18 -> Hiphop 15+ | F17: =Rooster!E18 -> Eigenaar | G17: =IFERROR(VLOOKUP(F17, Docenten!$A$2:$G$30, 7, FALSE), "0") -> 0 | H17: =SUM(G17/60)*C17 -> 0 | I17: =Rooster!H18 -> Santpoort Zuid | J17: =IFERROR(VLOOKUP(I17, Locaties!$A$2:$G$15, 7, FALSE), "0") -> 18.9 | K17: =SUM(J17/60)*C17 -> 18.9 | L17: =September!L17 -> 1 | N17: =IFERROR(VLOOKUP(M17, Tarieven!$A$1:$J$150, 10, FALSE), "0") -> 0 | O17: =September!O17 -> 3 | Q17: =IFERROR(VLOOKUP(P17, Tarieven!$A$2:$J$150, 10, FALSE), "0") -> 0 | R17: =September!R17 -> 1 | T17: =IFERROR(VLOOKUP(S17, Tarieven!$A$2:$J$150, 10, FALSE), "0") -> 0 | U17: =September!U17 | V17: =September!V17 | W17: =IFERROR(VLOOKUP(V17, Tarieven!$A$2:$J$150, 10, FALSE), "0") -> 0 | X17: =Jaarbetalingen!AD17 -> 9 | Y17: 0 | Z17: =SUM(L17+O17+R17+U17+X17) -> 14 | AA17: =SUM(H17+K17)*E17 -> 0 | AB17: =SUM((L17*N17)+(O17*Q17)+(R17*T17)+(U17*W17)+Y17) -> 0 | AC17: =SUM(AB17-AA17) -> 0
A18: =Rooster!A19 -> Woensdag | B18: =Rooster!B19 -> 0.60416667 | C18: =Rooster!C19 -> 60 | D18: =Rooster!D19 -> Streetdance 6+ | F18: =Rooster!E19 -> Julia | G18: =IFERROR(VLOOKUP(F18, Docenten!$A$2:$G$30, 7, FALSE), "0") -> 15 | H18: =SUM(G18/60)*C18 -> 15 | I18: =Rooster!H19 -> Santpoort Noord | J18: =IFERROR(VLOOKUP(I18, Locaties!$A$2:$G$15, 7, FALSE), "0") -> 14.2 | K18: =SUM(J18/60)*C18 -> 14.2 | L18: =September!L18 -> 4 | N18: =IFERROR(VLOOKUP(M18, Tarieven!$A$1:$J$150, 10, FALSE), "0") -> 0 | O18: =September!O18 -> 1 | Q18: =IFERROR(VLOOKUP(P18, Tarieven!$A$2:$J$150, 10, FALSE), "0") -> 0 | R18: =September!R18 -> 1 | T18: =IFERROR(VLOOKUP(S18, Tarieven!$A$2:$J$150, 10, FALSE), "0") -> 0 | U18: =September!U18 | V18: =September!V18 | W18: =IFERROR(VLOOKUP(V18, Tarieven!$A$2:$J$150, 10, FALSE), "0") -> 0 | X18: =Jaarbetalingen!AD18 -> 9 | Y18: 0 | Z18: =SUM(L18+O18+R18+U18+X18) -> 15 | AA18: =SUM(H18+K18)*E18 -> 0 | AB18: =SUM((L18*N18)+(O18*Q18)+(R18*T18)+(U18*W18)+Y18) -> 0 | AC18: =SUM(AB18-AA18) -> 0
A19: =Rooster!A20 -> Woensdag | B19: =Rooster!B20 -> 0.64583333 | C19: =Rooster!C20 -> 60 | D19: =Rooster!D20 -> Streetdance 8+ | F19: =Rooster!E20 -> Julia | G19: =IFERROR(VLOOKUP(F19, Docenten!$A$2:$G$30, 7, FALSE), "0") -> 15 | H19: =SUM(G19/60)*C19 -> 15 | I19: =Rooster!H20 -> Santpoort Noord | J19: =IFERROR(VLOOKUP(I19, Locaties!$A$2:$G$15, 7, FALSE), "0") -> 14.2 | K19: =SUM(J19/60)*C19 -> 14.2 | L19: =September!L19 -> 3 | N19: =IFERROR(VLOOKUP(M19, Tarieven!$A$1:$J$150, 10, FALSE), "0") -> 0 | O19: =September!O19 -> 1 | Q19: =IFERROR(VLOOKUP(P19, Tarieven!$A$2:$J$150, 10, FALSE), "0") -> 0 | R19: =September!R19 -> 1 | T19: =IFERROR(VLOOKUP(S19, Tarieven!$A$2:$J$150, 10, FALSE), "0") -> 0 | U19: =September!U19 | V19: =September!V19 | W19: =IFERROR(VLOOKUP(V19, Tarieven!$A$2:$J$150, 10, FALSE), "0") -> 0 | X19: =Jaarbetalingen!AD19 -> 11 | Y19: 0 | Z19: =SUM(L19+O19+R19+U19+X19) -> 16 | AA19: =SUM(H19+K19)*E19 -> 0 | AB19: =SUM((L19*N19)+(O19*Q19)+(R19*T19)+(U19*W19)+Y19) -> 0 | AC19: =SUM(AB19-AA19) -> 0
A20: =Rooster!A21 -> Woensdag | B20: =Rooster!B21 -> 0.6875 | C20: =Rooster!C21 -> 60 | D20: =Rooster!D21 -> Modern 11+ | F20: =Rooster!E21 -> Julia | G20: =IFERROR(VLOOKUP(F20, Docenten!$A$2:$G$30, 7, FALSE), "0") -> 15 | H20: =SUM(G20/60)*C20 -> 15 | I20: =Rooster!H21 -> Santpoort Noord | J20: =IFERROR(VLOOKUP(I20, Locaties!$A$2:$G$15, 7, FALSE), "0") -> 14.2 | K20: =SUM(J20/60)*C20 -> 14.2 | L20: =September!L20 -> 1 | N20: =IFERROR(VLOOKUP(M20, Tarieven!$A$1:$J$150, 10, FALSE), "0") -> 0 | O20: =September!O20 -> 3 | Q20: =IFERROR(VLOOKUP(P20, Tarieven!$A$2:$J$150, 10, FALSE), "0") -> 0 | R20: =September!R20 -> 1 | T20: =IFERROR(VLOOKUP(S20, Tarieven!$A$2:$J$150, 10, FALSE), "0") -> 0 | U20: =September!U20 | V20: =September!V20 | W20: =IFERROR(VLOOKUP(V20, Tarieven!$A$2:$J$150, 10, FALSE), "0") -> 0 | X20: =Jaarbetalingen!AD20 -> 9 | Y20: 0 | Z20: =SUM(L20+O20+R20+U20+X20) -> 14 | AA20: =SUM(H20+K20)*E20 -> 0 | AB20: =SUM((L20*N20)+(O20*Q20)+(R20*T20)+(U20*W20)+Y20) -> 0 | AC20: =SUM(AB20-AA20) -> 0
A21: =Rooster!A22 -> Woensdag | B21: =Rooster!B22 -> 0.72916667 | C21: =Rooster!C22 -> 60 | D21: =Rooster!D22 -> Selectie Hiphop 11+ | F21: =Rooster!E22 -> Eigenaar | G21: =IFERROR(VLOOKUP(F21, Docenten!$A$2:$G$30, 7, FALSE), "0") -> 0 | H21: =SUM(G21/60)*C21 -> 0 | I21: =Rooster!H22 -> Santpoort Noord | J21: =IFERROR(VLOOKUP(I21, Locaties!$A$2:$G$15, 7, FALSE), "0") -> 14.2 | K21: =SUM(J21/60)*C21 -> 14.2 | L21: =September!L21 -> 1 | N21: =IFERROR(VLOOKUP(M21, Tarieven!$A$1:$J$150, 10, FALSE), "0") -> 0 | O21: =September!O21 | Q21: =IFERROR(VLOOKUP(P21, Tarieven!$A$2:$J$150, 10, FALSE), "0") -> 0 | R21: =September!R21 | T21: =IFERROR(VLOOKUP(S21, Tarieven!$A$2:$J$150, 10, FALSE), "0") -> 0 | U21: =September!U21 | V21: =September!V21 | W21: =IFERROR(VLOOKUP(V21, Tarieven!$A$2:$J$150, 10, FALSE), "0") -> 0 | X21: =Jaarbetalingen!AD21 -> 11 | Y21: 0 | Z21: =SUM(L21+O21+R21+U21+X21) -> 12 | AA21: =SUM(H21+K21)*E21 -> 0 | AB21: =SUM((L21*N21)+(O21*Q21)+(R21*T21)+(U21*W21)+Y21) -> 0 | AC21: =SUM(AB21-AA21) -> 0
... A30: =Rooster!A31 -> Vrijdag | B30: =Rooster!B31 -> 0.625 | C30: =Rooster!C31 -> 60 | D30: =Rooster!D31 -> Selectie Hiphop 8+ | F30: =Rooster!E31 -> Eigenaar | G30: =IFERROR(VLOOKUP(F30, Docenten!$A$2:$G$30, 7, FALSE), "0") -> 0 | H30: =SUM(G30/60)*C30 -> 0 | I30: =Rooster!H31 -> Santpoort Zuid | J30: =IFERROR(VLOOKUP(I30, Locaties!$A$2:$G$15, 7, FALSE), "0") -> 18.9 | K30: =SUM(J30/60)*C30 -> 18.9 | L30: =September!L30 -> 3 | N30: =IFERROR(VLOOKUP(M30, Tarieven!$A$1:$J$150, 10, FALSE), "0") -> 0 | O30: =September!O30 -> 5 | Q30: =IFERROR(VLOOKUP(P30, Tarieven!$A$2:$J$150, 10, FALSE), "0") -> 0 | R30: =September!R30 -> 1 | T30: =IFERROR(VLOOKUP(S30, Tarieven!$A$2:$J$150, 10, FALSE), "0") -> 0 | U30: =September!U30 | V30: =September!V30 | W30: =IFERROR(VLOOKUP(V30, Tarieven!$A$2:$J$150, 10, FALSE), "0") -> 0 | X30: =Jaarbetalingen!AD30 -> 4 | Y30: 0 | Z30: =SUM(L30+O30+R30+U30+X30) -> 13 | AA30: =SUM(H30+K30)*E30 -> 0 | AB30: =SUM((L30*N30)+(O30*Q30)+(R30*T30)+(U30*W30)+Y30) -> 0 | AC30: =SUM(AB30-AA30) -> 0
A31: =Rooster!A32 -> Vrijdag | B31: =Rooster!B32 -> 0.66666667 | C31: =Rooster!C32 -> 60 | D31: =Rooster!D32 -> Cheer 8+ | F31: Ilja | G31: =IFERROR(VLOOKUP(F31, Docenten!$A$2:$G$30, 7, FALSE), "0") -> 0 | H31: =SUM(G31/60)*C31 -> 0 | I31: =Rooster!H32 -> Santpoort Zuid | J31: =IFERROR(VLOOKUP(I31, Locaties!$A$2:$G$15, 7, FALSE), "0") -> 18.9 | K31: =SUM(J31/60)*C31 -> 18.9 | L31: =September!L31 -> 4 | N31: =IFERROR(VLOOKUP(M31, Tarieven!$A$1:$J$150, 10, FALSE), "0") -> 0 | O31: =September!O31 -> 3 | Q31: =IFERROR(VLOOKUP(P31, Tarieven!$A$2:$J$150, 10, FALSE), "0") -> 0 | R31: =September!R31 | T31: =IFERROR(VLOOKUP(S31, Tarieven!$A$2:$J$150, 10, FALSE), "0") -> 0 | U31: =September!U31 | V31: =September!V31 | W31: =IFERROR(VLOOKUP(V31, Tarieven!$A$2:$J$150, 10, FALSE), "0") -> 0 | X31: =Jaarbetalingen!AD31 -> 11 | Y31: 0 | Z31: =SUM(L31+O31+R31+U31+X31) -> 18 | AA31: =SUM(H31+K31)*E31 -> 0 | AB31: =SUM((L31*N31)+(O31*Q31)+(R31*T31)+(U31*W31)+Y31) -> 0 | AC31: =SUM(AB31-AA31) -> 0
A32: =Rooster!A33 -> Vrijdag | B32: =Rooster!B33 -> 0.70833333 | C32: =Rooster!C33 -> 60 | D32: =Rooster!D33 -> Cheer 12+ | F32: =Rooster!E33 -> Eigenaar | G32: =IFERROR(VLOOKUP(F32, Docenten!$A$2:$G$30, 7, FALSE), "0") -> 0 | H32: =SUM(G32/60)*C32 -> 0 | I32: =Rooster!H33 -> Santpoort Zuid | J32: =IFERROR(VLOOKUP(I32, Locaties!$A$2:$G$15, 7, FALSE), "0") -> 18.9 | K32: =SUM(J32/60)*C32 -> 18.9 | L32: =September!L32 -> 2 | N32: =IFERROR(VLOOKUP(M32, Tarieven!$A$1:$J$150, 10, FALSE), "0") -> 0 | O32: =September!O32 -> 1 | Q32: =IFERROR(VLOOKUP(P32, Tarieven!$A$2:$J$150, 10, FALSE), "0") -> 0 | R32: =September!R32 | T32: =IFERROR(VLOOKUP(S32, Tarieven!$A$2:$J$150, 10, FALSE), "0") -> 0 | U32: =September!U32 | V32: =September!V32 | W32: =IFERROR(VLOOKUP(V32, Tarieven!$A$2:$J$150, 10, FALSE), "0") -> 0 | X32: =Jaarbetalingen!AD32 -> 5 | Y32: 0 | Z32: =SUM(L32+O32+R32+U32+X32) -> 8 | AA32: =SUM(H32+K32)*E32 -> 0 | AB32: =SUM((L32*N32)+(O32*Q32)+(R32*T32)+(U32*W32)+Y32) -> 0 | AC32: =SUM(AB32-AA32) -> 0
A33: =Rooster!A34 -> Vrijdag | B33: =Rooster!B34 -> 0.75 | C33: =Rooster!C34 -> 60 | D33: =Rooster!D34 -> Urban-pop-Show 11+ | F33: =Rooster!E34 -> Eigenaar | G33: =IFERROR(VLOOKUP(F33, Docenten!$A$2:$G$30, 7, FALSE), "0") -> 0 | H33: =SUM(G33/60)*C33 -> 0 | I33: =Rooster!H34 -> Santpoort Noord | J33: =IFERROR(VLOOKUP(I33, Locaties!$A$2:$G$15, 7, FALSE), "0") -> 14.2 | K33: =SUM(J33/60)*C33 -> 14.2 | L33: =September!L33 -> 1 | N33: =IFERROR(VLOOKUP(M33, Tarieven!$A$1:$J$150, 10, FALSE), "0") -> 0 | O33: =September!O33 -> 1 | Q33: =IFERROR(VLOOKUP(P33, Tarieven!$A$2:$J$150, 10, FALSE), "0") -> 0 | R33: =September!R33 | T33: =IFERROR(VLOOKUP(S33, Tarieven!$A$2:$J$150, 10, FALSE), "0") -> 0 | U33: =September!U33 | V33: =September!V33 | W33: =IFERROR(VLOOKUP(V33, Tarieven!$A$2:$J$150, 10, FALSE), "0") -> 0 | X33: =Jaarbetalingen!AD33 -> 8 | Y33: 0 | Z33: =SUM(L33+O33+R33+U33+X33) -> 10 | AA33: =SUM(H33+K33)*E33 -> 0 | AB33: =SUM((L33*N33)+(O33*Q33)+(R33*T33)+(U33*W33)+Y33) -> 0 | AC33: =SUM(AB33-AA33) -> 0
A34: =Rooster!A35 -> Zaterdag | B34: =Rooster!B35 -> 0.375 | C34: =Rooster!C35 -> 60 | D34: =Rooster!D35 -> Peuters | F34: =Rooster!E35 -> Frederique | G34: =IFERROR(VLOOKUP(F34, Docenten!$A$2:$G$30, 7, FALSE), "0") -> 12.5 | H34: =SUM(G34/60)*C34 -> 12.5 | I34: =Rooster!H35 -> Santpoort Noord | J34: =IFERROR(VLOOKUP(I34, Locaties!$A$2:$G$15, 7, FALSE), "0") -> 14.2 | K34: =SUM(J34/60)*C34 -> 14.2 | L34: =September!L34 -> 9 | N34: =IFERROR(VLOOKUP(M34, Tarieven!$A$1:$J$150, 10, FALSE), "0") -> 0 | O34: =September!O34 | Q34: =IFERROR(VLOOKUP(P34, Tarieven!$A$2:$J$150, 10, FALSE), "0") -> 0 | R34: =September!R34 | T34: =IFERROR(VLOOKUP(S34, Tarieven!$A$2:$J$150, 10, FALSE), "0") -> 0 | U34: =September!U34 | V34: =September!V34 | W34: =IFERROR(VLOOKUP(V34, Tarieven!$A$2:$J$150, 10, FALSE), "0") -> 0 | X34: =Jaarbetalingen!AD34 -> 4 | Y34: 0 | Z34: =SUM(L34+O34+R34+U34+X34) -> 13 | AA34: =SUM(H34+K34)*E34 -> 0 | AB34: =SUM((L34*N34)+(O34*Q34)+(R34*T34)+(U34*W34)+Y34) -> 0 | AC34: =SUM(AB34-AA34) -> 0
A35: =Rooster!A36 -> Zaterdag | B35: =Rooster!B36 -> 0.40625 | C35: =Rooster!C36 -> 60 | D35: =Rooster!D36 -> Kleuters | F35: =Rooster!E36 -> Frederique | G35: =IFERROR(VLOOKUP(F35, Docenten!$A$2:$G$30, 7, FALSE), "0") -> 12.5 | H35: =SUM(G35/60)*C35 -> 12.5 | I35: =Rooster!H36 -> Santpoort Noord | J35: =IFERROR(VLOOKUP(I35, Locaties!$A$2:$G$15, 7, FALSE), "0") -> 14.2 | K35: =SUM(J35/60)*C35 -> 14.2 | L35: =September!L35 -> 10 | N35: =IFERROR(VLOOKUP(M35, Tarieven!$A$1:$J$150, 10, FALSE), "0") -> 0 | O35: =September!O35 | Q35: =IFERROR(VLOOKUP(P35, Tarieven!$A$2:$J$150, 10, FALSE), "0") -> 0 | R35: =September!R35 | T35: =IFERROR(VLOOKUP(S35, Tarieven!$A$2:$J$150, 10, FALSE), "0") -> 0 | U35: =September!U35 | V35: =September!V35 | W35: =IFERROR(VLOOKUP(V35, Tarieven!$A$2:$J$150, 10, FALSE), "0") -> 0 | X35: =Jaarbetalingen!AD35 -> 5 | Y35: 0 | Z35: =SUM(L35+O35+R35+U35+X35) -> 15 | AA35: =SUM(H35+K35)*E35 -> 0 | AB35: =SUM((L35*N35)+(O35*Q35)+(R35*T35)+(U35*W35)+Y35) -> 0 | AC35: =SUM(AB35-AA35) -> 0
A36: =Rooster!A37 -> Zaterdag | B36: =Rooster!B37 -> 0.4375 | C36: =Rooster!C37 -> 60 | D36: =Rooster!D37 -> Showdance 5-6 | F36: =Rooster!E37 -> Frederique | G36: =IFERROR(VLOOKUP(F36, Docenten!$A$2:$G$30, 7, FALSE), "0") -> 12.5 | H36: =SUM(G36/60)*C36 -> 12.5 | I36: =Rooster!H37 -> Santpoort Noord | J36: =IFERROR(VLOOKUP(I36, Locaties!$A$2:$G$15, 7, FALSE), "0") -> 14.2 | K36: =SUM(J36/60)*C36 -> 14.2 | L36: =September!L36 -> 3 | N36: =IFERROR(VLOOKUP(M36, Tarieven!$A$1:$J$150, 10, FALSE), "0") -> 0 | O36: =September!O36 -> 1 | Q36: =IFERROR(VLOOKUP(P36, Tarieven!$A$2:$J$150, 10, FALSE), "0") -> 0 | R36: =September!R36 | T36: =IFERROR(VLOOKUP(S36, Tarieven!$A$2:$J$150, 10, FALSE), "0") -> 0 | U36: =September!U36 | V36: =September!V36 | W36: =IFERROR(VLOOKUP(V36, Tarieven!$A$2:$J$150, 10, FALSE), "0") -> 0 | X36: =Jaarbetalingen!AD36 -> 9 | Y36: 0 | Z36: =SUM(L36+O36+R36+U36+X36) -> 13 | AA36: =SUM(H36+K36)*E36 -> 0 | AB36: =SUM((L36*N36)+(O36*Q36)+(R36*T36)+(U36*W36)+Y36) -> 0 | AC36: =SUM(AB36-AA36) -> 0
A37: =Rooster!A38 -> Zaterdag | B37: =Rooster!B38 -> 0.47916667 | C37: =Rooster!C38 -> 60 | D37: =Rooster!D38 -> Showdance 7+ | F37: =Rooster!E38 -> Frederique | G37: =IFERROR(VLOOKUP(F37, Docenten!$A$2:$G$30, 7, FALSE), "0") -> 12.5 | H37: =SUM(G37/60)*C37 -> 12.5 | I37: =Rooster!H38 -> Santpoort Noord | J37: =IFERROR(VLOOKUP(I37, Locaties!$A$2:$G$15, 7, FALSE), "0") -> 14.2 | K37: =SUM(J37/60)*C37 -> 14.2 | L37: =September!L37 -> 3 | N37: =IFERROR(VLOOKUP(M37, Tarieven!$A$1:$J$150, 10, FALSE), "0") -> 0 | O37: =September!O37 | Q37: =IFERROR(VLOOKUP(P37, Tarieven!$A$2:$J$150, 10, FALSE), "0") -> 0 | R37: =September!R37 | T37: =IFERROR(VLOOKUP(S37, Tarieven!$A$2:$J$150, 10, FALSE), "0") -> 0 | U37: =September!U37 | V37: =September!V37 | W37: =IFERROR(VLOOKUP(V37, Tarieven!$A$2:$J$150, 10, FALSE), "0") -> 0 | X37: =Jaarbetalingen!AD37 -> 4 | Y37: 0 | Z37: =SUM(L37+O37+R37+U37+X37) -> 7 | AA37: =SUM(H37+K37)*E37 -> 0 | AB37: =SUM((L37*N37)+(O37*Q37)+(R37*T37)+(U37*W37)+Y37) -> 0 | AC37: =SUM(AB37-AA37) -> 0
A38: =Rooster!A39 -> Zaterdag | B38: =Rooster!B39 -> 0.41666667 | C38: =Rooster!C39 -> 60 | D38: =Rooster!D39 -> Peuters | F38: =Rooster!E39 -> Tess | G38: =IFERROR(VLOOKUP(F38, Docenten!$A$2:$G$30, 7, FALSE), "0") -> 17.5 | H38: =SUM(G38/60)*C38 -> 17.5 | I38: =Rooster!H39 -> Santpoort Zuid | J38: =IFERROR(VLOOKUP(I38, Locaties!$A$2:$G$15, 7, FALSE), "0") -> 18.9 | K38: =SUM(J38/60)*C38 -> 18.9 | L38: =September!L38 | N38: =IFERROR(VLOOKUP(M38, Tarieven!$A$1:$J$150, 10, FALSE), "0") -> 0 | O38: =September!O38 | Q38: =IFERROR(VLOOKUP(P38, Tarieven!$A$2:$J$150, 10, FALSE), "0") -> 0 | R38: =September!R38 | T38: =IFERROR(VLOOKUP(S38, Tarieven!$A$2:$J$150, 10, FALSE), "0") -> 0 | U38: =September!U38 | V38: =September!V38 | W38: =IFERROR(VLOOKUP(V38, Tarieven!$A$2:$J$150, 10, FALSE), "0") -> 0 | X38: =Jaarbetalingen!AD38 -> 0 | Y38: 0 | Z38: =SUM(L38+O38+R38+U38+X38) -> 0 | AA38: =SUM(H38+K38)*E38 -> 0 | AB38: =SUM((L38*N38)+(O38*Q38)+(R38*T38)+(U38*W38)+Y38) -> 0 | AC38: =SUM(AB38-AA38) -> 0
A39: =Rooster!A40 -> Zaterdag | B39: =Rooster!B40 -> 0.44791667 | C39: =Rooster!C40 -> 60 | D39: =Rooster!D40 -> Kleuters | F39: =Rooster!E40 -> Tess | G39: =IFERROR(VLOOKUP(F39, Docenten!$A$2:$G$30, 7, FALSE), "0") -> 17.5 | H39: =SUM(G39/60)*C39 -> 17.5 | I39: =Rooster!H40 -> Santpoort Zuid | J39: =IFERROR(VLOOKUP(I39, Locaties!$A$2:$G$15, 7, FALSE), "0") -> 18.9 | K39: =SUM(J39/60)*C39 -> 18.9 | L39: =September!L39 | N39: =IFERROR(VLOOKUP(M39, Tarieven!$A$1:$J$150, 10, FALSE), "0") -> 0 | O39: =September!O39 | Q39: =IFERROR(VLOOKUP(P39, Tarieven!$A$2:$J$150, 10, FALSE), "0") -> 0 | R39: =September!R39 | T39: =IFERROR(VLOOKUP(S39, Tarieven!$A$2:$J$150, 10, FALSE), "0") -> 0 | U39: =September!U39 | V39: =September!V39 | W39: =IFERROR(VLOOKUP(V39, Tarieven!$A$2:$J$150, 10, FALSE), "0") -> 0 | X39: =Jaarbetalingen!AD39 -> 0 | Y39: 0 | Z39: =SUM(L39+O39+R39+U39+X39) -> 0 | AA39: =SUM(H39+K39)*E39 -> 0 | AB39: =SUM((L39*N39)+(O39*Q39)+(R39*T39)+(U39*W39)+Y39) -> 0 | AC39: =SUM(AB39-AA39) -> 0
A40: =Rooster!A41 | B40: =Rooster!B41 | C40: =Rooster!C41 | D40: =Rooster!D41 | F40: =Rooster!E41 | G40: =IFERROR(VLOOKUP(F40, Docenten!$A$2:$G$30, 7, FALSE), "0") -> 0 | H40: =SUM(G40/60)*C40 -> 0 | I40: =Rooster!H41 | J40: =IFERROR(VLOOKUP(I40, Locaties!$A$2:$G$15, 7, FALSE), "0") -> 0 | K40: =SUM(J40/60)*C40 -> 0 | L40: =September!L40 | N40: =IFERROR(VLOOKUP(M40, Tarieven!$A$1:$J$150, 10, FALSE), "0") -> 0 | O40: =September!O40 | Q40: =IFERROR(VLOOKUP(P40, Tarieven!$A$2:$J$150, 10, FALSE), "0") -> 0 | R40: =September!R40 | T40: =IFERROR(VLOOKUP(S40, Tarieven!$A$2:$J$150, 10, FALSE), "0") -> 0 | U40: =September!U40 | V40: =September!V40 | W40: =IFERROR(VLOOKUP(V40, Tarieven!$A$2:$J$150, 10, FALSE), "0") -> 0 | X40: =Jaarbetalingen!AD40 -> 0 | Y40: 0 | Z40: =SUM(L40+O40+R40+U40+X40) -> 0 | AA40: =SUM(H40+K40)*E40 -> 0 | AB40: =SUM((L40*N40)+(O40*Q40)+(R40*T40)+(U40*W40)+Y40) -> 0 | AC40: =SUM(AB40-AA40) -> 0
A41: =Rooster!A42 | B41: =Rooster!B42 | C41: =Rooster!C42 | D41: =Rooster!D42 | F41: =Rooster!E42 | G41: =IFERROR(VLOOKUP(F41, Docenten!$A$2:$G$30, 7, FALSE), "0") -> 0 | H41: =SUM(G41/60)*C41 -> 0 | I41: =Rooster!H42 | J41: =IFERROR(VLOOKUP(I41, Locaties!$A$2:$G$15, 7, FALSE), "0") -> 0 | K41: =SUM(J41/60)*C41 -> 0 | L41: =September!L41 | N41: =IFERROR(VLOOKUP(M41, Tarieven!$A$1:$J$150, 10, FALSE), "0") -> 0 | O41: =September!O41 | Q41: =IFERROR(VLOOKUP(P41, Tarieven!$A$2:$J$150, 10, FALSE), "0") -> 0 | R41: =September!R41 | T41: =IFERROR(VLOOKUP(S41, Tarieven!$A$2:$J$150, 10, FALSE), "0") -> 0 | U41: =September!U41 | V41: =September!V41 | W41: =IFERROR(VLOOKUP(V41, Tarieven!$A$2:$J$150, 10, FALSE), "0") -> 0 | X41: =Jaarbetalingen!AD41 -> 0 | Y41: 0 | Z41: =SUM(L41+O41+R41+U41+X41) -> 0 | AA41: =SUM(H41+K41)*E41 -> 0 | AB41: =SUM((L41*N41)+(O41*Q41)+(R41*T41)+(U41*W41)+Y41) -> 0 | AC41: =SUM(AB41-AA41) -> 0
A42: =Rooster!A43 -> Maandag | B42: =Rooster!B43 -> 0.39583333 | C42: =Rooster!C43 -> 60 | D42: =Rooster!D43 -> Kinderopvang | F42: =Rooster!E43 -> Opvang T | G42: =IFERROR(VLOOKUP(F42, Docenten!$A$2:$G$30, 7, FALSE), "0") -> 45 | H42: =SUM(G42/60)*C42 -> 45 | I42: =Rooster!H43 | J42: =IFERROR(VLOOKUP(I42, Locaties!$A$2:$G$15, 7, FALSE), "0") -> 0 | K42: =SUM(J42/60)*C42 -> 0 | L42: 5 | M42: Aangepast tarief | N42: 400 | O42: =September!O42 | Q42: =IFERROR(VLOOKUP(P42, Tarieven!$A$2:$J$150, 10, FALSE), "0") -> 0 | R42: =September!R42 | T42: =IFERROR(VLOOKUP(S42, Tarieven!$A$2:$J$150, 10, FALSE), "0") -> 0 | U42: =September!U42 | V42: =September!V42 | W42: =IFERROR(VLOOKUP(V42, Tarieven!$A$2:$J$150, 10, FALSE), "0") -> 0 | X42: =Jaarbetalingen!AD42 -> 0 | Y42: 0 | Z42: =SUM(L42+O42+R42+U42+X42) -> 5 | AA42: =SUM(H42+K42)*E42 -> 0 | AB42: =SUM((L42*N42)+(O42*Q42)+(R42*T42)+(U42*W42)+Y42) -> 2000 | AC42: =SUM(AB42-AA42) -> 2000
G43: =IFERROR(VLOOKUP(F43, Docenten!$A$2:$G$30, 7, FALSE), "0") -> 0 | H43: =SUM(G43/60)*C43 -> 0 | I43: =Rooster!H44 | J43: =IFERROR(VLOOKUP(I43, Locaties!$A$2:$G$15, 7, FALSE), "0") -> 0 | K43: =SUM(J43/60)*C43 -> 0 | L43: =September!L43 | N43: =IFERROR(VLOOKUP(M43, Tarieven!$A$1:$J$150, 10, FALSE), "0") -> 0 | O43: =September!O43 | Q43: =IFERROR(VLOOKUP(P43, Tarieven!$A$2:$J$150, 10, FALSE), "0") -> 0 | R43: =September!R43 | T43: =IFERROR(VLOOKUP(S43, Tarieven!$A$2:$J$150, 10, FALSE), "0") -> 0 | U43: =September!U43 | V43: =September!V43 | W43: =IFERROR(VLOOKUP(V43, Tarieven!$A$2:$J$150, 10, FALSE), "0") -> 0 | X43: =Jaarbetalingen!AD43 -> 0 | Y43: 0 | Z43: =SUM(L43+O43+R43+U43+X43) -> 0 | AA43: =SUM(H43+K43)*E43 -> 0 | AB43: =SUM((L43*N43)+(O43*Q43)+(R43*T43)+(U43*W43)+Y43) -> 0 | AC43: =SUM(AB43-AA43) -> 0
G44: =IFERROR(VLOOKUP(F44, Docenten!$A$2:$G$30, 7, FALSE), "0") -> 0 | H44: =SUM(G44/60)*C44 -> 0 | I44: =Rooster!H45 | J44: =IFERROR(VLOOKUP(I44, Locaties!$A$2:$G$15, 7, FALSE), "0") -> 0 | K44: =SUM(J44/60)*C44 -> 0 | L44: =September!L44 | N44: =IFERROR(VLOOKUP(M44, Tarieven!$A$1:$J$150, 10, FALSE), "0") -> 0 | O44: =September!O44 | Q44: =IFERROR(VLOOKUP(P44, Tarieven!$A$2:$J$150, 10, FALSE), "0") -> 0 | R44: =September!R44 | T44: =IFERROR(VLOOKUP(S44, Tarieven!$A$2:$J$150, 10, FALSE), "0") -> 0 | U44: =September!U44 | V44: =September!V44 | W44: =IFERROR(VLOOKUP(V44, Tarieven!$A$2:$J$150, 10, FALSE), "0") -> 0 | X44: =Jaarbetalingen!AD44 -> 0 | Y44: 0 | Z44: =SUM(L44+O44+R44+U44+X44) -> 0 | AA44: =SUM(H44+K44)*E44 -> 0 | AB44: =SUM((L44*N44)+(O44*Q44)+(R44*T44)+(U44*W44)+Y44) -> 0 | AC44: =SUM(AB44-AA44) -> 0
A45: =Rooster!A46 | B45: =Rooster!B46 | C45: =Rooster!C46 | D45: =Rooster!D46 | F45: =Rooster!E46 | G45: =IFERROR(VLOOKUP(F45, Docenten!$A$2:$G$30, 7, FALSE), "0") -> 0 | H45: =SUM(G45/60)*C45 -> 0 | I45: =Rooster!H46 | J45: =IFERROR(VLOOKUP(I45, Locaties!$A$2:$G$15, 7, FALSE), "0") -> 0 | K45: =SUM(J45/60)*C45 -> 0 | L45: =September!L45 | N45: =IFERROR(VLOOKUP(M45, Tarieven!$A$1:$J$150, 10, FALSE), "0") -> 0 | O45: =September!O45 | Q45: =IFERROR(VLOOKUP(P45, Tarieven!$A$2:$J$150, 10, FALSE), "0") -> 0 | R45: =September!R45 | T45: =IFERROR(VLOOKUP(S45, Tarieven!$A$2:$J$150, 10, FALSE), "0") -> 0 | U45: =September!U45 | V45: =September!V45 | W45: =IFERROR(VLOOKUP(V45, Tarieven!$A$2:$J$150, 10, FALSE), "0") -> 0 | X45: =Jaarbetalingen!AD45 -> 0 | Y45: 0 | Z45: =SUM(L45+O45+R45+U45+X45) -> 0 | AA45: =SUM(H45+K45)*E45 -> 0 | AB45: =SUM((L45*N45)+(O45*Q45)+(R45*T45)+(U45*W45)+Y45) -> 0 | AC45: =SUM(AB45-AA45) -> 0
A46: =Rooster!A47 | B46: =Rooster!B47 | C46: =Rooster!C47 | D46: =Rooster!D47 | F46: =Rooster!E47 | G46: =IFERROR(VLOOKUP(F46, Docenten!$A$2:$G$30, 7, FALSE), "0") -> 0 | H46: =SUM(G46/60)*C46 -> 0 | I46: =Rooster!H47 | J46: =IFERROR(VLOOKUP(I46, Locaties!$A$2:$G$15, 7, FALSE), "0") -> 0 | K46: =SUM(J46/60)*C46 -> 0 | L46: =September!L46 | N46: =IFERROR(VLOOKUP(M46, Tarieven!$A$1:$J$150, 10, FALSE), "0") -> 0 | O46: =September!O46 | Q46: =IFERROR(VLOOKUP(P46, Tarieven!$A$2:$J$150, 10, FALSE), "0") -> 0 | R46: =September!R46 | T46: =IFERROR(VLOOKUP(S46, Tarieven!$A$2:$J$150, 10, FALSE), "0") -> 0 | U46: =September!U46 | V46: =September!V46 | W46: =IFERROR(VLOOKUP(V46, Tarieven!$A$2:$J$150, 10, FALSE), "0") -> 0 | X46: =Jaarbetalingen!AD46 -> 0 | Y46: 0 | Z46: =SUM(L46+O46+R46+U46+X46) -> 0 | AA46: =SUM(H46+K46)*E46 -> 0 | AB46: =SUM((L46*N46)+(O46*Q46)+(R46*T46)+(U46*W46)+Y46) -> 0 | AC46: =SUM(AB46-AA46) -> 0
A47: =Rooster!A48 -> Donderdag | B47: =Rooster!B48 -> 0.75 | C47: =Rooster!C48 -> 60 | D47: =Rooster!D48 -> Turnen 6+ | F47: =Rooster!E48 -> Dion + 3 | G47: =IFERROR(VLOOKUP(F47, Docenten!$A$2:$G$30, 7, FALSE), "0") -> 34 | H47: =SUM(G47/60)*C47 -> 34 | I47: =Rooster!H48 -> Santpoort Noord | J47: =IFERROR(VLOOKUP(I47, Locaties!$A$2:$G$15, 7, FALSE), "0") -> 14.2 | K47: =SUM(J47/60)*C47 -> 14.2 | L47: =September!L47 | N47: =IFERROR(VLOOKUP(M47, Tarieven!$A$1:$J$150, 10, FALSE), "0") -> 0 | O47: =September!O47 | Q47: =IFERROR(VLOOKUP(P47, Tarieven!$A$2:$J$150, 10, FALSE), "0") -> 0 | R47: =September!R47 | T47: =IFERROR(VLOOKUP(S47, Tarieven!$A$2:$J$150, 10, FALSE), "0") -> 0 | U47: =September!U47 | V47: =September!V47 | W47: =IFERROR(VLOOKUP(V47, Tarieven!$A$2:$J$150, 10, FALSE), "0") -> 0 | X47: =Jaarbetalingen!AD47 -> 0 | Y47: 0 | Z47: =SUM(L47+O47+R47+U47+X47) -> 0 | AA47: =SUM(H47+K47)*E47 -> 0 | AB47: =SUM((L47*N47)+(O47*Q47)+(R47*T47)+(U47*W47)+Y47) -> 0 | AC47: =SUM(AB47-AA47) -> 0
A48: =Rooster!A49 -> Donderdag | B48: =Rooster!B49 -> 0.79166667 | C48: =Rooster!C49 -> 60 | D48: =Rooster!D49 -> Turnen 12+ | F48: =Rooster!E49 -> Dion + 3 | G48: =IFERROR(VLOOKUP(F48, Docenten!$A$2:$G$30, 7, FALSE), "0") -> 34 | H48: =SUM(G48/60)*C48 -> 34 | I48: =Rooster!H49 -> Santpoort Noord | J48: =IFERROR(VLOOKUP(I48, Locaties!$A$2:$G$15, 7, FALSE), "0") -> 14.2 | K48: =SUM(J48/60)*C48 -> 14.2 | L48: =September!L48 | N48: =IFERROR(VLOOKUP(M48, Tarieven!$A$1:$J$150, 10, FALSE), "0") -> 0 | O48: =September!O48 | Q48: =IFERROR(VLOOKUP(P48, Tarieven!$A$2:$J$150, 10, FALSE), "0") -> 0 | R48: =September!R48 | T48: =IFERROR(VLOOKUP(S48, Tarieven!$A$2:$J$150, 10, FALSE), "0") -> 0 | U48: =September!U48 | V48: =September!V48 | W48: =IFERROR(VLOOKUP(V48, Tarieven!$A$2:$J$150, 10, FALSE), "0") -> 0 | X48: =Jaarbetalingen!AD48 -> 0 | Y48: 0 | Z48: =SUM(L48+O48+R48+U48+X48) -> 0 | AA48: =SUM(H48+K48)*E48 -> 0 | AB48: =SUM((L48*N48)+(O48*Q48)+(R48*T48)+(U48*W48)+Y48) -> 0 | AC48: =SUM(AB48-AA48) -> 0
A49: =Rooster!A50 | B49: =Rooster!B50 | C49: =Rooster!C50 | D49: =Rooster!D50 | F49: =Rooster!E50 | G49: =IFERROR(VLOOKUP(F49, Docenten!$A$2:$G$30, 7, FALSE), "0") -> 0 | H49: =SUM(G49/60)*C49 -> 0 | I49: =Rooster!H50 | J49: =IFERROR(VLOOKUP(I49, Locaties!$A$2:$G$15, 7, FALSE), "0") -> 0 | K49: =SUM(J49/60)*C49 -> 0 | L49: =September!L49 | N49: =IFERROR(VLOOKUP(M49, Tarieven!$A$1:$J$150, 10, FALSE), "0") -> 0 | O49: =September!O49 | Q49: =IFERROR(VLOOKUP(P49, Tarieven!$A$2:$J$150, 10, FALSE), "0") -> 0 | R49: =September!R49 | T49: =IFERROR(VLOOKUP(S49, Tarieven!$A$2:$J$150, 10, FALSE), "0") -> 0 | U49: =September!U49 | V49: =September!V49 | W49: =IFERROR(VLOOKUP(V49, Tarieven!$A$2:$J$150, 10, FALSE), "0") -> 0 | X49: =Jaarbetalingen!AD49 -> 0 | Y49: 0 | Z49: =SUM(L49+O49+R49+U49+X49) -> 0 | AA49: =SUM(H49+K49)*E49 -> 0 | AB49: =SUM((L49*N49)+(O49*Q49)+(R49*T49)+(U49*W49)+Y49) -> 0 | AC49: =SUM(AB49-AA49) -> 0
A50: =Rooster!A51 | B50: =Rooster!B51 | C50: =Rooster!C51 | D50: =Rooster!D51 | F50: =Rooster!E51 | G50: =IFERROR(VLOOKUP(F50, Docenten!$A$2:$G$30, 7, FALSE), "0") -> 0 | H50: =SUM(G50/60)*C50 -> 0 | I50: =Rooster!H51 | J50: =IFERROR(VLOOKUP(I50, Locaties!$A$2:$G$15, 7, FALSE), "0") -> 0 | K50: =SUM(J50/60)*C50 -> 0 | L50: =September!L50 | N50: =IFERROR(VLOOKUP(M50, Tarieven!$A$1:$J$150, 10, FALSE), "0") -> 0 | O50: =September!O50 | Q50: =IFERROR(VLOOKUP(P50, Tarieven!$A$2:$J$150, 10, FALSE), "0") -> 0 | R50: =September!R50 | T50: =IFERROR(VLOOKUP(S50, Tarieven!$A$2:$J$150, 10, FALSE), "0") -> 0 | U50: =September!U50 | V50: =September!V50 | W50: =IFERROR(VLOOKUP(V50, Tarieven!$A$2:$J$150, 10, FALSE), "0") -> 0 | X50: =Jaarbetalingen!AD50 -> 0 | Y50: 0 | Z50: =SUM(L50+O50+R50+U50+X50) -> 0 | AA50: =SUM(H50+K50)*E50 -> 0 | AB50: =SUM((L50*N50)+(O50*Q50)+(R50*T50)+(U50*W50)+Y50) -> 0 | AC50: =SUM(AB50-AA50) -> 0
A51: =Rooster!A52 | B51: =Rooster!B52 | C51: =Rooster!C52 | D51: =Rooster!D52 | F51: =Rooster!E52 | G51: =IFERROR(VLOOKUP(F51, Docenten!$A$2:$G$30, 7, FALSE), "0") -> 0 | H51: =SUM(G51/60)*C51 -> 0 | I51: =Rooster!H52 | J51: =IFERROR(VLOOKUP(I51, Locaties!$A$2:$G$15, 7, FALSE), "0") -> 0 | K51: =SUM(J51/60)*C51 -> 0 | L51: =September!L51 | N51: =IFERROR(VLOOKUP(M51, Tarieven!$A$1:$J$150, 10, FALSE), "0") -> 0 | O51: =September!O51 | Q51: =IFERROR(VLOOKUP(P51, Tarieven!$A$2:$J$150, 10, FALSE), "0") -> 0 | R51: =September!R51 | T51: =IFERROR(VLOOKUP(S51, Tarieven!$A$2:$J$150, 10, FALSE), "0") -> 0 | U51: =September!U51 | V51: =September!V51 | W51: =IFERROR(VLOOKUP(V51, Tarieven!$A$2:$J$150, 10, FALSE), "0") -> 0 | X51: =Jaarbetalingen!AD51 -> 0 | Y51: 0 | Z51: =SUM(L51+O51+R51+U51+X51) -> 0 | AA51: =SUM(H51+K51)*E51 -> 0 | AB51: =SUM((L51*N51)+(O51*Q51)+(R51*T51)+(U51*W51)+Y51) -> 0 | AC51: =SUM(AB51-AA51) -> 0
A52: =Rooster!A53 | B52: =Rooster!B53 | C52: =Rooster!C53 | D52: =Rooster!D53 | F52: =Rooster!E53 | G52: =IFERROR(VLOOKUP(F52, Docenten!$A$2:$G$30, 7, FALSE), "0") -> 0 | H52: =SUM(G52/60)*C52 -> 0 | I52: =Rooster!H53 | J52: =IFERROR(VLOOKUP(I52, Locaties!$A$2:$G$15, 7, FALSE), "0") -> 0 | K52: =SUM(J52/60)*C52 -> 0 | L52: =September!L52 | N52: =IFERROR(VLOOKUP(M52, Tarieven!$A$1:$J$150, 10, FALSE), "0") -> 0 | O52: =September!O52 | Q52: =IFERROR(VLOOKUP(P52, Tarieven!$A$2:$J$150, 10, FALSE), "0") -> 0 | R52: =September!R52 | T52: =IFERROR(VLOOKUP(S52, Tarieven!$A$2:$J$150, 10, FALSE), "0") -> 0 | U52: =September!U52 | V52: =September!V52 | W52: =IFERROR(VLOOKUP(V52, Tarieven!$A$2:$J$150, 10, FALSE), "0") -> 0 | X52: =Jaarbetalingen!AD52 -> 0 | Y52: 0 | Z52: =SUM(L52+O52+R52+U52+X52) -> 0 | AA52: =SUM(H52+K52)*E52 -> 0 | AB52: =SUM((L52*N52)+(O52*Q52)+(R52*T52)+(U52*W52)+Y52) -> 0 | AC52: =SUM(AB52-AA52) -> 0
A53: =Rooster!A54 | B53: =Rooster!B54 | C53: =Rooster!C54 | D53: =Rooster!D54 | F53: =Rooster!E54 | G53: =IFERROR(VLOOKUP(F53, Docenten!$A$2:$G$30, 7, FALSE), "0") -> 0 | H53: =SUM(G53/60)*C53 -> 0 | I53: =Rooster!H54 | J53: =IFERROR(VLOOKUP(I53, Locaties!$A$2:$G$15, 7, FALSE), "0") -> 0 | K53: =SUM(J53/60)*C53 -> 0 | L53: =September!L53 | N53: =IFERROR(VLOOKUP(M53, Tarieven!$A$1:$J$150, 10, FALSE), "0") -> 0 | O53: =September!O53 | Q53: =IFERROR(VLOOKUP(P53, Tarieven!$A$2:$J$150, 10, FALSE), "0") -> 0 | R53: =September!R53 | T53: =IFERROR(VLOOKUP(S53, Tarieven!$A$2:$J$150, 10, FALSE), "0") -> 0 | U53: =September!U53 | V53: =September!V53 | W53: =IFERROR(VLOOKUP(V53, Tarieven!$A$2:$J$150, 10, FALSE), "0") -> 0 | X53: =Jaarbetalingen!AD53 -> 0 | Y53: 0 | Z53: =SUM(L53+O53+R53+U53+X53) -> 0 | AA53: =SUM(H53+K53)*E53 -> 0 | AB53: =SUM((L53*N53)+(O53*Q53)+(R53*T53)+(U53*W53)+Y53) -> 0 | AC53: =SUM(AB53-AA53) -> 0
A54: =Rooster!A55 | B54: =Rooster!B55 | C54: =Rooster!C55 | D54: =Rooster!D55 | F54: =Rooster!E55 | G54: =IFERROR(VLOOKUP(F54, Docenten!$A$2:$G$30, 7, FALSE), "0") -> 0 | H54: =SUM(G54/60)*C54 -> 0 | I54: =Rooster!H55 | J54: =IFERROR(VLOOKUP(I54, Locaties!$A$2:$G$15, 7, FALSE), "0") -> 0 | K54: =SUM(J54/60)*C54 -> 0 | L54: =September!L54 | N54: =IFERROR(VLOOKUP(M54, Tarieven!$A$1:$J$150, 10, FALSE), "0") -> 0 | O54: =September!O54 | Q54: =IFERROR(VLOOKUP(P54, Tarieven!$A$2:$J$150, 10, FALSE), "0") -> 0 | R54: =September!R54 | T54: =IFERROR(VLOOKUP(S54, Tarieven!$A$2:$J$150, 10, FALSE), "0") -> 0 | U54: =September!U54 | V54: =September!V54 | W54: =IFERROR(VLOOKUP(V54, Tarieven!$A$2:$J$150, 10, FALSE), "0") -> 0 | X54: =Jaarbetalingen!AD54 -> 0 | Y54: 0 | Z54: =SUM(L54+O54+R54+U54+X54) -> 0 | AA54: =SUM(H54+K54)*E54 -> 0 | AB54: =SUM((L54*N54)+(O54*Q54)+(R54*T54)+(U54*W54)+Y54) -> 0 | AC54: =SUM(AB54-AA54) -> 0
A55: =Rooster!A56 | B55: =Rooster!B56 | C55: =Rooster!C56 | D55: =Rooster!D56 | F55: =Rooster!E56 | G55: =IFERROR(VLOOKUP(F55, Docenten!$A$2:$G$30, 7, FALSE), "0") -> 0 | H55: =SUM(G55/60)*C55 -> 0 | I55: =Rooster!H56 | J55: =IFERROR(VLOOKUP(I55, Locaties!$A$2:$G$15, 7, FALSE), "0") -> 0 | K55: =SUM(J55/60)*C55 -> 0 | L55: =September!L55 | N55: =IFERROR(VLOOKUP(M55, Tarieven!$A$1:$J$150, 10, FALSE), "0") -> 0 | O55: =September!O55 | Q55: =IFERROR(VLOOKUP(P55, Tarieven!$A$2:$J$150, 10, FALSE), "0") -> 0 | R55: =September!R55 | T55: =IFERROR(VLOOKUP(S55, Tarieven!$A$2:$J$150, 10, FALSE), "0") -> 0 | U55: =September!U55 | V55: =September!V55 | W55: =IFERROR(VLOOKUP(V55, Tarieven!$A$2:$J$150, 10, FALSE), "0") -> 0 | X55: =Jaarbetalingen!AD55 -> 0 | Y55: 0 | Z55: =SUM(L55+O55+R55+U55+X55) -> 0 | AA55: =SUM(H55+K55)*E55 -> 0 | AB55: =SUM((L55*N55)+(O55*Q55)+(R55*T55)+(U55*W55)+Y55) -> 0 | AC55: =SUM(AB55-AA55) -> 0
A56: =Rooster!A57 | B56: =Rooster!B57 | C56: =Rooster!C57 | D56: =Rooster!D57 | F56: =Rooster!E57 | G56: =IFERROR(VLOOKUP(F56, Docenten!$A$2:$G$30, 7, FALSE), "0") -> 0 | H56: =SUM(G56/60)*C56 -> 0 | I56: =Rooster!H57 | J56: =IFERROR(VLOOKUP(I56, Locaties!$A$2:$G$15, 7, FALSE), "0") -> 0 | K56: =SUM(J56/60)*C56 -> 0 | L56: =September!L56 | N56: =IFERROR(VLOOKUP(M56, Tarieven!$A$1:$J$150, 10, FALSE), "0") -> 0 | O56: =September!O56 | Q56: =IFERROR(VLOOKUP(P56, Tarieven!$A$2:$J$150, 10, FALSE), "0") -> 0 | R56: =September!R56 | T56: =IFERROR(VLOOKUP(S56, Tarieven!$A$2:$J$150, 10, FALSE), "0") -> 0 | U56: =September!U56 | V56: =September!V56 | W56: =IFERROR(VLOOKUP(V56, Tarieven!$A$2:$J$150, 10, FALSE), "0") -> 0 | X56: =Jaarbetalingen!AD56 -> 0 | Y56: 0 | Z56: =SUM(L56+O56+R56+U56+X56) -> 0 | AA56: =SUM(H56+K56)*E56 -> 0 | AB56: =SUM((L56*N56)+(O56*Q56)+(R56*T56)+(U56*W56)+Y56) -> 0 | AC56: =SUM(AB56-AA56) -> 0
... A100: =Rooster!A101 | B100: =Rooster!B101 | C100: =Rooster!C101 | D100: =Rooster!D101 | F100: =Rooster!E101 | G100: =IFERROR(VLOOKUP(F100, Docenten!$A$2:$G$30, 7, FALSE), "0") -> 0 | H100: =SUM(G100/60)*C100 -> 0 | I100: =Rooster!H101 | J100: =IFERROR(VLOOKUP(I100, Locaties!$A$2:$G$15, 7, FALSE), "0") -> 0 | K100: =SUM(J100/60)*C100 -> 0 | L100: =September!L100 | N100: =IFERROR(VLOOKUP(M100, Tarieven!$A$1:$J$150, 10, FALSE), "0") -> 0 | O100: =September!O100 | Q100: =IFERROR(VLOOKUP(P100, Tarieven!$A$2:$J$150, 10, FALSE), "0") -> 0 | R100: =September!R100 | T100: =IFERROR(VLOOKUP(S100, Tarieven!$A$2:$J$150, 10, FALSE), "0") -> 0 | U100: =September!U100 | V100: =September!V100 | W100: =IFERROR(VLOOKUP(V100, Tarieven!$A$2:$J$150, 10, FALSE), "0") -> 0 | X100: =Jaarbetalingen!AD100 -> 0 | Y100: 0 | Z100: =SUM(L100+O100+R100+U100+X100) -> 0 | AA100: =SUM(H100+K100)*E100 -> 0 | AB100: =SUM((L100*N100)+(O100*Q100)+(R100*T100)+(U100*W100)+Y100) -> 0 | AC100: =SUM(AB100-AA100) -> 0
A101: =Rooster!A102 | B101: =Rooster!B102 | C101: =Rooster!C102 | D101: =Rooster!D102 | F101: =Rooster!E102 | G101: =IFERROR(VLOOKUP(F101, Docenten!$A$2:$G$30, 7, FALSE), "0") -> 0 | H101: =SUM(G101/60)*C101 -> 0 | I101: =Rooster!H102 | J101: =IFERROR(VLOOKUP(I101, Locaties!$A$2:$G$15, 7, FALSE), "0") -> 0 | K101: =SUM(J101/60)*C101 -> 0 | L101: =SUM(L2:L100) -> 93 | N101: =IFERROR(VLOOKUP(M101, Tarieven!$A$1:$J$150, 10, FALSE), "0") -> 0 | O101: =SUM(O2:O100) -> 53 | Q101: =IFERROR(VLOOKUP(P101, Tarieven!$A$2:$J$150, 10, FALSE), "0") -> 0 | R101: =SUM(R2:R100) -> 24 | T101: =IFERROR(VLOOKUP(S101, Tarieven!$A$2:$J$150, 10, FALSE), "0") -> 0 | U101: =September!U101 -> 0 | V101: =September!V101 | W101: =IFERROR(VLOOKUP(V101, Tarieven!$A$2:$J$150, 10, FALSE), "0") -> 0 | X101: =Jaarbetalingen!AD101 -> 220 | Y101: 0 | Z101: =SUM(Z2:Z100) -> 390 | AA101: =SUM(H101+K101)*E101 -> 0 | AB101: =SUM((L101*N101)+(O101*Q101)+(R101*T101)+(U101*W101)+Y101) -> 0 | AC101: =SUM(AB101-AA101) -> 0

Sheet September
A1: Lesdag | B1: Lestijd | C1: Minuten les | D1: Naam les | E1: Aantal lessen deze maand | F1: Docent | G1: Tarief docent | H1: Tarief docent per les | I1: Locatie | J1: Zaalhuur per uur | K1: Zaalhuur per les | L1: Aantal leden tarief 1 | M1: Type lidmaatschap 1 | N1: Tarief 1 | O1: Aantal leden tarief 2 | P1: Type lidmaatschap 2 | Q1: Tarief 2 | R1: Aantal leden tarief 3 | S1: Type lidmaatschap 3 | T1: Tarief 3 | U1: Aantal leden tarief 4 | V1: Type lidmaatschap 4 | W1: Tarief 4 (excl btw) | X1: Aantal leden met een jaarabb. | Y1: Is hij betaald in deze maand? Vul hieronder het bedrag in. | Z1: Totaal aantal leden | AA1: Kosten per maand | AB1: Inkomsten per maand | AC1: Winst per maand | AD1: Kolom 30
A2: =Rooster!A3 | B2: =Rooster!B3 | C2: =Rooster!C3 | D2: =Rooster!D3 | F2: =Rooster!E3 | G2: =IFERROR(VLOOKUP(F2, Docenten!$A$2:$G$30, 7, FALSE), "0") -> 0 | H2: =SUM(G2/60)*C2 -> 0 | I2: =Rooster!H3 | J2: =IFERROR(VLOOKUP(I2, Locaties!$A$2:$G$15, 7, FALSE), "0") -> 0 | K2: =SUM(J2/60)*C2 -> 0 | N2: =IFERROR(VLOOKUP(M2, Tarieven!$A$1:$J$150, 10, FALSE), "0") -> 0 | Q2: =IFERROR(VLOOKUP(P2, Tarieven!$A$2:$J$150, 10, FALSE), "0") -> 0 | S2: =Augustus!S2 | T2: =IFERROR(VLOOKUP(S2, Tarieven!$A$2:$J$150, 10, FALSE), "0") -> 0 | W2: =IFERROR(VLOOKUP(V2, Tarieven!$A$2:$J$150, 10, FALSE), "0") -> 0 | X2: =Augustus!X2 -> 0 | Y2: 0 | Z2: =SUM(L2+O2+R2+U2+X2) -> 0 | AA2: =SUM(H2+K2)*E2 -> 0 | AB2: =SUM((L2*N2)+(O2*Q2)+(R2*T2)+(U2*W2)+Y2) -> 0 | AC2: =SUM(AB2-AA2) -> 0 | AE2: Categorie | AF2: Bedrag | AG2: Kolom 1
A3: =Rooster!A4 | B3: =Rooster!B4 | C3: =Rooster!C4 | D3: =Rooster!D4 | F3: =Rooster!E4 | G3: =IFERROR(VLOOKUP(F3, Docenten!$A$2:$G$30, 7, FALSE), "0") -> 0 | H3: =SUM(G3/60)*C3 -> 0 | I3: =Rooster!H4 | J3: =IFERROR(VLOOKUP(I3, Locaties!$A$2:$G$15, 7, FALSE), "0") -> 0 | K3: =SUM(J3/60)*C3 -> 0 | N3: =IFERROR(VLOOKUP(M3, Tarieven!$A$1:$J$150, 10, FALSE), "0") -> 0 | Q3: =IFERROR(VLOOKUP(P3, Tarieven!$A$2:$J$150, 10, FALSE), "0") -> 0 | T3: =IFERROR(VLOOKUP(S3, Tarieven!$A$2:$J$150, 10, FALSE), "0") -> 0 | W3: =IFERROR(VLOOKUP(V3, Tarieven!$A$2:$J$150, 10, FALSE), "0") -> 0 | X3: =Augustus!X3 -> 0 | Y3: 0 | Z3: =SUM(L3+O3+R3+U3+X3) -> 0 | AA3: =SUM(H3+K3)*E3 -> 0 | AB3: =SUM((L3*N3)+(O3*Q3)+(R3*T3)+(U3*W3)+Y3) -> 0 | AC3: =SUM(AB3-AA3) -> 0 | AE3: Inkomsten lessen | AF3: =SUM(AB2:AB101) -> 6935.928
A4: =Rooster!A5 -> Maandag | B4: =Rooster!B5 -> 0.625 | C4: =Rooster!C5 -> 60 | D4: =Rooster!D5 -> Kleuterdans | F4: =Rooster!E5 -> Lotte | G4: =IFERROR(VLOOKUP(F4, Docenten!$A$2:$G$30, 7, FALSE), "0") -> 22.5 | H4: =SUM(G4/60)*C4 -> 22.5 | I4: =Rooster!H5 -> Santpoort Zuid | J4: =IFERROR(VLOOKUP(I4, Locaties!$A$2:$G$15, 7, FALSE), "0") -> 18.9 | K4: =SUM(J4/60)*C4 -> 18.9 | N4: =IFERROR(VLOOKUP(M4, Tarieven!$A$1:$J$150, 10, FALSE), "0") -> 0 | Q4: =IFERROR(VLOOKUP(P4, Tarieven!$A$2:$J$150, 10, FALSE), "0") -> 0 | T4: =IFERROR(VLOOKUP(S4, Tarieven!$A$2:$J$150, 10, FALSE), "0") -> 0 | W4: =IFERROR(VLOOKUP(V4, Tarieven!$A$2:$J$150, 10, FALSE), "0") -> 0 | X4: =Augustus!X4 -> 0 | Y4: 0 | Z4: =SUM(L4+O4+R4+U4+X4) -> 0 | AA4: =SUM(H4+K4)*E4 -> 0 | AB4: =SUM((L4*N4)+(O4*Q4)+(R4*T4)+(U4*W4)+Y4) -> 0 | AC4: =SUM(AB4-AA4) -> 0 | AE4: Inkomsten overige | AF4: ='Extra activiteiten'!K3 -> 11430
A5: =Rooster!A6 -> Maandag | B5: =Rooster!B6 -> 0.625 | C5: =Rooster!C6 -> 60 | D5: =Rooster!D6 -> Streetdance 6+ | E5: 5 | F5: =Rooster!E6 -> Lotte | G5: =IFERROR(VLOOKUP(F5, Docenten!$A$2:$G$30, 7, FALSE), "0") -> 22.5 | H5: =SUM(G5/60)*C5 -> 22.5 | I5: =Rooster!H6 -> Santpoort Zuid | J5: =IFERROR(VLOOKUP(I5, Locaties!$A$2:$G$15, 7, FALSE), "0") -> 18.9 | K5: =SUM(J5/60)*C5 -> 18.9 | L5: 2 | M5: 2x per week abbo | N5: =IFERROR(VLOOKUP(M5, Tarieven!$A$1:$J$150, 10, FALSE), "0") -> 28.55 | Q5: =IFERROR(VLOOKUP(P5, Tarieven!$A$2:$J$150, 10, FALSE), "0") -> 0 | T5: =IFERROR(VLOOKUP(S5, Tarieven!$A$2:$J$150, 10, FALSE), "0") -> 0 | W5: =IFERROR(VLOOKUP(V5, Tarieven!$A$2:$J$150, 10, FALSE), "0") -> 0 | X5: =Augustus!X5 -> 0 | Y5: 0 | Z5: =SUM(L5+O5+R5+U5+X5) -> 2 | AA5: =SUM(H5+K5)*E5 -> 207 | AB5: =SUM((L5*N5)+(O5*Q5)+(R5*T5)+(U5*W5)+Y5) -> 57.1 | AC5: =SUM(AB5-AA5) -> -149.9 | AE5: Kosten lessen | AF5: =SUM(September[Kosten per maand]) -> 4064.65
A6: =Rooster!A7 -> Maandag | B6: =Rooster!B7 -> 0.66666667 | C6: =Rooster!C7 -> 60 | D6: =Rooster!D7 -> Urban-Pop-Show 10+ | E6: 5 | F6: =Rooster!E7 -> Lotte | G6: =IFERROR(VLOOKUP(F6, Docenten!$A$2:$G$30, 7, FALSE), "0") -> 22.5 | H6: =SUM(G6/60)*C6 -> 22.5 | I6: =Rooster!H7 -> Santpoort Zuid | J6: =IFERROR(VLOOKUP(I6, Locaties!$A$2:$G$15, 7, FALSE), "0") -> 18.9 | K6: =SUM(J6/60)*C6 -> 18.9 | L6: 1 | M6: 2x per week abbo | N6: =IFERROR(VLOOKUP(M6, Tarieven!$A$1:$J$150, 10, FALSE), "0") -> 28.55 | O6: 3 | P6: 1x per week abbo | Q6: =IFERROR(VLOOKUP(P6, Tarieven!$A$2:$J$150, 10, FALSE), "0") -> 31 | R6: 1 | S6: 1x per week abbo | T6: =IFERROR(VLOOKUP(S6, Tarieven!$A$2:$J$150, 10, FALSE), "0") -> 31 | W6: =IFERROR(VLOOKUP(V6, Tarieven!$A$2:$J$150, 10, FALSE), "0") -> 0 | X6: =Augustus!X6 -> 4 | Y6: 0 | Z6: =SUM(L6+O6+R6+U6+X6) -> 9 | AA6: =SUM(H6+K6)*E6 -> 207 | AB6: =SUM((L6*N6)+(O6*Q6)+(R6*T6)+(U6*W6)+Y6) -> 152.55 | AC6: =SUM(AB6-AA6) -> -54.45 | AE6: Kosten overige | AF6: =Kosten!C69 -> 10354.65 | AG6: Salaris doel
A7: =Rooster!A8 -> Maandag | B7: =Rooster!B8 -> 0.70833333 | C7: =Rooster!C8 -> 60 | D7: =Rooster!D8 -> Urban-Pop-Show 12+ | E7: 5 | F7: =Rooster!E8 -> Nova | G7: =IFERROR(VLOOKUP(F7, Docenten!$A$2:$G$30, 7, FALSE), "0") -> 22.5 | H7: =SUM(G7/60)*C7 -> 22.5 | I7: =Rooster!H8 -> Santpoort Zuid | J7: =IFERROR(VLOOKUP(I7, Locaties!$A$2:$G$15, 7, FALSE), "0") -> 18.9 | K7: =SUM(J7/60)*C7 -> 18.9 | L7: 1 | M7: 1x per week abbo | N7: =IFERROR(VLOOKUP(M7, Tarieven!$A$1:$J$150, 10, FALSE), "0") -> 31 | O7: 1 | P7: 2x per week abbo | Q7: =IFERROR(VLOOKUP(P7, Tarieven!$A$2:$J$150, 10, FALSE), "0") -> 28.55 | R7: 1 | S7: Cheer regulier +1 | T7: =IFERROR(VLOOKUP(S7, Tarieven!$A$2:$J$150, 10, FALSE), "0") -> 289.5 | W7: =IFERROR(VLOOKUP(V7, Tarieven!$A$2:$J$150, 10, FALSE), "0") -> 0 | X7: =Augustus!X7 -> 11 | Y7: 0 | Z7: =SUM(L7+O7+R7+U7+X7) -> 14 | AA7: =SUM(H7+K7)*E7 -> 207 | AB7: =SUM((L7*N7)+(O7*Q7)+(R7*T7)+(U7*W7)+Y7) -> 349.05 | AC7: =SUM(AB7-AA7) -> 142.05 | AE7: Winst deze maand | AF7: =SUM(AF3+AF4)-AF5-AF6 -> 3946.628 | AG7: ='Doel vs Werkelijkheid'!B2 -> 3000
A8: =Rooster!A9 -> Maandag | B8: =Rooster!B9 -> 0.75 | C8: =Rooster!C9 -> 60 | D8: =Rooster!D9 -> Selectie Show | E8: 5 | F8: =Rooster!E9 -> Nova | G8: =IFERROR(VLOOKUP(F8, Docenten!$A$2:$G$30, 7, FALSE), "0") -> 22.5 | H8: =SUM(G8/60)*C8 -> 22.5 | I8: =Rooster!H9 -> Santpoort Zuid | J8: =IFERROR(VLOOKUP(I8, Locaties!$A$2:$G$15, 7, FALSE), "0") -> 18.9 | K8: =SUM(J8/60)*C8 -> 18.9 | L8: 2 | M8: 3x per week abbo | N8: =IFERROR(VLOOKUP(M8, Tarieven!$A$1:$J$150, 10, FALSE), "0") -> 28.933333 | O8: 3 | P8: 2x per week abbo | Q8: =IFERROR(VLOOKUP(P8, Tarieven!$A$2:$J$150, 10, FALSE), "0") -> 28.55 | R8: 2 | S8: Onbeperkt abbo | T8: =IFERROR(VLOOKUP(S8, Tarieven!$A$2:$J$150, 10, FALSE), "0") -> 27 | W8: =IFERROR(VLOOKUP(V8, Tarieven!$A$2:$J$150, 10, FALSE), "0") -> 0 | X8: =Augustus!X8 -> 4 | Y8: 0 | Z8: =SUM(L8+O8+R8+U8+X8) -> 11 | AA8: =SUM(H8+K8)*E8 -> 207 | AB8: =SUM((L8*N8)+(O8*Q8)+(R8*T8)+(U8*W8)+Y8) -> 197.51667 | AC8: =SUM(AB8-AA8) -> -9.4833333
A9: =Rooster!A10 -> Maandag | B9: =Rooster!B10 -> 0.79166667 | C9: =Rooster!C10 -> 60 | D9: =Rooster!D10 -> Commercial 16+ | E9: 5 | F9: =Rooster!E10 -> Nova | G9: =IFERROR(VLOOKUP(F9, Docenten!$A$2:$G$30, 7, FALSE), "0") -> 22.5 | H9: =SUM(G9/60)*C9 -> 22.5 | I9: =Rooster!H10 -> Santpoort Zuid | J9: =IFERROR(VLOOKUP(I9, Locaties!$A$2:$G$15, 7, FALSE), "0") -> 18.9 | K9: =SUM(J9/60)*C9 -> 18.9 | L9: 3 | M9: 3x per week abbo | N9: =IFERROR(VLOOKUP(M9, Tarieven!$A$1:$J$150, 10, FALSE), "0") -> 28.933333 | O9: 1 | P9: 1x per week abbo | Q9: =IFERROR(VLOOKUP(P9, Tarieven!$A$2:$J$150, 10, FALSE), "0") -> 31 | R9: 3 | S9: 2x per week abbo | T9: =IFERROR(VLOOKUP(S9, Tarieven!$A$2:$J$150, 10, FALSE), "0") -> 28.55 | W9: =IFERROR(VLOOKUP(V9, Tarieven!$A$2:$J$150, 10, FALSE), "0") -> 0 | X9: =Augustus!X9 -> 5 | Y9: 0 | Z9: =SUM(L9+O9+R9+U9+X9) -> 12 | AA9: =SUM(H9+K9)*E9 -> 207 | AB9: =SUM((L9*N9)+(O9*Q9)+(R9*T9)+(U9*W9)+Y9) -> 203.45 | AC9: =SUM(AB9-AA9) -> -3.55 | AE9: Actieve leden | AF9: =Z101 -> 387
A10: =Rooster!A11 -> Maandag | B10: =Rooster!B11 -> 0.83333333 | C10: =Rooster!C11 -> 60 | D10: =Rooster!D11 -> Commercial 20+ | E10: 5 | F10: =Rooster!E11 -> Nova | G10: =IFERROR(VLOOKUP(F10, Docenten!$A$2:$G$30, 7, FALSE), "0") -> 22.5 | H10: =SUM(G10/60)*C10 -> 22.5 | I10: =Rooster!H11 -> Santpoort Zuid | J10: =IFERROR(VLOOKUP(I10, Locaties!$A$2:$G$15, 7, FALSE), "0") -> 18.9 | K10: =SUM(J10/60)*C10 -> 18.9 | L10: 4 | M10: Volwassenen 2x abbo | N10: =IFERROR(VLOOKUP(M10, Tarieven!$A$1:$J$150, 10, FALSE), "0") -> 27.255 | O10: 3 | P10: Volwassenen 1x abbo | Q10: =IFERROR(VLOOKUP(P10, Tarieven!$A$2:$J$150, 10, FALSE), "0") -> 25.596 | R10: 1 | S10: Strippenkaart 18+ | T10: 50 | W10: =IFERROR(VLOOKUP(V10, Tarieven!$A$2:$J$150, 10, FALSE), "0") -> 0 | X10: =Augustus!X10 -> 8 | Y10: 0 | Z10: =SUM(L10+O10+R10+U10+X10) -> 16 | AA10: =SUM(H10+K10)*E10 -> 207 | AB10: =SUM((L10*N10)+(O10*Q10)+(R10*T10)+(U10*W10)+Y10) -> 235.808 | AC10: =SUM(AB10-AA10) -> 28.808
A11: =Rooster!A12 -> Maandag | B11: =Rooster!B12 -> 0.875 | C11: =Rooster!C12 -> 60 | D11: =Rooster!D12 -> Jazz 20+ | E11: 5 | F11: =Rooster!E12 -> Nova | G11: =IFERROR(VLOOKUP(F11, Docenten!$A$2:$G$30, 7, FALSE), "0") -> 22.5 | H11: =SUM(G11/60)*C11 -> 22.5 | I11: =Rooster!H12 -> Santpoort Zuid | J11: =IFERROR(VLOOKUP(I11, Locaties!$A$2:$G$15, 7, FALSE), "0") -> 18.9 | K11: =SUM(J11/60)*C11 -> 18.9 | L11: 4 | M11: Volwassenen 2x abbo | N11: =IFERROR(VLOOKUP(M11, Tarieven!$A$1:$J$150, 10, FALSE), "0") -> 27.255 | Q11: =IFERROR(VLOOKUP(P11, Tarieven!$A$2:$J$150, 10, FALSE), "0") -> 0 | T11: =IFERROR(VLOOKUP(S11, Tarieven!$A$2:$J$150, 10, FALSE), "0") -> 0 | W11: =IFERROR(VLOOKUP(V11, Tarieven!$A$2:$J$150, 10, FALSE), "0") -> 0 | X11: =Augustus!X11 -> 4 | Y11: 0 | Z11: =SUM(L11+O11+R11+U11+X11) -> 8 | AA11: =SUM(H11+K11)*E11 -> 207 | AB11: =SUM((L11*N11)+(O11*Q11)+(R11*T11)+(U11*W11)+Y11) -> 109.02 | AC11: =SUM(AB11-AA11) -> -97.98
A12: =Rooster!A13 -> Maandag | B12: =Rooster!B13 -> 0.66666667 | C12: =Rooster!C13 -> 60 | D12: =Rooster!D13 -> Streetdance 6+ | E12: 5 | F12: =Rooster!E13 -> Julia | G12: =IFERROR(VLOOKUP(F12, Docenten!$A$2:$G$30, 7, FALSE), "0") -> 15 | H12: =SUM(G12/60)*C12 -> 15 | I12: =Rooster!H13 -> Santpoort Noord | J12: =IFERROR(VLOOKUP(I12, Locaties!$A$2:$G$15, 7, FALSE), "0") -> 14.2 | K12: =SUM(J12/60)*C12 -> 14.2 | L12: 3 | M12: 1x per week abbo | N12: =IFERROR(VLOOKUP(M12, Tarieven!$A$1:$J$150, 10, FALSE), "0") -> 31 | Q12: =IFERROR(VLOOKUP(P12, Tarieven!$A$2:$J$150, 10, FALSE), "0") -> 0 | T12: =IFERROR(VLOOKUP(S12, Tarieven!$A$2:$J$150, 10, FALSE), "0") -> 0 | W12: =IFERROR(VLOOKUP(V12, Tarieven!$A$2:$J$150, 10, FALSE), "0") -> 0 | X12: =Augustus!X12 -> 2 | Y12: 0 | Z12: =SUM(L12+O12+R12+U12+X12) -> 5 | AA12: =SUM(H12+K12)*E12 -> 146 | AB12: =SUM((L12*N12)+(O12*Q12)+(R12*T12)+(U12*W12)+Y12) -> 93 | AC12: =SUM(AB12-AA12) -> -53
A13: =Rooster!A14 -> Maandag | B13: =Rooster!B14 -> 0.70833333 | C13: =Rooster!C14 -> 60 | D13: =Rooster!D14 -> Streetdance 8+ | E13: 5 | F13: =Rooster!E14 -> Julia | G13: =IFERROR(VLOOKUP(F13, Docenten!$A$2:$G$30, 7, FALSE), "0") -> 15 | H13: =SUM(G13/60)*C13 -> 15 | I13: =Rooster!H14 -> Santpoort Noord | J13: =IFERROR(VLOOKUP(I13, Locaties!$A$2:$G$15, 7, FALSE), "0") -> 14.2 | K13: =SUM(J13/60)*C13 -> 14.2 | L13: 5 | M13: 2x per week abbo | N13: =IFERROR(VLOOKUP(M13, Tarieven!$A$1:$J$150, 10, FALSE), "0") -> 28.55 | O13: 1 | P13: 1x per week abbo | Q13: =IFERROR(VLOOKUP(P13, Tarieven!$A$2:$J$150, 10, FALSE), "0") -> 31 | T13: =IFERROR(VLOOKUP(S13, Tarieven!$A$2:$J$150, 10, FALSE), "0") -> 0 | W13: =IFERROR(VLOOKUP(V13, Tarieven!$A$2:$J$150, 10, FALSE), "0") -> 0 | X13: =Augustus!X13 -> 13 | Y13: 0 | Z13: =SUM(L13+O13+R13+U13+X13) -> 19 | AA13: =SUM(H13+K13)*E13 -> 146 | AB13: =SUM((L13*N13)+(O13*Q13)+(R13*T13)+(U13*W13)+Y13) -> 173.75 | AC13: =SUM(AB13-AA13) -> 27.75
A14: =Rooster!A15 -> Dinsdag | B14: =Rooster!B15 -> 0.66666667 | C14: =Rooster!C15 -> 60 | D14: =Rooster!D15 -> Modern 8+ | E14: 5 | F14: =Rooster!E15 -> Eigenaar | G14: =IFERROR(VLOOKUP(F14, Docenten!$A$2:$G$30, 7, FALSE), "0") -> 0 | H14: =SUM(G14/60)*C14 -> 0 | I14: =Rooster!H15 -> Santpoort Zuid | J14: =IFERROR(VLOOKUP(I14, Locaties!$A$2:$G$15, 7, FALSE), "0") -> 18.9 | K14: =SUM(J14/60)*C14 -> 18.9 | L14: 3 | M14: Cheer regulier + onbeperkt abbo | N14: =IFERROR(VLOOKUP(M14, Tarieven!$A$1:$J$150, 10, FALSE), "0") -> 44.45 | O14: 4 | P14: 2x per week abbo | Q14: =IFERROR(VLOOKUP(P14, Tarieven!$A$2:$J$150, 10, FALSE), "0") -> 28.55 | R14: 1 | S14: Cheer regulier +1 abbo | T14: =IFERROR(VLOOKUP(S14, Tarieven!$A$2:$J$150, 10, FALSE), "0") -> 32.25 | W14: =IFERROR(VLOOKUP(V14, Tarieven!$A$2:$J$150, 10, FALSE), "0") -> 0 | X14: =Augustus!X14 -> 8 | Y14: 0 | Z14: =SUM(L14+O14+R14+U14+X14) -> 16 | AA14: =SUM(H14+K14)*E14 -> 94.5 | AB14: =SUM((L14*N14)+(O14*Q14)+(R14*T14)+(U14*W14)+Y14) -> 279.8 | AC14: =SUM(AB14-AA14) -> 185.3
A15: =Rooster!A16 -> Dinsdag | B15: =Rooster!B16 -> 0.70833333 | C15: =Rooster!C16 -> 60 | D15: =Rooster!D16 -> Selectie show 8+ | E15: 5 | F15: =Rooster!E16 -> Eigenaar | G15: =IFERROR(VLOOKUP(F15, Docenten!$A$2:$G$30, 7, FALSE), "0") -> 0 | H15: =SUM(G15/60)*C15 -> 0 | I15: =Rooster!H16 -> Santpoort Zuid | J15: =IFERROR(VLOOKUP(I15, Locaties!$A$2:$G$15, 7, FALSE), "0") -> 18.9 | K15: =SUM(J15/60)*C15 -> 18.9 | L15: 2 | M15: Cheer regulier + onbeperkt abbo | N15: =IFERROR(VLOOKUP(M15, Tarieven!$A$1:$J$150, 10, FALSE), "0") -> 44.45 | O15: 2 | P15: 2x per week abbo | Q15: =IFERROR(VLOOKUP(P15, Tarieven!$A$2:$J$150, 10, FALSE), "0") -> 28.55 | R15: 1 | S15: Cheer regulier +2 abbo | T15: =IFERROR(VLOOKUP(S15, Tarieven!$A$2:$J$150, 10, FALSE), "0") -> 29.033333 | W15: =IFERROR(VLOOKUP(V15, Tarieven!$A$2:$J$150, 10, FALSE), "0") -> 0 | X15: =Augustus!X15 -> 7 | Y15: 0 | Z15: =SUM(L15+O15+R15+U15+X15) -> 12 | AA15: =SUM(H15+K15)*E15 -> 94.5 | AB15: =SUM((L15*N15)+(O15*Q15)+(R15*T15)+(U15*W15)+Y15) -> 175.03333 | AC15: =SUM(AB15-AA15) -> 80.533333
A16: =Rooster!A17 -> Dinsdag | B16: =Rooster!B17 -> 0.75 | C16: =Rooster!C17 -> 90 | D16: =Rooster!D17 -> Selectie Cheer | E16: 5 | F16: =Rooster!E17 -> Eigenaar | G16: =IFERROR(VLOOKUP(F16, Docenten!$A$2:$G$30, 7, FALSE), "0") -> 0 | H16: =SUM(G16/60)*C16 -> 0 | I16: =Rooster!H17 -> Santpoort Zuid | J16: =IFERROR(VLOOKUP(I16, Locaties!$A$2:$G$15, 7, FALSE), "0") -> 18.9 | K16: =SUM(J16/60)*C16 -> 28.35 | L16: 2 | M16: Cheer selectie +2 abbo | N16: =IFERROR(VLOOKUP(M16, Tarieven!$A$1:$J$150, 10, FALSE), "0") -> 31.533333 | O16: 1 | P16: Cheer selectie +1 abbo | Q16: =IFERROR(VLOOKUP(P16, Tarieven!$A$2:$J$150, 10, FALSE), "0") -> 34.25 | T16: =IFERROR(VLOOKUP(S16, Tarieven!$A$2:$J$150, 10, FALSE), "0") -> 0 | W16: =IFERROR(VLOOKUP(V16, Tarieven!$A$2:$J$150, 10, FALSE), "0") -> 0 | X16: =Augustus!X16 -> 8 | Y16: 0 | Z16: =SUM(L16+O16+R16+U16+X16) -> 11 | AA16: =SUM(H16+K16)*E16 -> 141.75 | AB16: =SUM((L16*N16)+(O16*Q16)+(R16*T16)+(U16*W16)+Y16) -> 97.316667 | AC16: =SUM(AB16-AA16) -> -44.433333
A17: =Rooster!A18 -> Dinsdag | B17: =Rooster!B18 -> 0.8125 | C17: =Rooster!C18 -> 60 | D17: =Rooster!D18 -> Hiphop 15+ | E17: 5 | F17: =Rooster!E18 -> Eigenaar | G17: =IFERROR(VLOOKUP(F17, Docenten!$A$2:$G$30, 7, FALSE), "0") -> 0 | H17: =SUM(G17/60)*C17 -> 0 | I17: =Rooster!H18 -> Santpoort Zuid | J17: =IFERROR(VLOOKUP(I17, Locaties!$A$2:$G$15, 7, FALSE), "0") -> 18.9 | K17: =SUM(J17/60)*C17 -> 18.9 | L17: 1 | M17: 2x per week abbo | N17: =IFERROR(VLOOKUP(M17, Tarieven!$A$1:$J$150, 10, FALSE), "0") -> 28.55 | O17: 3 | P17: 3x per week abbo | Q17: =IFERROR(VLOOKUP(P17, Tarieven!$A$2:$J$150, 10, FALSE), "0") -> 28.933333 | R17: 1 | S17: 1x per week abbo | T17: =IFERROR(VLOOKUP(S17, Tarieven!$A$2:$J$150, 10, FALSE), "0") -> 31 | W17: =IFERROR(VLOOKUP(V17, Tarieven!$A$2:$J$150, 10, FALSE), "0") -> 0 | X17: =Augustus!X17 -> 9 | Y17: 0 | Z17: =SUM(L17+O17+R17+U17+X17) -> 14 | AA17: =SUM(H17+K17)*E17 -> 94.5 | AB17: =SUM((L17*N17)+(O17*Q17)+(R17*T17)+(U17*W17)+Y17) -> 146.35 | AC17: =SUM(AB17-AA17) -> 51.85
A18: =Rooster!A19 -> Woensdag | B18: =Rooster!B19 -> 0.60416667 | C18: =Rooster!C19 -> 60 | D18: =Rooster!D19 -> Streetdance 6+ | E18: 4 | F18: =Rooster!E19 -> Julia | G18: =IFERROR(VLOOKUP(F18, Docenten!$A$2:$G$30, 7, FALSE), "0") -> 15 | H18: =SUM(G18/60)*C18 -> 15 | I18: =Rooster!H19 -> Santpoort Noord | J18: =IFERROR(VLOOKUP(I18, Locaties!$A$2:$G$15, 7, FALSE), "0") -> 14.2 | K18: =SUM(J18/60)*C18 -> 14.2 | L18: 4 | M18: 1x per week abbo | N18: =IFERROR(VLOOKUP(M18, Tarieven!$A$1:$J$150, 10, FALSE), "0") -> 31 | O18: 1 | P18: Cheer regulier +1 abbo | Q18: =IFERROR(VLOOKUP(P18, Tarieven!$A$2:$J$150, 10, FALSE), "0") -> 32.25 | R18: 1 | S18: Cheer regulier + onbeperkt abbo | T18: =IFERROR(VLOOKUP(S18, Tarieven!$A$2:$J$150, 10, FALSE), "0") -> 44.45 | W18: =IFERROR(VLOOKUP(V18, Tarieven!$A$2:$J$150, 10, FALSE), "0") -> 0 | X18: =Augustus!X18 -> 9 | Y18: 0 | Z18: =SUM(L18+O18+R18+U18+X18) -> 15 | AA18: =SUM(H18+K18)*E18 -> 116.8 | AB18: =SUM((L18*N18)+(O18*Q18)+(R18*T18)+(U18*W18)+Y18) -> 200.7 | AC18: =SUM(AB18-AA18) -> 83.9
A19: =Rooster!A20 -> Woensdag | B19: =Rooster!B20 -> 0.64583333 | C19: =Rooster!C20 -> 60 | D19: =Rooster!D20 -> Streetdance 8+ | E19: 4 | F19: =Rooster!E20 -> Julia | G19: =IFERROR(VLOOKUP(F19, Docenten!$A$2:$G$30, 7, FALSE), "0") -> 15 | H19: =SUM(G19/60)*C19 -> 15 | I19: =Rooster!H20 -> Santpoort Noord | J19: =IFERROR(VLOOKUP(I19, Locaties!$A$2:$G$15, 7, FALSE), "0") -> 14.2 | K19: =SUM(J19/60)*C19 -> 14.2 | L19: 3 | M19: 1x per week abbo | N19: =IFERROR(VLOOKUP(M19, Tarieven!$A$1:$J$150, 10, FALSE), "0") -> 31 | O19: 1 | P19: Cheer regulier +1 abbo | Q19: =IFERROR(VLOOKUP(P19, Tarieven!$A$2:$J$150, 10, FALSE), "0") -> 32.25 | R19: 1 | S19: Cheer regulier + onbeperkt abbo | T19: =IFERROR(VLOOKUP(S19, Tarieven!$A$2:$J$150, 10, FALSE), "0") -> 44.45 | W19: =IFERROR(VLOOKUP(V19, Tarieven!$A$2:$J$150, 10, FALSE), "0") -> 0 | X19: =Augustus!X19 -> 11 | Y19: 0 | Z19: =SUM(L19+O19+R19+U19+X19) -> 16 | AA19: =SUM(H19+K19)*E19 -> 116.8 | AB19: =SUM((L19*N19)+(O19*Q19)+(R19*T19)+(U19*W19)+Y19) -> 169.7 | AC19: =SUM(AB19-AA19) -> 52.9
A20: =Rooster!A21 -> Woensdag | B20: =Rooster!B21 -> 0.6875 | C20: =Rooster!C21 -> 60 | D20: =Rooster!D21 -> Modern 11+ | E20: 4 | F20: =Rooster!E21 -> Julia | G20: =IFERROR(VLOOKUP(F20, Docenten!$A$2:$G$30, 7, FALSE), "0") -> 15 | H20: =SUM(G20/60)*C20 -> 15 | I20: =Rooster!H21 -> Santpoort Noord | J20: =IFERROR(VLOOKUP(I20, Locaties!$A$2:$G$15, 7, FALSE), "0") -> 14.2 | K20: =SUM(J20/60)*C20 -> 14.2 | L20: 1 | M20: 1x per week abbo | N20: =IFERROR(VLOOKUP(M20, Tarieven!$A$1:$J$150, 10, FALSE), "0") -> 31 | O20: 3 | P20: 2x per week abbo | Q20: =IFERROR(VLOOKUP(P20, Tarieven!$A$2:$J$150, 10, FALSE), "0") -> 28.55 | R20: 1 | S20: Cheer regulier +1 abbo | T20: =IFERROR(VLOOKUP(S20, Tarieven!$A$2:$J$150, 10, FALSE), "0") -> 32.25 | W20: =IFERROR(VLOOKUP(V20, Tarieven!$A$2:$J$150, 10, FALSE), "0") -> 0 | X20: =Augustus!X20 -> 9 | Y20: 0 | Z20: =SUM(L20+O20+R20+U20+X20) -> 14 | AA20: =SUM(H20+K20)*E20 -> 116.8 | AB20: =SUM((L20*N20)+(O20*Q20)+(R20*T20)+(U20*W20)+Y20) -> 148.9 | AC20: =SUM(AB20-AA20) -> 32.1
A21: =Rooster!A22 -> Woensdag | B21: =Rooster!B22 -> 0.72916667 | C21: =Rooster!C22 -> 60 | D21: =Rooster!D22 -> Selectie Hiphop 11+ | E21: 4 | F21: =Rooster!E22 -> Eigenaar | G21: =IFERROR(VLOOKUP(F21, Docenten!$A$2:$G$30, 7, FALSE), "0") -> 0 | H21: =SUM(G21/60)*C21 -> 0 | I21: =Rooster!H22 -> Santpoort Noord | J21: =IFERROR(VLOOKUP(I21, Locaties!$A$2:$G$15, 7, FALSE), "0") -> 14.2 | K21: =SUM(J21/60)*C21 -> 14.2 | L21: 1 | M21: Cheer selectie +1 abbo | N21: =IFERROR(VLOOKUP(M21, Tarieven!$A$1:$J$150, 10, FALSE), "0") -> 34.25 | Q21: =IFERROR(VLOOKUP(P21, Tarieven!$A$2:$J$150, 10, FALSE), "0") -> 0 | T21: =IFERROR(VLOOKUP(S21, Tarieven!$A$2:$J$150, 10, FALSE), "0") -> 0 | W21: =IFERROR(VLOOKUP(V21, Tarieven!$A$2:$J$150, 10, FALSE), "0") -> 0 | X21: =Augustus!X21 -> 11 | Y21: 0 | Z21: =SUM(L21+O21+R21+U21+X21) -> 12 | AA21: =SUM(H21+K21)*E21 -> 56.8 | AB21: =SUM((L21*N21)+(O21*Q21)+(R21*T21)+(U21*W21)+Y21) -> 34.25 | AC21: =SUM(AB21-AA21) -> -22.55
A22: =Rooster!A23 -> Woensdag | B22: =Rooster!B23 -> 0.77083333 | C22: =Rooster!C23 -> 60 | D22: =Rooster!D23 -> Show 12+ | E22: 4 | F22: =Rooster!E23 -> Eigenaar | G22: =IFERROR(VLOOKUP(F22, Docenten!$A$2:$G$30, 7, FALSE), "0") -> 0 | H22: =SUM(G22/60)*C22 -> 0 | I22: =Rooster!H23 -> Santpoort Noord | J22: =IFERROR(VLOOKUP(I22, Locaties!$A$2:$G$15, 7, FALSE), "0") -> 14.2 | K22: =SUM(J22/60)*C22 -> 14.2 | L22: 1 | M22: 1x per week abbo | N22: =IFERROR(VLOOKUP(M22, Tarieven!$A$1:$J$150, 10, FALSE), "0") -> 31 | O22: 4 | P22: 1x per week | Q22: =IFERROR(VLOOKUP(P22, Tarieven!$A$2:$J$150, 10, FALSE), "0") -> 279 | R22: 1 | S22: Aangepast tarief | T22: 260 | W22: =IFERROR(VLOOKUP(V22, Tarieven!$A$2:$J$150, 10, FALSE), "0") -> 0 | X22: =Augustus!X22 -> 9 | Y22: 0 | Z22: =SUM(L22+O22+R22+U22+X22) -> 15 | AA22: =SUM(H22+K22)*E22 -> 56.8 | AB22: =SUM((L22*N22)+(O22*Q22)+(R22*T22)+(U22*W22)+Y22) -> 1407 | AC22: =SUM(AB22-AA22) -> 1350.2
A23: =Rooster!A24 | B23: =Rooster!B24 | C23: =Rooster!C24 | D23: =Rooster!D24 | E23: 4 | F23: =Rooster!E24 | G23: =IFERROR(VLOOKUP(F23, Docenten!$A$2:$G$30, 7, FALSE), "0") -> 0 | H23: =SUM(G23/60)*C23 -> 0 | I23: =Rooster!H24 | J23: =IFERROR(VLOOKUP(I23, Locaties!$A$2:$G$15, 7, FALSE), "0") -> 0 | K23: =SUM(J23/60)*C23 -> 0 | N23: =IFERROR(VLOOKUP(M23, Tarieven!$A$1:$J$150, 10, FALSE), "0") -> 0 | Q23: =IFERROR(VLOOKUP(P23, Tarieven!$A$2:$J$150, 10, FALSE), "0") -> 0 | T23: =IFERROR(VLOOKUP(S23, Tarieven!$A$2:$J$150, 10, FALSE), "0") -> 0 | W23: =IFERROR(VLOOKUP(V23, Tarieven!$A$2:$J$150, 10, FALSE), "0") -> 0 | X23: =Augustus!X23 -> 0 | Y23: 0 | Z23: =SUM(L23+O23+R23+U23+X23) -> 0 | AA23: =SUM(H23+K23)*E23 -> 0 | AB23: =SUM((L23*N23)+(O23*Q23)+(R23*T23)+(U23*W23)+Y23) -> 0 | AC23: =SUM(AB23-AA23) -> 0
A24: =Rooster!A25 -> Donderdag | B24: =Rooster!B25 -> 0.64583333 | C24: =Rooster!C25 -> 60 | D24: =Rooster!D25 -> Showdance 6+ | E24: 4 | F24: =Rooster!E25 -> Eigenaar | G24: =IFERROR(VLOOKUP(F24, Docenten!$A$2:$G$30, 7, FALSE), "0") -> 0 | H24: =SUM(G24/60)*C24 -> 0 | I24: =Rooster!H25 -> Santpoort Zuid | J24: =IFERROR(VLOOKUP(I24, Locaties!$A$2:$G$15, 7, FALSE), "0") -> 18.9 | K24: =SUM(J24/60)*C24 -> 18.9 | L24: 3 | M24: 1x per week abbo | N24: =IFERROR(VLOOKUP(M24, Tarieven!$A$1:$J$150, 10, FALSE), "0") -> 31 | O24: 3 | P24: 2x per week abbo | Q24: =IFERROR(VLOOKUP(P24, Tarieven!$A$2:$J$150, 10, FALSE), "0") -> 28.55 | T24: =IFERROR(VLOOKUP(S24, Tarieven!$A$2:$J$150, 10, FALSE), "0") -> 0 | W24: =IFERROR(VLOOKUP(V24, Tarieven!$A$2:$J$150, 10, FALSE), "0") -> 0 | X24: =Augustus!X24 -> 4 | Y24: 0 | Z24: =SUM(L24+O24+R24+U24+X24) -> 10 | AA24: =SUM(H24+K24)*E24 -> 75.6 | AB24: =SUM((L24*N24)+(O24*Q24)+(R24*T24)+(U24*W24)+Y24) -> 178.65 | AC24: =SUM(AB24-AA24) -> 103.05
A25: =Rooster!A26 -> Donderdag | B25: =Rooster!B26 -> 0.6875 | C25: =Rooster!C26 -> 60 | D25: =Rooster!D26 -> Showdance 8+ | E25: 4 | F25: =Rooster!E26 -> Eigenaar | G25: =IFERROR(VLOOKUP(F25, Docenten!$A$2:$G$30, 7, FALSE), "0") -> 0 | H25: =SUM(G25/60)*C25 -> 0 | I25: =Rooster!H26 -> Santpoort Zuid | J25: =IFERROR(VLOOKUP(I25, Locaties!$A$2:$G$15, 7, FALSE), "0") -> 18.9 | K25: =SUM(J25/60)*C25 -> 18.9 | L25: 3 | M25: 1x per week abbo | N25: =IFERROR(VLOOKUP(M25, Tarieven!$A$1:$J$150, 10, FALSE), "0") -> 31 | O25: 2 | P25: Cheer regulier + onbeperkt abbo | Q25: =IFERROR(VLOOKUP(P25, Tarieven!$A$2:$J$150, 10, FALSE), "0") -> 44.45 | R25: 1 | S25: Cheer regulier +1 abbo | T25: =IFERROR(VLOOKUP(S25, Tarieven!$A$2:$J$150, 10, FALSE), "0") -> 32.25 | W25: =IFERROR(VLOOKUP(V25, Tarieven!$A$2:$J$150, 10, FALSE), "0") -> 0 | X25: =Augustus!X25 -> 4 | Y25: 0 | Z25: =SUM(L25+O25+R25+U25+X25) -> 10 | AA25: =SUM(H25+K25)*E25 -> 75.6 | AB25: =SUM((L25*N25)+(O25*Q25)+(R25*T25)+(U25*W25)+Y25) -> 214.15 | AC25: =SUM(AB25-AA25) -> 138.55
A26: =Rooster!A27 -> Donderdag | B26: =Rooster!B27 -> 0.72916667 | C26: =Rooster!C27 -> 60 | D26: =Rooster!D27 -> Modern 14+ | E26: 4 | F26: =Rooster!E27 -> Eigenaar | G26: =IFERROR(VLOOKUP(F26, Docenten!$A$2:$G$30, 7, FALSE), "0") -> 0 | H26: =SUM(G26/60)*C26 -> 0 | I26: =Rooster!H27 -> Santpoort Zuid | J26: =IFERROR(VLOOKUP(I26, Locaties!$A$2:$G$15, 7, FALSE), "0") -> 18.9 | K26: =SUM(J26/60)*C26 -> 18.9 | L26: 2 | M26: 3x per week abbo | N26: =IFERROR(VLOOKUP(M26, Tarieven!$A$1:$J$150, 10, FALSE), "0") -> 28.933333 | Q26: =IFERROR(VLOOKUP(P26, Tarieven!$A$2:$J$150, 10, FALSE), "0") -> 0 | R26: 2 | S26: Cheer selectie +2 abbo | T26: =IFERROR(VLOOKUP(S26, Tarieven!$A$2:$J$150, 10, FALSE), "0") -> 31.533333 | W26: =IFERROR(VLOOKUP(V26, Tarieven!$A$2:$J$150, 10, FALSE), "0") -> 0 | X26: =Augustus!X26 -> 7 | Y26: 0 | Z26: =SUM(L26+O26+R26+U26+X26) -> 11 | AA26: =SUM(H26+K26)*E26 -> 75.6 | AB26: =SUM((L26*N26)+(O26*Q26)+(R26*T26)+(U26*W26)+Y26) -> 120.93333 | AC26: =SUM(AB26-AA26) -> 45.333333
A27: =Rooster!A28 -> Donderdag | B27: =Rooster!B28 -> 0.77083333 | C27: =Rooster!C28 -> 60 | D27: =Rooster!D28 -> Commercial 14+ | E27: 4 | F27: =Rooster!E28 -> Nova | G27: =IFERROR(VLOOKUP(F27, Docenten!$A$2:$G$30, 7, FALSE), "0") -> 22.5 | H27: =SUM(G27/60)*C27 -> 22.5 | I27: =Rooster!H28 -> Santpoort Zuid | J27: =IFERROR(VLOOKUP(I27, Locaties!$A$2:$G$15, 7, FALSE), "0") -> 18.9 | K27: =SUM(J27/60)*C27 -> 18.9 | L27: 2 | M27: Cheer selectie +2 abbo | N27: =IFERROR(VLOOKUP(M27, Tarieven!$A$1:$J$150, 10, FALSE), "0") -> 31.533333 | O27: 3 | P27: 3x per week abbo | Q27: =IFERROR(VLOOKUP(P27, Tarieven!$A$2:$J$150, 10, FALSE), "0") -> 28.933333 | R27: 2 | S27: 2x per week abbo | T27: =IFERROR(VLOOKUP(S27, Tarieven!$A$2:$J$150, 10, FALSE), "0") -> 28.55 | W27: =IFERROR(VLOOKUP(V27, Tarieven!$A$2:$J$150, 10, FALSE), "0") -> 0 | X27: =Augustus!X27 -> 10 | Y27: 0 | Z27: =SUM(L27+O27+R27+U27+X27) -> 17 | AA27: =SUM(H27+K27)*E27 -> 165.6 | AB27: =SUM((L27*N27)+(O27*Q27)+(R27*T27)+(U27*W27)+Y27) -> 206.96667 | AC27: =SUM(AB27-AA27) -> 41.366667
A28: =Rooster!A29 -> Donderdag | B28: =Rooster!B29 -> 0.8125 | C28: =Rooster!C29 -> 60 | D28: =Rooster!D29 -> Selectie Hiphop 16+ | E28: 4 | F28: =Rooster!E29 -> Nova | G28: =IFERROR(VLOOKUP(F28, Docenten!$A$2:$G$30, 7, FALSE), "0") -> 22.5 | H28: =SUM(G28/60)*C28 -> 22.5 | I28: =Rooster!H29 -> Santpoort Zuid | J28: =IFERROR(VLOOKUP(I28, Locaties!$A$2:$G$15, 7, FALSE), "0") -> 18.9 | K28: =SUM(J28/60)*C28 -> 18.9 | L28: 2 | M28: 2x per week abbo | N28: =IFERROR(VLOOKUP(M28, Tarieven!$A$1:$J$150, 10, FALSE), "0") -> 28.55 | O28: 2 | P28: 3x per week abbo | Q28: =IFERROR(VLOOKUP(P28, Tarieven!$A$2:$J$150, 10, FALSE), "0") -> 28.933333 | R28: 2 | S28: Onbeperkt abbo | T28: =IFERROR(VLOOKUP(S28, Tarieven!$A$2:$J$150, 10, FALSE), "0") -> 27 | W28: =IFERROR(VLOOKUP(V28, Tarieven!$A$2:$J$150, 10, FALSE), "0") -> 0 | X28: =Augustus!X28 -> 8 | Y28: 0 | Z28: =SUM(L28+O28+R28+U28+X28) -> 14 | AA28: =SUM(H28+K28)*E28 -> 165.6 | AB28: =SUM((L28*N28)+(O28*Q28)+(R28*T28)+(U28*W28)+Y28) -> 168.96667 | AC28: =SUM(AB28-AA28) -> 3.3666667
A29: =Rooster!A30 -> Donderdag | B29: =Rooster!B30 -> 0.85416667 | C29: =Rooster!C30 -> 60 | D29: =Rooster!D30 -> Modern 16+ | E29: 4 | F29: =Rooster!E30 -> Nova | G29: =IFERROR(VLOOKUP(F29, Docenten!$A$2:$G$30, 7, FALSE), "0") -> 22.5 | H29: =SUM(G29/60)*C29 -> 22.5 | I29: =Rooster!H30 -> Santpoort Zuid | J29: =IFERROR(VLOOKUP(I29, Locaties!$A$2:$G$15, 7, FALSE), "0") -> 18.9 | K29: =SUM(J29/60)*C29 -> 18.9 | N29: =IFERROR(VLOOKUP(M29, Tarieven!$A$1:$J$150, 10, FALSE), "0") -> 0 | O29: 1 | P29: 3x per week abbo | Q29: =IFERROR(VLOOKUP(P29, Tarieven!$A$2:$J$150, 10, FALSE), "0") -> 28.933333 | R29: 1 | S29: 1x per week abbo | T29: =IFERROR(VLOOKUP(S29, Tarieven!$A$2:$J$150, 10, FALSE), "0") -> 31 | W29: =IFERROR(VLOOKUP(V29, Tarieven!$A$2:$J$150, 10, FALSE), "0") -> 0 | X29: =Augustus!X29 -> 5 | Y29: 0 | Z29: =SUM(L29+O29+R29+U29+X29) -> 7 | AA29: =SUM(H29+K29)*E29 -> 165.6 | AB29: =SUM((L29*N29)+(O29*Q29)+(R29*T29)+(U29*W29)+Y29) -> 59.933333 | AC29: =SUM(AB29-AA29) -> -105.66667
A30: =Rooster!A31 -> Vrijdag | B30: =Rooster!B31 -> 0.625 | C30: =Rooster!C31 -> 60 | D30: =Rooster!D31 -> Selectie Hiphop 8+ | E30: 4 | F30: =Rooster!E31 -> Eigenaar | G30: =IFERROR(VLOOKUP(F30, Docenten!$A$2:$G$30, 7, FALSE), "0") -> 0 | H30: =SUM(G30/60)*C30 -> 0 | I30: =Rooster!H31 -> Santpoort Zuid | J30: =IFERROR(VLOOKUP(I30, Locaties!$A$2:$G$15, 7, FALSE), "0") -> 18.9 | K30: =SUM(J30/60)*C30 -> 18.9 | L30: 3 | M30: Cheer regulier + onbeperkt abbo | N30: =IFERROR(VLOOKUP(M30, Tarieven!$A$1:$J$150, 10, FALSE), "0") -> 44.45 | O30: 5 | P30: 2x per week abbo | Q30: =IFERROR(VLOOKUP(P30, Tarieven!$A$2:$J$150, 10, FALSE), "0") -> 28.55 | R30: 1 | S30: Cheer regulier +2 abbo | T30: =IFERROR(VLOOKUP(S30, Tarieven!$A$2:$J$150, 10, FALSE), "0") -> 29.033333 | W30: =IFERROR(VLOOKUP(V30, Tarieven!$A$2:$J$150, 10, FALSE), "0") -> 0 | X30: =Augustus!X30 -> 4 | Y30: 0 | Z30: =SUM(L30+O30+R30+U30+X30) -> 13 | AA30: =SUM(H30+K30)*E30 -> 75.6 | AB30: =SUM((L30*N30)+(O30*Q30)+(R30*T30)+(U30*W30)+Y30) -> 305.13333 | AC30: =SUM(AB30-AA30) -> 229.53333
A31: =Rooster!A32 -> Vrijdag | B31: =Rooster!B32 -> 0.66666667 | C31: =Rooster!C32 -> 60 | D31: =Rooster!D32 -> Cheer 8+ | E31: 4 | F31: =Rooster!E32 -> Eigenaar | G31: =IFERROR(VLOOKUP(F31, Docenten!$A$2:$G$30, 7, FALSE), "0") -> 0 | H31: =SUM(G31/60)*C31 -> 0 | I31: =Rooster!H32 -> Santpoort Zuid | J31: =IFERROR(VLOOKUP(I31, Locaties!$A$2:$G$15, 7, FALSE), "0") -> 18.9 | K31: =SUM(J31/60)*C31 -> 18.9 | L31: 4 | M31: Cheer regulier +1 abbo | N31: =IFERROR(VLOOKUP(M31, Tarieven!$A$1:$J$150, 10, FALSE), "0") -> 32.25 | O31: 3 | P31: Cheer regulier + onbeperkt abbo | Q31: =IFERROR(VLOOKUP(P31, Tarieven!$A$2:$J$150, 10, FALSE), "0") -> 44.45 | T31: =IFERROR(VLOOKUP(S31, Tarieven!$A$2:$J$150, 10, FALSE), "0") -> 0 | W31: =IFERROR(VLOOKUP(V31, Tarieven!$A$2:$J$150, 10, FALSE), "0") -> 0 | X31: =Augustus!X31 -> 11 | Y31: 0 | Z31: =SUM(L31+O31+R31+U31+X31) -> 18 | AA31: =SUM(H31+K31)*E31 -> 75.6 | AB31: =SUM((L31*N31)+(O31*Q31)+(R31*T31)+(U31*W31)+Y31) -> 262.35 | AC31: =SUM(AB31-AA31) -> 186.75
A32: =Rooster!A33 -> Vrijdag | B32: =Rooster!B33 -> 0.70833333 | C32: =Rooster!C33 -> 60 | D32: =Rooster!D33 -> Cheer 12+ | E32: 4 | F32: =Rooster!E33 -> Eigenaar | G32: =IFERROR(VLOOKUP(F32, Docenten!$A$2:$G$30, 7, FALSE), "0") -> 0 | H32: =SUM(G32/60)*C32 -> 0 | I32: =Rooster!H33 -> Santpoort Zuid | J32: =IFERROR(VLOOKUP(I32, Locaties!$A$2:$G$15, 7, FALSE), "0") -> 18.9 | K32: =SUM(J32/60)*C32 -> 18.9 | L32: 2 | M32: Cheer regulier +1 abbo | N32: =IFERROR(VLOOKUP(M32, Tarieven!$A$1:$J$150, 10, FALSE), "0") -> 32.25 | O32: 1 | P32: Cheer regulier +1 | Q32: =IFERROR(VLOOKUP(P32, Tarieven!$A$2:$J$150, 10, FALSE), "0") -> 289.5 | T32: =IFERROR(VLOOKUP(S32, Tarieven!$A$2:$J$150, 10, FALSE), "0") -> 0 | W32: =IFERROR(VLOOKUP(V32, Tarieven!$A$2:$J$150, 10, FALSE), "0") -> 0 | X32: =Augustus!X32 -> 5 | Y32: 0 | Z32: =SUM(L32+O32+R32+U32+X32) -> 8 | AA32: =SUM(H32+K32)*E32 -> 75.6 | AB32: =SUM((L32*N32)+(O32*Q32)+(R32*T32)+(U32*W32)+Y32) -> 354 | AC32: =SUM(AB32-AA32) -> 278.4
A33: =Rooster!A34 -> Vrijdag | B33: =Rooster!B34 -> 0.75 | C33: =Rooster!C34 -> 60 | D33: =Rooster!D34 -> Urban-pop-Show 11+ | E33: 4 | F33: =Rooster!E34 -> Eigenaar | G33: =IFERROR(VLOOKUP(F33, Docenten!$A$2:$G$30, 7, FALSE), "0") -> 0 | H33: =SUM(G33/60)*C33 -> 0 | I33: =Rooster!H34 -> Santpoort Noord | J33: =IFERROR(VLOOKUP(I33, Locaties!$A$2:$G$15, 7, FALSE), "0") -> 14.2 | K33: =SUM(J33/60)*C33 -> 14.2 | L33: 1 | M33: 1x per week abbo | N33: =IFERROR(VLOOKUP(M33, Tarieven!$A$1:$J$150, 10, FALSE), "0") -> 31 | O33: 1 | P33: Cheer regulier +1 | T33: =IFERROR(VLOOKUP(S33, Tarieven!$A$2:$J$150, 10, FALSE), "0") -> 0 | W33: =IFERROR(VLOOKUP(V33, Tarieven!$A$2:$J$150, 10, FALSE), "0") -> 0 | X33: =Augustus!X33 -> 8 | Y33: 0 | Z33: =SUM(L33+O33+R33+U33+X33) -> 10 | AA33: =SUM(H33+K33)*E33 -> 56.8 | AB33: =SUM((L33*N33)+(O33*Q33)+(R33*T33)+(U33*W33)+Y33) -> 31 | AC33: =SUM(AB33-AA33) -> -25.8
A34: =Rooster!A35 -> Zaterdag | B34: =Rooster!B35 -> 0.375 | C34: =Rooster!C35 -> 60 | D34: =Rooster!D35 -> Peuters | E34: 4 | F34: =Rooster!E35 -> Frederique | G34: =IFERROR(VLOOKUP(F34, Docenten!$A$2:$G$30, 7, FALSE), "0") -> 12.5 | H34: =SUM(G34/60)*C34 -> 12.5 | I34: =Rooster!H35 -> Santpoort Noord | J34: =IFERROR(VLOOKUP(I34, Locaties!$A$2:$G$15, 7, FALSE), "0") -> 14.2 | K34: =SUM(J34/60)*C34 -> 14.2 | L34: 9 | M34: 1x per week abbo | N34: =IFERROR(VLOOKUP(M34, Tarieven!$A$1:$J$150, 10, FALSE), "0") -> 31 | P34: =Augustus!P34 | Q34: =IFERROR(VLOOKUP(P34, Tarieven!$A$2:$J$150, 10, FALSE), "0") -> 0 | T34: =IFERROR(VLOOKUP(S34, Tarieven!$A$2:$J$150, 10, FALSE), "0") -> 0 | W34: =IFERROR(VLOOKUP(V34, Tarieven!$A$2:$J$150, 10, FALSE), "0") -> 0 | X34: =Augustus!X34 -> 4 | Y34: 0 | Z34: =SUM(L34+O34+R34+U34+X34) -> 13 | AA34: =SUM(H34+K34)*E34 -> 106.8 | AB34: =SUM((L34*N34)+(O34*Q34)+(R34*T34)+(U34*W34)+Y34) -> 279 | AC34: =SUM(AB34-AA34) -> 172.2
A35: =Rooster!A36 -> Zaterdag | B35: =Rooster!B36 -> 0.40625 | C35: =Rooster!C36 -> 60 | D35: =Rooster!D36 -> Kleuters | E35: 4 | F35: =Rooster!E36 -> Frederique | G35: =IFERROR(VLOOKUP(F35, Docenten!$A$2:$G$30, 7, FALSE), "0") -> 12.5 | H35: =SUM(G35/60)*C35 -> 12.5 | I35: =Rooster!H36 -> Santpoort Noord | J35: =IFERROR(VLOOKUP(I35, Locaties!$A$2:$G$15, 7, FALSE), "0") -> 14.2 | K35: =SUM(J35/60)*C35 -> 14.2 | L35: 10 | M35: 1x per week abbo | N35: =IFERROR(VLOOKUP(M35, Tarieven!$A$1:$J$150, 10, FALSE), "0") -> 31 | P35: =Augustus!P35 | T35: =IFERROR(VLOOKUP(S35, Tarieven!$A$2:$J$150, 10, FALSE), "0") -> 0 | W35: =IFERROR(VLOOKUP(V35, Tarieven!$A$2:$J$150, 10, FALSE), "0") -> 0 | X35: =Augustus!X35 -> 5 | Y35: 0 | Z35: =SUM(L35+O35+R35+U35+X35) -> 15 | AA35: =SUM(H35+K35)*E35 -> 106.8 | AB35: =SUM((L35*N35)+(O35*Q35)+(R35*T35)+(U35*W35)+Y35) -> 310 | AC35: =SUM(AB35-AA35) -> 203.2
A36: =Rooster!A37 -> Zaterdag | B36: =Rooster!B37 -> 0.4375 | C36: =Rooster!C37 -> 60 | D36: =Rooster!D37 -> Showdance 5-6 | E36: 4 | F36: =Rooster!E37 -> Frederique | G36: =IFERROR(VLOOKUP(F36, Docenten!$A$2:$G$30, 7, FALSE), "0") -> 12.5 | H36: =SUM(G36/60)*C36 -> 12.5 | I36: =Rooster!H37 -> Santpoort Noord | J36: =IFERROR(VLOOKUP(I36, Locaties!$A$2:$G$15, 7, FALSE), "0") -> 14.2 | K36: =SUM(J36/60)*C36 -> 14.2 | L36: 3 | M36: 1x per week abbo | N36: =IFERROR(VLOOKUP(M36, Tarieven!$A$1:$J$150, 10, FALSE), "0") -> 31 | O36: 1 | P36: 2x per week abbo | Q36: =IFERROR(VLOOKUP(P36, Tarieven!$A$2:$J$150, 10, FALSE), "0") -> 28.55 | T36: =IFERROR(VLOOKUP(S36, Tarieven!$A$2:$J$150, 10, FALSE), "0") -> 0 | W36: =IFERROR(VLOOKUP(V36, Tarieven!$A$2:$J$150, 10, FALSE), "0") -> 0 | X36: =Augustus!X36 -> 9 | Y36: 0 | Z36: =SUM(L36+O36+R36+U36+X36) -> 13 | AA36: =SUM(H36+K36)*E36 -> 106.8 | AB36: =SUM((L36*N36)+(O36*Q36)+(R36*T36)+(U36*W36)+Y36) -> 121.55 | AC36: =SUM(AB36-AA36) -> 14.75
A37: =Rooster!A38 -> Zaterdag | B37: =Rooster!B38 -> 0.47916667 | C37: =Rooster!C38 -> 60 | D37: =Rooster!D38 -> Showdance 7+ | E37: 4 | F37: =Rooster!E38 -> Frederique | G37: =IFERROR(VLOOKUP(F37, Docenten!$A$2:$G$30, 7, FALSE), "0") -> 12.5 | H37: =SUM(G37/60)*C37 -> 12.5 | I37: =Rooster!H38 -> Santpoort Noord | J37: =IFERROR(VLOOKUP(I37, Locaties!$A$2:$G$15, 7, FALSE), "0") -> 14.2 | K37: =SUM(J37/60)*C37 -> 14.2 | L37: 3 | M37: 1x per week abbo | N37: =IFERROR(VLOOKUP(M37, Tarieven!$A$1:$J$150, 10, FALSE), "0") -> 31 | P37: =Augustus!P37 | Q37: =IFERROR(VLOOKUP(P37, Tarieven!$A$2:$J$150, 10, FALSE), "0") -> 0 | T37: =IFERROR(VLOOKUP(S37, Tarieven!$A$2:$J$150, 10, FALSE), "0") -> 0 | W37: =IFERROR(VLOOKUP(V37, Tarieven!$A$2:$J$150, 10, FALSE), "0") -> 0 | X37: =Augustus!X37 -> 4 | Y37: 0 | Z37: =SUM(L37+O37+R37+U37+X37) -> 7 | AA37: =SUM(H37+K37)*E37 -> 106.8 | AB37: =SUM((L37*N37)+(O37*Q37)+(R37*T37)+(U37*W37)+Y37) -> 93 | AC37: =SUM(AB37-AA37) -> -13.8
A38: =Rooster!A39 -> Zaterdag | B38: =Rooster!B39 -> 0.41666667 | C38: =Rooster!C39 -> 60 | D38: =Rooster!D39 -> Peuters | F38: =Rooster!E39 -> Tess | G38: =IFERROR(VLOOKUP(F38, Docenten!$A$2:$G$30, 7, FALSE), "0") -> 17.5 | H38: =SUM(G38/60)*C38 -> 17.5 | I38: =Rooster!H39 -> Santpoort Zuid | J38: =IFERROR(VLOOKUP(I38, Locaties!$A$2:$G$15, 7, FALSE), "0") -> 18.9 | K38: =SUM(J38/60)*C38 -> 18.9 | N38: =IFERROR(VLOOKUP(M38, Tarieven!$A$1:$J$150, 10, FALSE), "0") -> 0 | P38: =Augustus!P38 | Q38: =IFERROR(VLOOKUP(P38, Tarieven!$A$2:$J$150, 10, FALSE), "0") -> 0 | T38: =IFERROR(VLOOKUP(S38, Tarieven!$A$2:$J$150, 10, FALSE), "0") -> 0 | W38: =IFERROR(VLOOKUP(V38, Tarieven!$A$2:$J$150, 10, FALSE), "0") -> 0 | X38: =Augustus!X38 -> 0 | Y38: 0 | Z38: =SUM(L38+O38+R38+U38+X38) -> 0 | AA38: =SUM(H38+K38)*E38 -> 0 | AB38: =SUM((L38*N38)+(O38*Q38)+(R38*T38)+(U38*W38)+Y38) -> 0 | AC38: =SUM(AB38-AA38) -> 0
A39: =Rooster!A40 -> Zaterdag | B39: =Rooster!B40 -> 0.44791667 | C39: =Rooster!C40 -> 60 | D39: =Rooster!D40 -> Kleuters | F39: =Rooster!E40 -> Tess | G39: =IFERROR(VLOOKUP(F39, Docenten!$A$2:$G$30, 7, FALSE), "0") -> 17.5 | H39: =SUM(G39/60)*C39 -> 17.5 | I39: =Rooster!H40 -> Santpoort Zuid | J39: =IFERROR(VLOOKUP(I39, Locaties!$A$2:$G$15, 7, FALSE), "0") -> 18.9 | K39: =SUM(J39/60)*C39 -> 18.9 | N39: =IFERROR(VLOOKUP(M39, Tarieven!$A$1:$J$150, 10, FALSE), "0") -> 0 | P39: =Augustus!P39 | Q39: =IFERROR(VLOOKUP(P39, Tarieven!$A$2:$J$150, 10, FALSE), "0") -> 0 | S39: =Augustus!S39 | T39: =IFERROR(VLOOKUP(S39, Tarieven!$A$2:$J$150, 10, FALSE), "0") -> 0 | W39: =IFERROR(VLOOKUP(V39, Tarieven!$A$2:$J$150, 10, FALSE), "0") -> 0 | X39: =Augustus!X39 -> 0 | Y39: 0 | Z39: =SUM(L39+O39+R39+U39+X39) -> 0 | AA39: =SUM(H39+K39)*E39 -> 0 | AB39: =SUM((L39*N39)+(O39*Q39)+(R39*T39)+(U39*W39)+Y39) -> 0 | AC39: =SUM(AB39-AA39) -> 0
A40: =Rooster!A41 | B40: =Rooster!B41 | C40: =Rooster!C41 | D40: =Rooster!D41 | F40: =Rooster!E41 | G40: =IFERROR(VLOOKUP(F40, Docenten!$A$2:$G$30, 7, FALSE), "0") -> 0 | H40: =SUM(G40/60)*C40 -> 0 | I40: =Rooster!H41 | J40: =IFERROR(VLOOKUP(I40, Locaties!$A$2:$G$15, 7, FALSE), "0") -> 0 | K40: =SUM(J40/60)*C40 -> 0 | N40: =IFERROR(VLOOKUP(M40, Tarieven!$A$1:$J$150, 10, FALSE), "0") -> 0 | Q40: =IFERROR(VLOOKUP(P40, Tarieven!$A$2:$J$150, 10, FALSE), "0") -> 0 | S40: =Augustus!S40 | T40: =IFERROR(VLOOKUP(S40, Tarieven!$A$2:$J$150, 10, FALSE), "0") -> 0 | W40: =IFERROR(VLOOKUP(V40, Tarieven!$A$2:$J$150, 10, FALSE), "0") -> 0 | X40: =Augustus!X40 -> 0 | Y40: 0 | Z40: =SUM(L40+O40+R40+U40+X40) -> 0 | AA40: =SUM(H40+K40)*E40 -> 0 | AB40: =SUM((L40*N40)+(O40*Q40)+(R40*T40)+(U40*W40)+Y40) -> 0 | AC40: =SUM(AB40-AA40) -> 0
A41: =Rooster!A42 | B41: =Rooster!B42 | C41: =Rooster!C42 | D41: =Rooster!D42 | F41: =Rooster!E42 | G41: =IFERROR(VLOOKUP(F41, Docenten!$A$2:$G$30, 7, FALSE), "0") -> 0 | H41: =SUM(G41/60)*C41 -> 0 | I41: =Rooster!H42 | J41: =IFERROR(VLOOKUP(I41, Locaties!$A$2:$G$15, 7, FALSE), "0") -> 0 | K41: =SUM(J41/60)*C41 -> 0 | N41: =IFERROR(VLOOKUP(M41, Tarieven!$A$1:$J$150, 10, FALSE), "0") -> 0 | P41: =Augustus!P41 | Q41: =IFERROR(VLOOKUP(P41, Tarieven!$A$2:$J$150, 10, FALSE), "0") -> 0 | S41: =Augustus!S41 | T41: =IFERROR(VLOOKUP(S41, Tarieven!$A$2:$J$150, 10, FALSE), "0") -> 0 | W41: =IFERROR(VLOOKUP(V41, Tarieven!$A$2:$J$150, 10, FALSE), "0") -> 0 | X41: =Augustus!X41 -> 0 | Y41: 0 | Z41: =SUM(L41+O41+R41+U41+X41) -> 0 | AA41: =SUM(H41+K41)*E41 -> 0 | AB41: =SUM((L41*N41)+(O41*Q41)+(R41*T41)+(U41*W41)+Y41) -> 0 | AC41: =SUM(AB41-AA41) -> 0
A42: =Rooster!A43 -> Maandag | B42: =Rooster!B43 -> 0.39583333 | C42: =Rooster!C43 -> 60 | D42: =Rooster!D43 -> Kinderopvang | G42: =IFERROR(VLOOKUP(F42, Docenten!$A$2:$G$30, 7, FALSE), "0") -> 0 | H42: =SUM(G42/60)*C42 -> 0 | I42: =Rooster!H43 | J42: =IFERROR(VLOOKUP(I42, Locaties!$A$2:$G$15, 7, FALSE), "0") -> 0 | K42: =SUM(J42/60)*C42 -> 0 | P42: =Augustus!P42 | Q42: =IFERROR(VLOOKUP(P42, Tarieven!$A$2:$J$150, 10, FALSE), "0") -> 0 | S42: =Augustus!S42 | T42: =IFERROR(VLOOKUP(S42, Tarieven!$A$2:$J$150, 10, FALSE), "0") -> 0 | W42: =IFERROR(VLOOKUP(V42, Tarieven!$A$2:$J$150, 10, FALSE), "0") -> 0 | X42: =Augustus!X42 -> 0 | Y42: 0 | Z42: =SUM(L42+O42+R42+U42+X42) -> 0 | AA42: =SUM(H42+K42)*E42 -> 0 | AB42: =SUM((L42*N42)+(O42*Q42)+(R42*T42)+(U42*W42)+Y42) -> 0 | AC42: =SUM(AB42-AA42) -> 0
A43: =Rooster!A44 -> Vrijdag | B43: =Rooster!B44 -> 0.79166667 | C43: 60 | D43: =Rooster!D44 -> Prive training | J43: =IFERROR(VLOOKUP(I43, Locaties!$A$2:$G$15, 7, FALSE), "0") -> 0 | K43: =SUM(J43/60)*C43 -> 0 | N43: =IFERROR(VLOOKUP(M43, Tarieven!$A$1:$J$150, 10, FALSE), "0") -> 0 | P43: =Augustus!P43 | Q43: =IFERROR(VLOOKUP(P43, Tarieven!$A$2:$J$150, 10, FALSE), "0") -> 0 | S43: =Augustus!S43 | T43: =IFERROR(VLOOKUP(S43, Tarieven!$A$2:$J$150, 10, FALSE), "0") -> 0 | W43: =IFERROR(VLOOKUP(V43, Tarieven!$A$2:$J$150, 10, FALSE), "0") -> 0 | X43: =Augustus!X43 -> 0 | Y43: 0 | Z43: =SUM(L43+O43+R43+U43+X43) -> 0 | AA43: =SUM(H43+K43)*E43 -> 0 | AB43: =SUM((L43*N43)+(O43*Q43)+(R43*T43)+(U43*W43)+Y43) -> 0 | AC43: =SUM(AB43-AA43) -> 0
A44: =Rooster!A45 -> Zaterdag | B44: =Rooster!B45 -> 0.5625 | C44: 60 | D44: =Rooster!D45 -> Prive training | J44: =IFERROR(VLOOKUP(I44, Locaties!$A$2:$G$15, 7, FALSE), "0") -> 0 | K44: =SUM(J44/60)*C44 -> 0 | N44: =IFERROR(VLOOKUP(M44, Tarieven!$A$1:$J$150, 10, FALSE), "0") -> 0 | Q44: =IFERROR(VLOOKUP(P44, Tarieven!$A$2:$J$150, 10, FALSE), "0") -> 0 | S44: =Augustus!S44 | T44: =IFERROR(VLOOKUP(S44, Tarieven!$A$2:$J$150, 10, FALSE), "0") -> 0 | W44: =IFERROR(VLOOKUP(V44, Tarieven!$A$2:$J$150, 10, FALSE), "0") -> 0 | X44: =Augustus!X44 -> 0 | Y44: 0 | Z44: =SUM(L44+O44+R44+U44+X44) -> 0 | AA44: =SUM(H44+K44)*E44 -> 0 | AB44: =SUM((L44*N44)+(O44*Q44)+(R44*T44)+(U44*W44)+Y44) -> 0 | AC44: =SUM(AB44-AA44) -> 0
A45: =Rooster!A46 | B45: =Rooster!B46 | C45: =Rooster!C46 | D45: =Rooster!D46 | F45: =Rooster!E46 | G45: =IFERROR(VLOOKUP(F45, Docenten!$A$2:$G$30, 7, FALSE), "0") -> 0 | H45: =SUM(G45/60)*C45 -> 0 | I45: =Rooster!H46 | J45: =IFERROR(VLOOKUP(I45, Locaties!$A$2:$G$15, 7, FALSE), "0") -> 0 | K45: =SUM(J45/60)*C45 -> 0 | N45: =IFERROR(VLOOKUP(M45, Tarieven!$A$1:$J$150, 10, FALSE), "0") -> 0 | Q45: =IFERROR(VLOOKUP(P45, Tarieven!$A$2:$J$150, 10, FALSE), "0") -> 0 | S45: =Augustus!S45 | T45: =IFERROR(VLOOKUP(S45, Tarieven!$A$2:$J$150, 10, FALSE), "0") -> 0 | W45: =IFERROR(VLOOKUP(V45, Tarieven!$A$2:$J$150, 10, FALSE), "0") -> 0 | X45: =Augustus!X45 -> 0 | Y45: 0 | Z45: =SUM(L45+O45+R45+U45+X45) -> 0 | AA45: =SUM(H45+K45)*E45 -> 0 | AB45: =SUM((L45*N45)+(O45*Q45)+(R45*T45)+(U45*W45)+Y45) -> 0 | AC45: =SUM(AB45-AA45) -> 0
